Workbook

Sheet Свод
A1: ИД мероприятия | B1: ИД значения результата | C1: Наименование мероприятия | D1: Описательная часть характеристики | E1: Подпись план | F1: Подпись факт | G1: Подпись подтверждение | H1: Корректно по предыдущему статусу ЦПМ | I1: Прошлый статус | J1: Прошлый анализ | K1: ЦПМ корректность статуса ИИ | L1: ЦПМ корректность анализа ИИ | M1: ЦПМ Полный комментарий | N1: Характеристика план | O1: Характеристика факт | P1: Характеристика подтверждение | Q1: Корректно по предыдущему статусу ЦПМ | R1: Прошлый статус | S1: Прошлый анализ | T1: ЦПМ корректность статуса ИИ | U1: ЦПМ корректность анализа ИИ | V1: ЦПМ Полный комментарий | W1: ПХР план | X1: ПХР факт | Y1: ПХР подтверждение | Z1: Корректно по предыдущему статусу ЦПМ | AA1: Прошлый статус | AB1: Прошлый анализ | AC1: ЦПМ корректность статуса ИИ | AD1: ЦПМ корректность анализа ИИ | AE1: ЦПМ Полный комментарий | AF1: Результат план | AG1: Результат единица | AH1: Результат факт | AI1: Результат подтверждение | AJ1: Корректно по предыдущему статусу ЦПМ | AK1: Прошлый статус | AL1: Прошлый анализ | AM1: ЦПМ корректность статуса ИИ | AN1: ЦПМ корректность анализа ИИ | AO1: ЦПМ Полный комментарий
A2: 9351223676 | B2: 9351225755 | C2: Переведены сведения, содержащиеся в реестре требований, в машиночитаемый и машинопонимаемый формат | D2: Выполнены работы по переводу сведений, содержащихся в реестре требований, подлежащих применению при выполнении инженерных изысканий, осуществлении архитектурно-строительного проектирования, проведении экспертизы проектной документации и (или) экспертизы результатов инженерных изысканий, строительстве, реконструкции, капитальном ремонте, эксплуатации и сносе объектов капитального строительства, в машиночитаемый и машинопонимаемый формат и переработке нормативных требований в принципиально новой форме логических условий, возможной для интерпретации компьютерной техники, и детального перевода всего документа в код, пригодный для использования компьютером без предварительной обработки. | E2: =VLOOKUP(B2,Подпись!$A$1:$E$100,5,0) -> Музыченко Сергей Григорьевич - Заместитель Министра, Файзуллин Ирек Энварович, Ломакин Александр Николаевич, Муценек Юрий Петрович, Стасишин Никита Евгеньевич, Гордеев Юрий Сергеевич, Музыченко Сергей Григорьевич, Михайлик Константин Александрович, Ересько Алексей Васильевич, Леонов Валерий Владимирович, Хусаинов Алмаз Шаукатович | F2: =VLOOKUP(B2,Подпись!$A$1:$E$100,2,0) -> Михайлик Константин Александрович | G2: Подтверждено | H2: {=_xlfn.IFS(AND(G2=I2,K2="нет"),"нет",AND(G2=I2,K2="да"),"да",AND(G2<>I2,K2="нет"),"да",AND(G2<>I2,K2="да"),"нет")} -> нет | I2: =VLOOKUP(B2,'Старый ИИ'!A:AQ,3,FALSE) -> Не подтверждено | J2: =VLOOKUP(B2,'Старый ИИ'!A:AQ,5,FALSE) -> Ошибка анализа: ошибка анализа | K2: =VLOOKUP(B2,'Старый ИИ'!A:AQ,6,FALSE) -> да | L2: =VLOOKUP(B2,'Старый ИИ'!A:AQ,7,FALSE) -> нет | M2: =VLOOKUP(B2,'Старый ИИ'!A:AQ,8,FALSE) -> ИИ корректно не принимает мероприятие - так как в документах стоит подпись не ответственного исполнителя, но в обосновании пишет о технической ошибке. Нет корректного обоснования какие подписи найдены. | N2: Выполнены работы по переводу сведений, содержащихся в реестре требований, подлежащих применению при выполнении инженерных изысканий, осуществлении архитектурно-строительного проектирования, проведении экспертизы проектной документации и (или) экспертизы результатов инженерных изысканий, строительстве, реконструкции, капитальном ремонте, эксплуатации и сносе объектов капитального строительства, в машиночитаемый и машинопонимаемый формат и переработке нормативных требований в принципиально новой форме логических условий, возможной для интерпретации компьютерной техники, и детального перевода всего документа в код, пригодный для использования компьютером без предварительной обработки. | O2: =VLOOKUP(A2,Характеристика!$A$1:$D$100,2,0) -> Подтверждающие сведения 1.pdf - Документ описывает подготовку нормативных и технических требований в машиночитаемом и машинопонимаемом форматах (XML). Это напрямую соответствует цели события по переводу сведений из реестра требований в машиночитаемый формат. Упоминается апробация требований в специализированном ПО, что подтверждает выполнение работ. Подтверждающие сведения 2.pdf - Документ подтверждает достижение показателя федерального проекта по созданию подсистем для перевода Реестра требований в машиночитаемый и машинопонимаемый форматы. Это напрямую соответствует цели события, описанного как перевод сведений из реестра требований в машиночитаемый формат. Упоминание о готовности функционала подсистемы «Реестр требований» подтверждает выполнение работ. | P2: =VLOOKUP(A2,Характеристика!$A$1:$D$100,4,0) -> Подтверждено | Q2: {=_xlfn.IFS(AND(P2=R2,T2="нет"),"нет",AND(P2=R2,T2="да"),"да",AND(P2<>R2,T2="нет"),"да",AND(P2<>R2,T2="да"),"нет")} -> да | R2: =VLOOKUP(B2,'Старый ИИ'!A:AQ,9,FALSE) -> Подтверждено | S2: =VLOOKUP(B2,'Старый ИИ'!A:AQ,11,FALSE) -> Отчет подтверждает выполнение мероприятия: на странице 1 указано достижение результата «Перевод Реестра требований в машиночитаемый и машинопонимаемый форматы» (1 штука). На странице 3 и 4 описаны испытания и готовность подсистемы «Реестр требований» к ввод‑у в опытную эксплуатацию, что свидетельствует о завершённом переводе данных в требуемый формат. | T2: =VLOOKUP(B2,'Старый ИИ'!A:AQ,12,FALSE) -> да | U2: =VLOOKUP(B2,'Старый ИИ'!A:AQ,13,FALSE) -> да | V2: =VLOOKUP(B2,'Старый ИИ'!A:AQ,14,FALSE) -> - | W2: =VLOOKUP(B2,'ПХР актуальный'!$A$1:$C$34,3,0) -> #NUM! | X2: =VLOOKUP(B2,'Результат и ПХР'!$A$1:$Q$992,14,0) -> Проверка опиралась на summary документа "Подтверждающие сведения 1.pdf". В выбранном evidence для метрики "Количество созданных и/или развиваемых подсистем в целях перевода Реестра требований в машиночитаемый и машинопонимаемый форматы" установлено, что характеристика объекта не подтверждена явно; количество не привязано к объекту метрики. Имеющийся фрагмент "100 требований в формате XML подготовлены и успешно апробированы в специализированном ПО" не дает прямого подтверждения выполнения. По правилу fail-closed статус ПХР установлен как "не подтверждено". | Y2: =VLOOKUP(B2,'Результат и ПХР'!$A$1:$Q$992,7,0) -> не подтверждено | Z2: {=_xlfn.IFS(AND(Y2=AA2,AC2="нет"),"нет",AND(Y2=AA2,AC2="да"),"да",AND(Y2<>AA2,AC2="нет"),"да",AND(Y2<>AA2,AC2="да"),"нет")} -> нет | AA2: =VLOOKUP(B2,'Старый ИИ'!A:AQ,21,FALSE) -> Подтверждено | AB2: =VLOOKUP(B2,'Старый ИИ'!A:AQ,23,FALSE) -> Отчет подтверждает выполнение мероприятия: в пункте «19.12.2025 ФАУ «ФЦС» принял результат… – 100 нормативных требований переведены в машиночитаемый и машинопонимаемый XML‑формат и соответствуют методическому пособию (стр. 2). Плановое значение – перевод не менее 100 требований, также указано, что к 30.12.2025 будет размещено 100 требований в подсистеме «Реестр требований» (стр. 3). Таким образом, цель мероприятия полностью достигнута. | AC2: =VLOOKUP(B2,'Старый ИИ'!A:AQ,24,FALSE) -> да | AD2: =VLOOKUP(B2,'Старый ИИ'!A:AQ,25,FALSE) -> нет | AE2: =VLOOKUP(B2,'Старый ИИ'!A:AQ,26,FALSE) -> Корректно по статусу, но некорректно по анализируемой информации по ПХР, она не ровна нулю. | AF2: =VLOOKUP(B2,Общий!$E$2:$O$2000,10,0) -> 0 | AG2: =VLOOKUP(B2,Общий!$E$2:$O$2000,11,0) -> Единица | AH2: =VLOOKUP(B2,'Результат и ПХР'!$A$1:$M$992,13,0) -> Основой вывода выбран summary документа "Подтверждающие сведения 2.pdf". В evidence найдены действие "Переведены сведения", объект "содержащиеся в реестре требований, в машиночитаемый и машинопонимаемый формат" и прямой сигнал выполнения "подтверждающий готовность". Ключевой фрагмент evidence: "К письму прилагается акт от 10.12.2025, подтверждающий готовность доработанного функционала подсистемы «Реестр требований» и открытой части подсистемы «Официальный сайт» в составе ЕГИС «Стройкомплекс.РФ» к вводу в опытную эксплуатацию по результатам предварительных испытаний.". Этого достаточно для качественного подтверждения, поэтому статус мероприятия установлен как "подтверждено". | AI2: =VLOOKUP(B2,'Результат и ПХР'!$A$1:$T$992,6,0) -> подтверждено | AJ2: да | AK2: =VLOOKUP(B2,'Старый ИИ'!A:AQ,27,FALSE) -> Подтверждено | AL2: =VLOOKUP(B2,'Старый ИИ'!A:AQ,29,FALSE) -> В отчете указано, что результат достигнут в количестве 1 штука, что соответствует заявленному количеству единиц (1) мероприятия. Плановое значение в данных мероприятия указано как None, поэтому полное соответствие невозможно оценить полностью. | AM2: =VLOOKUP(B2,'Старый ИИ'!A:AQ,30,FALSE) -> да | AN2: =VLOOKUP(B2,'Старый ИИ'!A:AQ,31,FALSE) -> да | AO2: =VLOOKUP(B2,'Старый ИИ'!A:AQ,32,FALSE) -> -
A3: 9351224712 | B3: 9351225752 | C3: Организованы и проведены профориентационные образовательные отраслевые форумы для школьников, студентов и педагогов общеобразовательных организаций, колледжей и высших учебных заведений, и представителей крупнейших отраслевых компаний. | D3: Обеспечено взаимодействие студентов, педагогов и представителей отраслевых компаний, способствующее повышению компетенций молодежи, развитию и популяризации строительных профессий через практическое вовлечение, профориентацию и обмен опытом | E3: =VLOOKUP(B3,Подпись!$A$1:$E$100,5,0) -> #N/A | F3: =VLOOKUP(B3,Подпись!$A$1:$E$100,2,0) -> #N/A | G3: #N/A | H3: {=_xlfn.IFS(AND(G3=I3,K3="нет"),"нет",AND(G3=I3,K3="да"),"да",AND(G3<>I3,K3="нет"),"да",AND(G3<>I3,K3="да"),"нет")} -> #N/A | I3: =VLOOKUP(B3,'Старый ИИ'!A:AQ,3,FALSE) -> Не подтверждено | J3: =VLOOKUP(B3,'Старый ИИ'!A:AQ,5,FALSE) -> Найдены подписи: Бигава ГД, но они не совпадают с ответственными лицами | K3: =VLOOKUP(B3,'Старый ИИ'!A:AQ,6,FALSE) -> да | L3: =VLOOKUP(B3,'Старый ИИ'!A:AQ,7,FALSE) -> да | M3: =VLOOKUP(B3,'Старый ИИ'!A:AQ,8,FALSE) -> - | N3: Обеспечено взаимодействие студентов, педагогов и представителей отраслевых компаний, способствующее повышению компетенций молодежи, развитию и популяризации строительных профессий через практическое вовлечение, профориентацию и обмен опытом | O3: =VLOOKUP(A3,Характеристика!$A$1:$D$100,2,0) -> Подтверждающие сведения 1.pdf - Документ описывает проведение серии региональных форумов «Молодой специалист — строитель будущего». Эти форумы были направлены на повышение престижа строительных профессий и развитие ранней профориентации. Участие в мероприятиях включали школьников, студентов и представителей компаний-работодателей, что соответствует цели события. | P3: =VLOOKUP(A3,Характеристика!$A$1:$D$100,4,0) -> Подтверждено | Q3: {=_xlfn.IFS(AND(P3=R3,T3="нет"),"нет",AND(P3=R3,T3="да"),"да",AND(P3<>R3,T3="нет"),"да",AND(P3<>R3,T3="да"),"нет")} -> да | R3: =VLOOKUP(B3,'Старый ИИ'!A:AQ,9,FALSE) -> Подтверждено | S3: =VLOOKUP(B3,'Старый ИИ'!A:AQ,11,FALSE) -> Отчет подробно подтверждает проведение профориентционных отраслевых форумов для школьников, студентов, педагогов и представителей компаний: в разделе "Итоговый отчет о проведенных форумах" (стр. 3‑4) указано 14 форумов с более 12 000 участниками, в том числе 8 000+ студентов, 2 650+ школьников, 440 преподавателей и 360 представителей работодателей. Программа форумов (стр. 5) включает профориентационный трек для школьников, образовательный блок для студентов, секции для педагогов и формат для работодателей. Дополнительные результаты доступны по ссылке: https://prof.roskapstroy.ru/mery-podderzhki/rezultaty-issledovaniya/. | T3: =VLOOKUP(B3,'Старый ИИ'!A:AQ,12,FALSE) -> да | U3: =VLOOKUP(B3,'Старый ИИ'!A:AQ,13,FALSE) -> да | V3: =VLOOKUP(B3,'Старый ИИ'!A:AQ,14,FALSE) -> - | W3: =VLOOKUP(B3,'ПХР актуальный'!$A$1:$C$34,3,0) -> #NUM! | X3: =VLOOKUP(B3,'Результат и ПХР'!$A$1:$Q$992,14,0) -> Основой вывода выбран summary документа "Подтверждающие сведения 1.pdf". В evidence явно подтверждены метрика "Количество участников форумов", требуемая характеристика объекта и привязка количества к самому объекту метрики; зафиксировано значение 12000 человек. Ключевой фрагмент evidence: "В мероприятиях приняли участие более 12 000 человек, включая более 8 000 студентов, свыше 2 650 школьников, 440 преподавателей и 360 представителей компаний-работодателей.". Поэтому строгие правила ПХР выполнены, и итоговый статус установлен как "подтверждено". | Y3: =VLOOKUP(B3,'Результат и ПХР'!$A$1:$Q$992,7,0) -> подтверждено | Z3: {=_xlfn.IFS(AND(Y3=AA3,AC3="нет"),"нет",AND(Y3=AA3,AC3="да"),"да",AND(Y3<>AA3,AC3="нет"),"да",AND(Y3<>AA3,AC3="да"),"нет")} -> да | AA3: =VLOOKUP(B3,'Старый ИИ'!A:AQ,21,FALSE) -> Подтверждено | AB3: =VLOOKUP(B3,'Старый ИИ'!A:AQ,23,FALSE) -> Отчет детально подтверждает проведение профориентационных отраслевых форумов: на 14 форумах в 2025 г. (стр. 3‑4) приняло участие более 12 000 человек, включая >2 600 школьников, >8 000 студентов и 440 преподавателей, а также представителей компаний. Описаны конкретные города, количество участников и содержание программ (стр. 4‑5). Всё это полностью соответствует заявленному мероприятию. | AC3: =VLOOKUP(B3,'Старый ИИ'!A:AQ,24,FALSE) -> да | AD3: =VLOOKUP(B3,'Старый ИИ'!A:AQ,25,FALSE) -> нет | AE3: =VLOOKUP(B3,'Старый ИИ'!A:AQ,26,FALSE) -> Корректно по статусу, но некорректно по анализируемой информации по ПХР, она не ровна нулю | AF3: =VLOOKUP(B3,Общий!$E$2:$O$2000,10,0) -> 0 | AG3: =VLOOKUP(B3,Общий!$E$2:$O$2000,11,0) -> Единица | AH3: =VLOOKUP(B3,'Результат и ПХР'!$A$1:$M$992,13,0) -> Основой вывода выбран summary документа "Подтверждающие сведения 1.pdf". В evidence найдены действие "Организованы и проведены профориентационные образовательные отраслевые форумы для школьников", объект "студентов и педагогов общеобразовательных организаций, колледжей и высших учебных заведений, и представителей крупнейших отраслевых компаний." и прямой сигнал выполнения "итоговый отчет о проведении". Ключевой фрагмент evidence: "ФАУ «РосКапСтрой» представило в Минстрой России итоговый отчет о проведении в 2025 году серии региональных форумов «Молодой специалист — строитель будущего».". Этого достаточно для качественного подтверждения, поэтому статус мероприятия установлен как "подтверждено". | AI3: =VLOOKUP(B3,'Результат и ПХР'!$A$1:$T$992,6,0) -> подтверждено | AJ3: да | AK3: =VLOOKUP(B3,'Старый ИИ'!A:AQ,27,FALSE) -> Подтверждено | AL3: =VLOOKUP(B3,'Старый ИИ'!A:AQ,29,FALSE) -> Отчет подтверждает проведение 14 региональных форумов в 2025 г., соответствуя заявленной цели организации профориентационных мероприятий (см. раздел «Итоговый отчет…»). Подтверждение доступно в тексте и на сайте https://prof.roskapstroy.ru/mery-podderzhki/rezultaty-issledovaniya/. | AM3: =VLOOKUP(B3,'Старый ИИ'!A:AQ,30,FALSE) -> да | AN3: =VLOOKUP(B3,'Старый ИИ'!A:AQ,31,FALSE) -> нет | AO3: =VLOOKUP(B3,'Старый ИИ'!A:AQ,32,FALSE) -> Некорректно предоставлена информация ИИ в качестве планового значения - 0. В анализе ИИ пишет о корректном выполнении - 14.
A4: 9351223679 | B4: 9351224715 | C4: Обеспечено развитие подсистемы реестр документов и калькулятор мероприятий в системе "Стройкомплекс.РФ" | D4: Соотнесение сведений, содержащихся в реестре документов, сведений, материалов, согласований, предусмотренных нормативными правовыми актами Российской Федерации и необходимых застройщику, техническому заказчику для выполнения мероприятий при реализации проекта по строительству объекта капитального строительства с действующим нормативным правовым регулированием, а также доработка схем в калькуляторе реализации мероприятий, осуществляемых при реализации проектов по строительству объектов капитального строительства, направленных на расчет сроков реализации проектов по строительству ОКС применительно к конкретным ОКС | E4: =VLOOKUP(B4,Подпись!$A$1:$E$100,5,0) -> #N/A | F4: =VLOOKUP(B4,Подпись!$A$1:$E$100,2,0) -> #N/A | G4: #N/A | H4: {=_xlfn.IFS(AND(G4=I4,K4="нет"),"нет",AND(G4=I4,K4="да"),"да",AND(G4<>I4,K4="нет"),"да",AND(G4<>I4,K4="да"),"нет")} -> #N/A | I4: =VLOOKUP(B4,'Старый ИИ'!A:AQ,3,FALSE) -> Не подтверждено | J4: =VLOOKUP(B4,'Старый ИИ'!A:AQ,5,FALSE) -> Найдены подписи: Минстрой Р.З., Уважаемая О.А., В.Н. Медведев, но они не совпадают с ответственными лицами | K4: =VLOOKUP(B4,'Старый ИИ'!A:AQ,6,FALSE) -> да | L4: =VLOOKUP(B4,'Старый ИИ'!A:AQ,7,FALSE) -> да | M4: =VLOOKUP(B4,'Старый ИИ'!A:AQ,8,FALSE) -> - | N4: Соотнесение сведений, содержащихся в реестре документов, сведений, материалов, согласований, предусмотренных нормативными правовыми актами Российской Федерации и необходимых застройщику, техническому заказчику для выполнения мероприятий при реализации проекта по строительству объекта капитального строительства с действующим нормативным правовым регулированием, а также доработка схем в калькуляторе реализации мероприятий, осуществляемых при реализации проектов по строительству объектов капитального строительства, направленных на расчет сроков реализации проектов по строительству ОКС применительно к конкретным ОКС | O4: =VLOOKUP(A4,Характеристика!$A$1:$D$100,2,0) -> Подтверждающие сведения 1.pdf - Документ напрямую касается калькулятора реализации мероприятий в системе «Стройкомплекс.РФ». Упоминается количество схем в этом калькуляторе, что соответствует части описания события. Это подтверждает развитие и работу указанной подсистемы. | P4: =VLOOKUP(A4,Характеристика!$A$1:$D$100,4,0) -> Подтверждено | Q4: {=_xlfn.IFS(AND(P4=R4,T4="нет"),"нет",AND(P4=R4,T4="да"),"да",AND(P4<>R4,T4="нет"),"да",AND(P4<>R4,T4="да"),"нет")} -> да | R4: =VLOOKUP(B4,'Старый ИИ'!A:AQ,9,FALSE) -> Подтверждено | S4: =VLOOKUP(B4,'Старый ИИ'!A:AQ,11,FALSE) -> В отчёте указано, что в рамках мероприятия «Количество схем в калькуляторе мероприятий» в системе «Стройкомплекс.РФ» размещён калькулятор реализации мероприятий с 6 схемами (стр.1). Это подтверждает развитие подсистемы калькулятора мероприятий, однако сведения о подсистеме реестра документов отсутствуют, поэтому оценка не максимальна. | T4: =VLOOKUP(B4,'Старый ИИ'!A:AQ,12,FALSE) -> да | U4: =VLOOKUP(B4,'Старый ИИ'!A:AQ,13,FALSE) -> да | V4: =VLOOKUP(B4,'Старый ИИ'!A:AQ,14,FALSE) -> Корректно, подробности мероприятия предоставлены не все, но это не критично | W4: =VLOOKUP(B4,'ПХР актуальный'!$A$1:$C$34,3,0) -> #NUM! | X4: =VLOOKUP(B4,'Результат и ПХР'!$A$1:$Q$992,14,0) -> Основой вывода выбран ocr документа "Подтверждающие сведения 1.pdf". В evidence явно подтверждены метрика "Количество схем в реестре документов", требуемая характеристика объекта и привязка количества к самому объекту метрики; зафиксировано значение 6 Единица. Ключевой фрагмент evidence: "калькулятор реализации мероприятий, размещенный в единой государственной информационной системе обеспечения градостроительной деятельности «Стройкомплекс.РФ», содержит 6 схем". Поэтому строгие правила ПХР выполнены, и итоговый статус установлен как "подтверждено". | Y4: =VLOOKUP(B4,'Результат и ПХР'!$A$1:$Q$992,7,0) -> подтверждено | Z4: {=_xlfn.IFS(AND(Y4=AA4,AC4="нет"),"нет",AND(Y4=AA4,AC4="да"),"да",AND(Y4<>AA4,AC4="нет"),"да",AND(Y4<>AA4,AC4="да"),"нет")} -> да | AA4: =VLOOKUP(B4,'Старый ИИ'!A:AQ,21,FALSE) -> Подтверждено | AB4: =VLOOKUP(B4,'Старый ИИ'!A:AQ,23,FALSE) -> Отчет подтверждает развитие подсистемы: в нём указано, что калькулятор мероприятий в «Стройкомплекс.РФ» содержит 6 схем (стр. 1) – это согласуется с заявленным развитием калькулятора. Кроме того, в ПХР зафиксировано количество схем в реестре документов (1.0), что подтверждает наличие и развитие подсистемы реестра документов. Оба компонента мероприятия подтверждены документально. | AC4: =VLOOKUP(B4,'Старый ИИ'!A:AQ,24,FALSE) -> да | AD4: =VLOOKUP(B4,'Старый ИИ'!A:AQ,25,FALSE) -> нет | AE4: =VLOOKUP(B4,'Старый ИИ'!A:AQ,26,FALSE) -> Корректно по статусу, но некорректно по анализируемой информации по ПХР, она не ровна 1 (корректное значение - 3) | AF4: =VLOOKUP(B4,Общий!$E$2:$O$2000,10,0) -> 0 | AG4: =VLOOKUP(B4,Общий!$E$2:$O$2000,11,0) -> Единица | AH4: =VLOOKUP(B4,'Результат и ПХР'!$A$1:$M$992,13,0) -> Проверка опиралась на ocr документа "Подтверждающие сведения 1.pdf". В выбранном evidence не подтверждены следующие обязательные сигналы: обязательные сигналы. Имеющийся фрагмент "калькулятор реализации мероприятий, размещенный в единой государственной информационной системе обеспечения градостроительной деятельности «Стройкомплекс.РФ», содержит 6 схем" не дает прямого подтверждения выполнения. По правилу fail-closed статус мероприятия установлен как "не подтверждено". | AI4: =VLOOKUP(B4,'Результат и ПХР'!$A$1:$T$992,6,0) -> подтверждено | AJ4: да | AK4: =VLOOKUP(B4,'Старый ИИ'!A:AQ,27,FALSE) -> Не подтверждено | AL4: =VLOOKUP(B4,'Старый ИИ'!A:AQ,29,FALSE) -> Отчет фиксирует состояние калькулятора на конец декабря 2025 г., что частично соответствует требуемой дате 2025‑12‑31, однако точного указания «2025‑12‑31 00:00:00» нет, поэтому соответствие ограничено. | AM4: =VLOOKUP(B4,'Старый ИИ'!A:AQ,30,FALSE) -> нет | AN4: =VLOOKUP(B4,'Старый ИИ'!A:AQ,31,FALSE) -> нет | AO4: =VLOOKUP(B4,'Старый ИИ'!A:AQ,32,FALSE) -> Некорректно ИИ ищет точную дату подтверждения в подтверждении планового значения, а не сроков выполнения мероприятия. Фактическое значение 1 подтверждено.
A5: 9351224709 | B5: 9351224720 | C5: Реализованы проекты по повышению производительности труда в жилищно-коммунальном хозяйстве на базе отраслевого центра компетенций | D5: Центр компетенций реализует проекты по повышению производительности труда на предприятиях ЖКХ с использованием инструментов бережливого ЖКХ . Специалисты ОЦК, прошедшие обучение в АНО Федеральный центр компетенций в сфере производительности труда, проводят обучение представителей указанных организаций инструментам бережливого производства, которые позволят выстроить производственный процесс, создать решения по росту производительности труда за счёт устранения всех видов потерь, а также разработке корректирующих мероприятий для повышения эффективности. | E5: =VLOOKUP(B5,Подпись!$A$1:$E$100,5,0) -> Музыченко Сергей Григорьевич - Заместитель Министра, Файзуллин Ирек Энварович, Ломакин Александр Николаевич, Муценек Юрий Петрович, Стасишин Никита Евгеньевич, Гордеев Юрий Сергеевич, Музыченко Сергей Григорьевич, Михайлик Константин Александрович, Ересько Алексей Васильевич, Леонов Валерий Владимирович, Хусаинов Алмаз Шаукатович | F5: =VLOOKUP(B5,Подпись!$A$1:$E$100,2,0) -> Ересько Алексей Васильевич, Гордеев Юрий Сергеевич | G5: Подтверждено | H5: {=_xlfn.IFS(AND(G5=I5,K5="нет"),"нет",AND(G5=I5,K5="да"),"да",AND(G5<>I5,K5="нет"),"да",AND(G5<>I5,K5="да"),"нет")} -> нет | I5: =VLOOKUP(B5,'Старый ИИ'!A:AQ,3,FALSE) -> Не подтверждено | J5: =VLOOKUP(B5,'Старый ИИ'!A:AQ,5,FALSE) -> OCR обнаружил подписи, но анализ текста их не подтвердил. Возможно проблемы с качеством скана или распознаванием. | K5: =VLOOKUP(B5,'Старый ИИ'!A:AQ,6,FALSE) -> да | L5: =VLOOKUP(B5,'Старый ИИ'!A:AQ,7,FALSE) -> нет | M5: =VLOOKUP(B5,'Старый ИИ'!A:AQ,8,FALSE) -> ИИ корректно не принимает мероприятие - так как в документах стоит подпись не ответственного исполнителя, но в обосновании пишет о технической ошибке. Нет корректного обоснования какие подписи найдены. | N5: Центр компетенций реализует проекты по повышению производительности труда на предприятиях ЖКХ с использованием инструментов бережливого ЖКХ . Специалисты ОЦК, прошедшие обучение в АНО Федеральный центр компетенций в сфере производительности труда, проводят обучение представителей указанных организаций инструментам бережливого производства, которые позволят выстроить производственный процесс, создать решения по росту производительности труда за счёт устранения всех видов потерь, а также разработке корректирующих мероприятий для повышения эффективности. | O5: =VLOOKUP(A5,Характеристика!$A$1:$D$100,2,0) -> #N/A | P5: =VLOOKUP(A5,Характеристика!$A$1:$D$100,4,0) -> #N/A | Q5: {=_xlfn.IFS(AND(P5=R5,T5="нет"),"нет",AND(P5=R5,T5="да"),"да",AND(P5<>R5,T5="нет"),"да",AND(P5<>R5,T5="да"),"нет")} -> #N/A | R5: =VLOOKUP(B5,'Старый ИИ'!A:AQ,9,FALSE) -> Подтверждено | S5: =VLOOKUP(B5,'Старый ИИ'!A:AQ,11,FALSE) -> Отчет подтверждает реализацию проектов: указано, что целевые показатели достигнуты в полном объёме (пункт 1), разработано коробочное решение (1 ед.), описаны 10 лучших практик и проведено обучение 100 специалистов ЖКХ, что полностью соответствует заявленному мероприятию по повышению производительности труда в ЖКХ на базе отраслевого центра компетенций. | T5: =VLOOKUP(B5,'Старый ИИ'!A:AQ,12,FALSE) -> да | U5: =VLOOKUP(B5,'Старый ИИ'!A:AQ,13,FALSE) -> да | V5: =VLOOKUP(B5,'Старый ИИ'!A:AQ,14,FALSE) -> - | W5: =VLOOKUP(B5,'ПХР актуальный'!$A$1:$C$34,3,0) -> #NUM! | X5: =VLOOKUP(B5,'Результат и ПХР'!$A$1:$Q$992,14,0) -> #N/A | Y5: =VLOOKUP(B5,'Результат и ПХР'!$A$1:$Q$992,7,0) -> #N/A | Z5: {=_xlfn.IFS(AND(Y5=AA5,AC5="нет"),"нет",AND(Y5=AA5,AC5="да"),"да",AND(Y5<>AA5,AC5="нет"),"да",AND(Y5<>AA5,AC5="да"),"нет")} -> #N/A | AA5: =VLOOKUP(B5,'Старый ИИ'!A:AQ,21,FALSE) -> Подтверждено | AB5: =VLOOKUP(B5,'Старый ИИ'!A:AQ,23,FALSE) -> Отчет подтверждает реализацию проектов по повышению производительности труда в ЖКХ на базе отраслевого центра компетенций, о чём сказано в начале документа (стр. 1) и подтверждается перечислением достигнутых показателей: разработано 1 коробочное решение, описано 10 лучших практик, обучено 100 человек. Также указано, что проект отраслевой программы версии 2.0 разработан и передан в Минэкономразвития. Всё это полностью соответствует заявленному мероприятию. | AC5: =VLOOKUP(B5,'Старый ИИ'!A:AQ,24,FALSE) -> да | AD5: =VLOOKUP(B5,'Старый ИИ'!A:AQ,25,FALSE) -> нет | AE5: =VLOOKUP(B5,'Старый ИИ'!A:AQ,26,FALSE) -> ИИ некорректно описывает ПХР и ее количество, но корректно подтверждает ПХР. | AF5: =VLOOKUP(B5,Общий!$E$2:$O$2000,10,0) -> 0 | AG5: =VLOOKUP(B5,Общий!$E$2:$O$2000,11,0) -> Единица | AH5: =VLOOKUP(B5,'Результат и ПХР'!$A$1:$M$992,13,0) -> #N/A | AI5: =VLOOKUP(B5,'Результат и ПХР'!$A$1:$T$992,6,0) -> #N/A | AJ5: #N/A | AK5: =VLOOKUP(B5,'Старый ИИ'!A:AQ,27,FALSE) -> Подтверждено | AL5: =VLOOKUP(B5,'Старый ИИ'!A:AQ,29,FALSE) -> Отчет подтверждает реализацию мероприятия: в тексте указано разработка 1 коробочного решения, описание 10 лучших практик и обучение 100 специалистов, а также создание проекта программы версии 2.0 (см. раздел «Сообщаем, что целевые показатели…» и пункт о версии 2.0). Даты соответствуют 2025 году, требуемому сроку. | AM5: =VLOOKUP(B5,'Старый ИИ'!A:AQ,30,FALSE) -> да | AN5: =VLOOKUP(B5,'Старый ИИ'!A:AQ,31,FALSE) -> нет | AO5: =VLOOKUP(B5,'Старый ИИ'!A:AQ,32,FALSE) -> ИИ приводит некорректное плановое значение мероприятия. Корректное плановое значение мероприятия достигается в полном объеме.
A6: 9351224706 | B6: 9351225749 | C6: Реализованы проекты по повышению производительности труда с использованием инструментов бережливого проектирования и строительства на базе отраслевого центра компетенций | D6: Центр компетенций бережливого проектирования и строительства реализует проекты по повышению производительности труда с использованием инструментов бережливого строительства в средних и крупных проектно-строительных организациях. Специалисты ОЦК, прошедшие обучение в АНО Федеральный центр компетенций в сфере производительности труда, проводят обучение представителей указанных организаций инструментам бережливого производства, которые позволят выстроить производственный процесс, создать решения по росту производительности труда за счёт устранения всех видов потерь, а также разработке корректирующих мероприятий для повышения эффективности. | E6: =VLOOKUP(B6,Подпись!$A$1:$E$100,5,0) -> Музыченко Сергей Григорьевич - Заместитель Министра, Файзуллин Ирек Энварович, Ломакин Александр Николаевич, Муценек Юрий Петрович, Стасишин Никита Евгеньевич, Гордеев Юрий Сергеевич, Музыченко Сергей Григорьевич, Михайлик Константин Александрович, Ересько Алексей Васильевич, Леонов Валерий Владимирович, Хусаинов Алмаз Шаукатович | F6: =VLOOKUP(B6,Подпись!$A$1:$E$100,2,0) -> Музыченко Сергей Григорьевич | G6: Подтверждено | H6: {=_xlfn.IFS(AND(G6=I6,K6="нет"),"нет",AND(G6=I6,K6="да"),"да",AND(G6<>I6,K6="нет"),"да",AND(G6<>I6,K6="да"),"нет")} -> нет | I6: =VLOOKUP(B6,'Старый ИИ'!A:AQ,3,FALSE) -> Не подтверждено | J6: =VLOOKUP(B6,'Старый ИИ'!A:AQ,5,FALSE) -> Найдены подписи: Бигавва Г.Д., но они не совпадают с ответственными лицами | K6: =VLOOKUP(B6,'Старый ИИ'!A:AQ,6,FALSE) -> да | L6: =VLOOKUP(B6,'Старый ИИ'!A:AQ,7,FALSE) -> да | M6: =VLOOKUP(B6,'Старый ИИ'!A:AQ,8,FALSE) -> - | N6: Центр компетенций бережливого проектирования и строительства реализует проекты по повышению производительности труда с использованием инструментов бережливого строительства в средних и крупных проектно-строительных организациях. Специалисты ОЦК, прошедшие обучение в АНО Федеральный центр компетенций в сфере производительности труда, проводят обучение представителей указанных организаций инструментам бережливого производства, которые позволят выстроить производственный процесс, создать решения по росту производительности труда за счёт устранения всех видов потерь, а также разработке корректирующих мероприятий для повышения эффективности. | O6: =VLOOKUP(A6,Характеристика!$A$1:$D$100,2,0) -> Подтверждающие сведения 1.pdf - Документ описывает утверждение Положения об Отраслевом центре компетенций (ОЦК) по проектированию и строительству. Цели ОЦК прямо включают повышение производительности труда методами бережливого проектирования. Это соответствует теме реализации проектов по повышению производительности труда с использованием инструментов бережливого проектирования. Подтверждающие сведения 2.pdf - Документ упоминает реализацию проектов по повышению производительности труда на базе Отраслевого центра компетенций (ОЦК). Это напрямую соответствует теме события, где ОЦК реализует такие проекты. Также в тексте говорится о создании и запуске ОЦК, что является частью реализации указанных проектов. | P6: =VLOOKUP(A6,Характеристика!$A$1:$D$100,4,0) -> Подтверждено | Q6: {=_xlfn.IFS(AND(P6=R6,T6="нет"),"нет",AND(P6=R6,T6="да"),"да",AND(P6<>R6,T6="нет"),"да",AND(P6<>R6,T6="да"),"нет")} -> да | R6: =VLOOKUP(B6,'Старый ИИ'!A:AQ,9,FALSE) -> Не выполнено | S6: =VLOOKUP(B6,'Старый ИИ'!A:AQ,11,FALSE) -> 0 | T6: =VLOOKUP(B6,'Старый ИИ'!A:AQ,12,FALSE) -> нет | U6: =VLOOKUP(B6,'Старый ИИ'!A:AQ,13,FALSE) -> нет | V6: =VLOOKUP(B6,'Старый ИИ'!A:AQ,14,FALSE) -> Некорректно. Подтверждающий документ подтверждает суть описания мероприятия. | W6: =VLOOKUP(B6,'ПХР актуальный'!$A$1:$C$34,3,0) -> #NUM! | X6: =VLOOKUP(B6,'Результат и ПХР'!$A$1:$Q$992,14,0) -> Проверка опиралась на summary документа "Подтверждающие сведения 1.pdf". В выбранном evidence для метрики "Количество обученных специалистов отраслевого центра компетенций" установлено, что характеристика объекта не подтверждена явно; количество не привязано к объекту метрики; фактическое значение отсутствует; единица измерения отсутствует. Прямой подтверждающий фрагмент в evidence не найден. По правилу fail-closed статус ПХР установлен как "не подтверждено". | Y6: =VLOOKUP(B6,'Результат и ПХР'!$A$1:$Q$992,7,0) -> не подтверждено | Z6: {=_xlfn.IFS(AND(Y6=AA6,AC6="нет"),"нет",AND(Y6=AA6,AC6="да"),"да",AND(Y6<>AA6,AC6="нет"),"да",AND(Y6<>AA6,AC6="да"),"нет")} -> да | AA6: =VLOOKUP(B6,'Старый ИИ'!A:AQ,21,FALSE) -> Не выполнено | AB6: =VLOOKUP(B6,'Старый ИИ'!A:AQ,23,FALSE) -> 0 | AC6: =VLOOKUP(B6,'Старый ИИ'!A:AQ,24,FALSE) -> нет | AD6: =VLOOKUP(B6,'Старый ИИ'!A:AQ,25,FALSE) -> нет | AE6: =VLOOKUP(B6,'Старый ИИ'!A:AQ,26,FALSE) -> ИИ пишет о невыполнении количественной части характеристики, хотя у мероприятия нет характеристики с ненулевым плановым значением на 2025 год | AF6: =VLOOKUP(B6,Общий!$E$2:$O$2000,10,0) -> 0 | AG6: =VLOOKUP(B6,Общий!$E$2:$O$2000,11,0) -> Единица | AH6: =VLOOKUP(B6,'Результат и ПХР'!$A$1:$M$992,13,0) -> Проверка опиралась на summary документа "Подтверждающие сведения 1.pdf". В выбранном evidence не подтверждены следующие обязательные сигналы: действие, субъект, сигнал завершения. Прямой подтверждающий фрагмент в evidence не найден. По правилу fail-closed статус мероприятия установлен как "не подтверждено". | AI6: =VLOOKUP(B6,'Результат и ПХР'!$A$1:$T$992,6,0) -> не подтверждено | AJ6: нет | AK6: =VLOOKUP(B6,'Старый ИИ'!A:AQ,27,FALSE) -> Не выполнено | AL6: =VLOOKUP(B6,'Старый ИИ'!A:AQ,29,FALSE) -> 0 | AM6: =VLOOKUP(B6,'Старый ИИ'!A:AQ,30,FALSE) -> нет | AN6: =VLOOKUP(B6,'Старый ИИ'!A:AQ,31,FALSE) -> нет | AO6: =VLOOKUP(B6,'Старый ИИ'!A:AQ,32,FALSE) -> ИИ анализирует некорректное плановое значение, корректное плановое значение равно - 1. Подтверждающие документы говорят об утверждении положения об отраслевом центре компетенции
A7: 9187229902 | B7: 9187229922 | C7: Реализованы мероприятия по благоустройству общественных территорий (набережные, центральные площади, парки и др.) и иные мероприятия, предусмотренные государственными (муниципальными) программами формирования современной городской среды | D7: Ежегодно на территории муниципальных образований будут улучшены условия жизни граждан за счет создания качественных и современных общественных пространств, формирования новых возможностей для отдыха, занятия спортом, самореализации людей. | E7: =VLOOKUP(B7,Подпись!$A$1:$E$100,5,0) -> #N/A | F7: =VLOOKUP(B7,Подпись!$A$1:$E$100,2,0) -> #N/A | G7: #N/A | H7: {=_xlfn.IFS(AND(G7=I7,K7="нет"),"нет",AND(G7=I7,K7="да"),"да",AND(G7<>I7,K7="нет"),"да",AND(G7<>I7,K7="да"),"нет")} -> #N/A | I7: =VLOOKUP(B7,'Старый ИИ'!A:AQ,3,FALSE) -> Не подтверждено | J7: =VLOOKUP(B7,'Старый ИИ'!A:AQ,5,FALSE) -> Ошибка анализа: ошибка анализа | K7: =VLOOKUP(B7,'Старый ИИ'!A:AQ,6,FALSE) -> нет | L7: =VLOOKUP(B7,'Старый ИИ'!A:AQ,7,FALSE) -> нет | M7: =VLOOKUP(B7,'Старый ИИ'!A:AQ,8,FALSE) -> ИИ некорректно не принимает мероприятие - так как в документах стоит подпись ответственного исполнителя. | N7: Ежегодно на территории муниципальных образований будут улучшены условия жизни граждан за счет создания качественных и современных общественных пространств, формирования новых возможностей для отдыха, занятия спортом, самореализации людей. | O7: =VLOOKUP(A7,Характеристика!$A$1:$D$100,2,0) -> Подтверждающие сведения 1 (2).pdf - Документ содержит статистический отчет о количестве благоустроенных общественных территорий, таких как парки, набережные и центральные площади. Это напрямую соответствует теме реализации мероприятий по благоустройству общественных территорий, указанной в названии события. Также упоминается реализация мероприятий по формированию современной городской среды. | P7: =VLOOKUP(A7,Характеристика!$A$1:$D$100,4,0) -> Подтверждено | Q7: {=_xlfn.IFS(AND(P7=R7,T7="нет"),"нет",AND(P7=R7,T7="да"),"да",AND(P7<>R7,T7="нет"),"да",AND(P7<>R7,T7="да"),"нет")} -> да | R7: =VLOOKUP(B7,'Старый ИИ'!A:AQ,9,FALSE) -> Подтверждено | S7: =VLOOKUP(B7,'Старый ИИ'!A:AQ,11,FALSE) -> В отчёте (стр. 1) указаны разделы «Комплексное благоустройство общественных территорий… и иных мероприятий, предусмотренные государственными программами» и «Реализация мероприятий по благоустройству общественных территорий», подтверждающие реализацию описанных мероприятий. Таблицы на стр. 2‑4 содержат плановые и фактические показатели по регионам (пример — Республика Ингушетия, где отмечено 100 % выполнения), что соотносится с заявленными действиями по улучшению набережных, площадей и парков. | T7: =VLOOKUP(B7,'Старый ИИ'!A:AQ,12,FALSE) -> да | U7: =VLOOKUP(B7,'Старый ИИ'!A:AQ,13,FALSE) -> да | V7: =VLOOKUP(B7,'Старый ИИ'!A:AQ,14,FALSE) -> - | W7: Не указан | X7: =VLOOKUP(B7,'Результат и ПХР'!$A$1:$Q$992,14,0) -> Для мероприятия ПХР не задан в исходных данных. Поэтому doc-level проверка ПХР не запускалась и документы по ПХР не анализировались. Итоговый статус ПХР установлен как "не указано". | Y7: =VLOOKUP(B7,'Результат и ПХР'!$A$1:$Q$992,7,0) -> не указано | Z7: да | AA7: =VLOOKUP(B7,'Старый ИИ'!A:AQ,21,FALSE) -> Не применимо | AB7: =VLOOKUP(B7,'Старый ИИ'!A:AQ,23,FALSE) -> Анализ ПХР пропущен: показатели ПХР не указаны для данного мероприятия | AC7: =VLOOKUP(B7,'Старый ИИ'!A:AQ,24,FALSE) -> да | AD7: =VLOOKUP(B7,'Старый ИИ'!A:AQ,25,FALSE) -> да | AE7: =VLOOKUP(B7,'Старый ИИ'!A:AQ,26,FALSE) -> - | AF7: =VLOOKUP(B7,Общий!$E$2:$O$2000,10,0) -> 5000 | AG7: =VLOOKUP(B7,Общий!$E$2:$O$2000,11,0) -> Единица | AH7: =VLOOKUP(B7,'Результат и ПХР'!$A$1:$M$992,13,0) -> Проверка опиралась на summary документа "Подтверждающие сведения 1 (2).pdf". В выбранном evidence не подтверждены следующие обязательные сигналы: сигнал завершения, фактическое значение, единица измерения. Прямой подтверждающий фрагмент в evidence не найден. По правилу fail-closed статус мероприятия установлен как "не подтверждено". | AI7: =VLOOKUP(B7,'Результат и ПХР'!$A$1:$T$992,6,0) -> не подтверждено | AJ7: нет | AK7: =VLOOKUP(B7,'Старый ИИ'!A:AQ,27,FALSE) -> Подтверждено | AL7: =VLOOKUP(B7,'Старый ИИ'!A:AQ,29,FALSE) -> **1. Что удалось собрать:** - Подтверждено плановое значение: да. - Фактическое значение найдено в отчёте: да. - Фактическое значение соответствует плановому: да. - Вывод: плановое значение «23» полностью совпало с фактическим «23», показатель 100 % к плану, чек‑лист выполнен полностью. **2. Что не удалось собрать:** - Отсутствуют недостающие параметры – все необходимые сведения найдены и подтверждены. **3. Общий статус:** - Подтверждено выполнение планового значения: да. - Резюме: отчёт подтверждает полное выполнение запланированного объёма мероприятий для Республики Ингушетия. | AM7: =VLOOKUP(B7,'Старый ИИ'!A:AQ,30,FALSE) -> да | AN7: =VLOOKUP(B7,'Старый ИИ'!A:AQ,31,FALSE) -> нет | AO7: =VLOOKUP(B7,'Старый ИИ'!A:AQ,32,FALSE) -> ИИ сравнивал некорректное плановое значения с некорректным фактическим, но итоговый статус сошелся с правильным. | AP7: Плохой скан, не может быть прочитан
A8: 9187229901 | B8: 9187229919 | C8: Реализованы проекты победителей Всероссийского конкурса лучших проектов создания комфортной городской среды в малых городах и исторических поселениях (нарастающим итогом с 2025 г.) | D8: Ежегодно на территории победителей Всероссийского конкурса лучших проектов создания комфортной городской среды будут улучшены условия жизни граждан за счет создания качественных и современных общественных пространств, формирования новых возможностей для отдыха, занятия спортом, самореализации людей. | E8: =VLOOKUP(B8,Подпись!$A$1:$E$100,5,0) -> Ересько Алексей Васильевич - Заместитель Министра строительства и жилищно-коммунального хозяйства Российской Федерации, Файзуллин Ирек Энварович, Ломакин Александр Николаевич, Муценек Юрий Петрович, Стасишин Никита Евгеньевич, Гордеев Юрий Сергеевич, Музыченко Сергей Григорьевич, Михайлик Константин Александрович, Ересько Алексей Васильевич, Леонов Валерий Владимирович, Хусаинов Алмаз Шаукатович | F8: =VLOOKUP(B8,Подпись!$A$1:$E$100,2,0) -> Ересько Алексей Васильевич | G8: Подтверждено | H8: {=_xlfn.IFS(AND(G8=I8,K8="нет"),"нет",AND(G8=I8,K8="да"),"да",AND(G8<>I8,K8="нет"),"да",AND(G8<>I8,K8="да"),"нет")} -> да | I8: =VLOOKUP(B8,'Старый ИИ'!A:AQ,3,FALSE) -> Не подтверждено | J8: =VLOOKUP(B8,'Старый ИИ'!A:AQ,5,FALSE) -> Найдены подписи: Ереско А.В., но они не совпадают с ответственными лицами | K8: =VLOOKUP(B8,'Старый ИИ'!A:AQ,6,FALSE) -> нет | L8: =VLOOKUP(B8,'Старый ИИ'!A:AQ,7,FALSE) -> нет | M8: =VLOOKUP(B8,'Старый ИИ'!A:AQ,8,FALSE) -> ИИ пишет о найденной подписи ответственного исполнителя, но в статусе не подтверждает ее. | N8: Ежегодно на территории победителей Всероссийского конкурса лучших проектов создания комфортной городской среды будут улучшены условия жизни граждан за счет создания качественных и современных общественных пространств, формирования новых возможностей для отдыха, занятия спортом, самореализации людей. | O8: =VLOOKUP(A8,Характеристика!$A$1:$D$100,2,0) -> Подтверждающие сведения 1 (1).pdf - Документ представляет собой статистический отчет о реализации проектов победителей Всероссийского конкурса лучших проектов создания комфортной городской среды. Он содержит данные о количестве реализованных объектов, что напрямую связано с описанием события. Упоминается, что отчет составлен по состоянию на 31.12.2025, что соответствует временному контексту. | P8: =VLOOKUP(A8,Характеристика!$A$1:$D$100,4,0) -> Подтверждено | Q8: {=_xlfn.IFS(AND(P8=R8,T8="нет"),"нет",AND(P8=R8,T8="да"),"да",AND(P8<>R8,T8="нет"),"да",AND(P8<>R8,T8="да"),"нет")} -> да | R8: =VLOOKUP(B8,'Старый ИИ'!A:AQ,9,FALSE) -> Подтверждено | S8: =VLOOKUP(B8,'Старый ИИ'!A:AQ,11,FALSE) -> Отчет подтверждает, что реализованы проекты победителей Всероссийского конкурса по созданию комфортной городской среды (стр. 1, абз. «Reализованы проекты…», дата 31.12.2025). Таблицы 2‑4 содержат сведения о завершённых проектах в конкретных регионах (письма о завершении в г. Камышин, Поворино, Химки и др.) и показатели факта к плану, что соответствует заявленной цели мероприятия. | T8: =VLOOKUP(B8,'Старый ИИ'!A:AQ,12,FALSE) -> да | U8: =VLOOKUP(B8,'Старый ИИ'!A:AQ,13,FALSE) -> да | V8: =VLOOKUP(B8,'Старый ИИ'!A:AQ,14,FALSE) -> - | W8: Не указан | X8: =VLOOKUP(B8,'Результат и ПХР'!$A$1:$Q$992,14,0) -> Для мероприятия ПХР не задан в исходных данных. Поэтому doc-level проверка ПХР не запускалась и документы по ПХР не анализировались. Итоговый статус ПХР установлен как "не указано". | Y8: =VLOOKUP(B8,'Результат и ПХР'!$A$1:$Q$992,7,0) -> не указано | Z8: да | AA8: =VLOOKUP(B8,'Старый ИИ'!A:AQ,21,FALSE) -> Не применимо | AB8: =VLOOKUP(B8,'Старый ИИ'!A:AQ,23,FALSE) -> Анализ ПХР пропущен: показатели ПХР не указаны для данного мероприятия | AC8: =VLOOKUP(B8,'Старый ИИ'!A:AQ,24,FALSE) -> да | AD8: =VLOOKUP(B8,'Старый ИИ'!A:AQ,25,FALSE) -> да | AE8: =VLOOKUP(B8,'Старый ИИ'!A:AQ,26,FALSE) -> - | AF8: =VLOOKUP(B8,Общий!$E$2:$O$2000,10,0) -> 195 | AG8: =VLOOKUP(B8,Общий!$E$2:$O$2000,11,0) -> Единица | AH8: =VLOOKUP(B8,'Результат и ПХР'!$A$1:$M$992,13,0) -> Основой вывода выбран summary документа "Подтверждающие сведения 1 (1).pdf". В evidence найдены действие "Реализованы проекты победителей Всероссийского конкурса лучших проектов создания комфортной городской среды в малых городах и исторических поселениях", объект "нарастающим итогом с 2025 г.)", сигнал завершения "фактическое количество составило" и фактическое значение 246.0 проектов. Ключевой фрагмент evidence: "Согласно сводным данным, по Российской Федерации план в 195 объектов перевыполнен: фактическое количество составило 246 проектов (126,2%).". Сравнение результата определено как meets_target, поэтому статус мероприятия установлен как "подтверждено". | AI8: =VLOOKUP(B8,'Результат и ПХР'!$A$1:$T$992,6,0) -> подтверждено | AJ8: да | AK8: =VLOOKUP(B8,'Старый ИИ'!A:AQ,27,FALSE) -> Подтверждено | AL8: =VLOOKUP(B8,'Старый ИИ'!A:AQ,29,FALSE) -> В таблице первой страницы (строка «Центральный федеральный округ (в т. ч. Москва)») указано плановое значение 195 ед., а фактическое – 246 ед. за 2025 г. Это подтверждает заявленное значение мероприятия 195 ед. (план) и показывает превышение факта. | AM8: =VLOOKUP(B8,'Старый ИИ'!A:AQ,30,FALSE) -> да | AN8: =VLOOKUP(B8,'Старый ИИ'!A:AQ,31,FALSE) -> да | AO8: =VLOOKUP(B8,'Старый ИИ'!A:AQ,32,FALSE) -> -
A9: 9187604899 | B9: 9187604948 | C9: Обеспечена методологическая поддержка и информационно-аналитическое сопровождение реализации федерального проекта "Формирование комфортной городской среды" | D9: Обеспечение функций по управлению и сопровождению федерального проекта, оказание методического и консультационного сопровождения реализации федерального проекта, мониторинг реализации федерального проекта, достижение результатов федерального проекта. | E9: =VLOOKUP(B9,Подпись!$A$1:$E$100,5,0) -> #N/A | F9: =VLOOKUP(B9,Подпись!$A$1:$E$100,2,0) -> #N/A | G9: #N/A | H9: {=_xlfn.IFS(AND(G9=I9,K9="нет"),"нет",AND(G9=I9,K9="да"),"да",AND(G9<>I9,K9="нет"),"да",AND(G9<>I9,K9="да"),"нет")} -> #N/A | I9: =VLOOKUP(B9,'Старый ИИ'!A:AQ,3,FALSE) -> Не подтверждено | J9: =VLOOKUP(B9,'Старый ИИ'!A:AQ,5,FALSE) -> Найдены подписи: Зенкина О.Б., но они не совпадают с ответственными лицами | K9: =VLOOKUP(B9,'Старый ИИ'!A:AQ,6,FALSE) -> да | L9: =VLOOKUP(B9,'Старый ИИ'!A:AQ,7,FALSE) -> да | M9: =VLOOKUP(B9,'Старый ИИ'!A:AQ,8,FALSE) -> - | N9: Обеспечение функций по управлению и сопровождению федерального проекта, оказание методического и консультационного сопровождения реализации федерального проекта, мониторинг реализации федерального проекта, достижение результатов федерального проекта. | O9: =VLOOKUP(A9,Характеристика!$A$1:$D$100,2,0) -> Подтверждающие сведения 1.pdf - Текст напрямую касается реализации федерального проекта «Формирование комфортной городской среды». В нем упоминается подготовка аналитических отчетов и проведение конкурсов, что соответствует обеспечению информационно-аналитического сопровождения. Также в документе отражены результаты, что связано с мониторингом реализации проекта. | P9: =VLOOKUP(A9,Характеристика!$A$1:$D$100,4,0) -> Подтверждено | Q9: {=_xlfn.IFS(AND(P9=R9,T9="нет"),"нет",AND(P9=R9,T9="да"),"да",AND(P9<>R9,T9="нет"),"да",AND(P9<>R9,T9="да"),"нет")} -> да | R9: =VLOOKUP(B9,'Старый ИИ'!A:AQ,9,FALSE) -> Подтверждено | S9: =VLOOKUP(B9,'Старый ИИ'!A:AQ,11,FALSE) -> В отчете указано, что осуществляется сбор информации о ходе исполнения проектов, еженедельный мониторинг, подготовка аналитических отчетов «Светофор» и аналитики по победителям конкурсов — всё это подтверждает методологическую поддержку и информационно‑аналитическое сопровождение проекта «Формирование комфортной городской среды» (стр.1‑2). | T9: =VLOOKUP(B9,'Старый ИИ'!A:AQ,12,FALSE) -> да | U9: =VLOOKUP(B9,'Старый ИИ'!A:AQ,13,FALSE) -> да | V9: =VLOOKUP(B9,'Старый ИИ'!A:AQ,14,FALSE) -> - | W9: Не указан | X9: =VLOOKUP(B9,'Результат и ПХР'!$A$1:$Q$992,14,0) -> Для мероприятия ПХР не задан в исходных данных. Поэтому doc-level проверка ПХР не запускалась и документы по ПХР не анализировались. Итоговый статус ПХР установлен как "не указано". | Y9: =VLOOKUP(B9,'Результат и ПХР'!$A$1:$Q$992,7,0) -> не указано | Z9: да | AA9: =VLOOKUP(B9,'Старый ИИ'!A:AQ,21,FALSE) -> Не применимо | AB9: =VLOOKUP(B9,'Старый ИИ'!A:AQ,23,FALSE) -> Анализ ПХР пропущен: показатели ПХР не указаны для данного мероприятия | AC9: =VLOOKUP(B9,'Старый ИИ'!A:AQ,24,FALSE) -> да | AD9: =VLOOKUP(B9,'Старый ИИ'!A:AQ,25,FALSE) -> нет | AE9: =VLOOKUP(B9,'Старый ИИ'!A:AQ,26,FALSE) -> ИИ не проанализировал ПХР, хотя у мероприятия есть количественная ненулевая характеристика. По документам она выполнена. | AF9: =VLOOKUP(B9,Общий!$E$2:$O$2000,10,0) -> 1 | AG9: =VLOOKUP(B9,Общий!$E$2:$O$2000,11,0) -> Условная единица | AH9: =VLOOKUP(B9,'Результат и ПХР'!$A$1:$M$992,13,0) -> Проверка опиралась на ocr документа "Подтверждающие сведения 1.pdf". В выбранном evidence не подтверждены следующие обязательные сигналы: действие, субъект, сигнал завершения. Прямой подтверждающий фрагмент в evidence не найден. По правилу fail-closed статус мероприятия установлен как "не подтверждено". | AI9: =VLOOKUP(B9,'Результат и ПХР'!$A$1:$T$992,6,0) -> не подтверждено | AJ9: нет | AK9: =VLOOKUP(B9,'Старый ИИ'!A:AQ,27,FALSE) -> Подтверждено | AL9: =VLOOKUP(B9,'Старый ИИ'!A:AQ,29,FALSE) -> Отчет подтверждает выполнение мероприятия: подготовлены аналитические отчёты «Светофор» по реализации проекта (стр. 2) и по объектам победителей (стр. 2), а также осуществлён еженедельный мониторинг и сбор информации о ходе работ (стр. 1). Эти действия непосредственно соответствуют методологической поддержке и информационно‑аналитическому сопровождению проекта. | AM9: =VLOOKUP(B9,'Старый ИИ'!A:AQ,30,FALSE) -> да | AN9: =VLOOKUP(B9,'Старый ИИ'!A:AQ,31,FALSE) -> да | AO9: =VLOOKUP(B9,'Старый ИИ'!A:AQ,32,FALSE) -> -
A10: 9193757674 | B10: 9206711678 | C10: Приобретены с использованием Пушкинской карты билеты на посещение мероприятий (нарастающий итог) | D10: Целью мероприятия является создание условий для воспитания гармонично развитой и социально ответственной личности на основе духовно-нравственных ценностей народов Российской Федерации, исторических и национально-культурных традиций. В рамках мероприятия предоставляется возможность гражданам в возрасте с 14 до 22 лет воспользоваться программой социальной поддержки посещения учреждений культуры (театры, организации кинопоказа (кинотеатры), концертные организации, музеи, организации культурно-досугового типа, библиотеки и образовательные организации в сфере культуры).Реализация мероприятия способствует формированию художественного вкуса, кругозора в области культуры и искусства, а также привычки регулярно посещать мероприятия учреждений культуры у молодежи. | E10: =VLOOKUP(B10,Подпись!$A$1:$E$100,5,0) -> #N/A | F10: =VLOOKUP(B10,Подпись!$A$1:$E$100,2,0) -> #N/A | G10: #N/A | H10: {=_xlfn.IFS(AND(G10=I10,K10="нет"),"нет",AND(G10=I10,K10="да"),"да",AND(G10<>I10,K10="нет"),"да",AND(G10<>I10,K10="да"),"нет")} -> #N/A | I10: =VLOOKUP(B10,'Старый ИИ'!A:AQ,3,FALSE) -> Не подтверждено | J10: =VLOOKUP(B10,'Старый ИИ'!A:AQ,5,FALSE) -> Найдены подписи: Богданов С.Ю., но они не совпадают с ответственными лицами | K10: =VLOOKUP(B10,'Старый ИИ'!A:AQ,6,FALSE) -> да | L10: =VLOOKUP(B10,'Старый ИИ'!A:AQ,7,FALSE) -> да | M10: =VLOOKUP(B10,'Старый ИИ'!A:AQ,8,FALSE) -> - | N10: Целью мероприятия является создание условий для воспитания гармонично развитой и социально ответственной личности на основе духовно-нравственных ценностей народов Российской Федерации, исторических и национально-культурных традиций. В рамках мероприятия предоставляется возможность гражданам в возрасте с 14 до 22 лет воспользоваться программой социальной поддержки посещения учреждений культуры (театры, организации кинопоказа (кинотеатры), концертные организации, музеи, организации культурно-досугового типа, библиотеки и образовательные организации в сфере культуры).Реализация мероприятия способствует формированию художественного вкуса, кругозора в области культуры и искусства, а также привычки регулярно посещать мероприятия учреждений культуры у молодежи. | O10: =VLOOKUP(A10,Характеристика!$A$1:$D$100,2,0) -> Подтверждающие сведения 2.pdf - Документ содержит отчет об исполнении федерального проекта, связанного с программой «Пушкинская карта». В тексте прямо упоминается «нарастающее количество приобретенных билетов», что соответствует теме мероприятия. Это подтверждает реализацию программы, направленной на посещение учреждений культуры молодежью. | P10: =VLOOKUP(A10,Характеристика!$A$1:$D$100,4,0) -> Подтверждено | Q10: {=_xlfn.IFS(AND(P10=R10,T10="нет"),"нет",AND(P10=R10,T10="да"),"да",AND(P10<>R10,T10="нет"),"да",AND(P10<>R10,T10="да"),"нет")} -> да | R10: =VLOOKUP(B10,'Старый ИИ'!A:AQ,9,FALSE) -> Подтверждено | S10: =VLOOKUP(B10,'Старый ИИ'!A:AQ,11,FALSE) -> Отчет подтверждает достижение результата: на странице 1 указано фактическое значение «Приобретены с использованием Пушкинской карты билеты на посещение мероприятий» — 102,204 млн ед. (из них 22,06 млн ед. за 2025 год). Кроме того, в таблице (стр. 2) в строке «— Количество выданных билетов (шт.)» приведены кумулятивные цифры, достигающие 101 283 797 шт., что также свидетельствует о покупке билетов по карте. | T10: =VLOOKUP(B10,'Старый ИИ'!A:AQ,12,FALSE) -> да | U10: =VLOOKUP(B10,'Старый ИИ'!A:AQ,13,FALSE) -> да | V10: =VLOOKUP(B10,'Старый ИИ'!A:AQ,14,FALSE) -> - | W10: =VLOOKUP(B10,'ПХР актуальный'!$A$1:$C$34,3,0) -> #NUM! | X10: =VLOOKUP(B10,'Результат и ПХР'!$A$1:$Q$992,14,0) -> Основой вывода выбран ocr документа "Подтверждающие сведения 2.pdf". В evidence явно подтверждены метрика "Количество выданных Пушкинских карт", требуемая характеристика объекта и привязка количества к самому объекту метрики; зафиксировано значение 13.02 Миллион единиц. Ключевой фрагмент evidence: "по итогам 2025 года количество выданных Пушкинских карт составило 13,02 млн единиц.". Поэтому строгие правила ПХР выполнены, и итоговый статус установлен как "подтверждено". | Y10: =VLOOKUP(B10,'Результат и ПХР'!$A$1:$Q$992,7,0) -> подтверждено | Z10: {=_xlfn.IFS(AND(Y10=AA10,AC10="нет"),"нет",AND(Y10=AA10,AC10="да"),"да",AND(Y10<>AA10,AC10="нет"),"да",AND(Y10<>AA10,AC10="да"),"нет")} -> да | AA10: =VLOOKUP(B10,'Старый ИИ'!A:AQ,21,FALSE) -> Подтверждено | AB10: =VLOOKUP(B10,'Старый ИИ'!A:AQ,23,FALSE) -> Отчёт напрямую посвящён результату «Приобретены с использованием Пушкинской карты билеты на посещение мероприятий» (см. страница 1). В таблице указано количество выданных билетов к 31.12.2025 = 101 283 797 шт. (≈101,3 млн ед.), что подтверждает нарастающий итог мероприятия. | AC10: =VLOOKUP(B10,'Старый ИИ'!A:AQ,24,FALSE) -> да | AD10: =VLOOKUP(B10,'Старый ИИ'!A:AQ,25,FALSE) -> нет | AE10: =VLOOKUP(B10,'Старый ИИ'!A:AQ,26,FALSE) -> Корректно по статусу, но некорректно по анализу. ИИ соотносит некорректное количество ПХР. По документу все количественные части характеристики выполнены. | AF10: =VLOOKUP(B10,Общий!$E$2:$O$2000,10,0) -> 100.144 | AG10: =VLOOKUP(B10,Общий!$E$2:$O$2000,11,0) -> Миллион единиц | AH10: =VLOOKUP(B10,'Результат и ПХР'!$A$1:$M$992,13,0) -> Основой вывода выбран ocr документа "Подтверждающие сведения 2.pdf". В evidence найдены действие "Приобретены с использованием Пушкинской карты билеты на посещение мероприятий", объект "нарастающий итог)", сигнал завершения "фактическое значение" и фактическое значение 102.204 млн ед.. Ключевой фрагмент evidence: "фактическое значение (нарастающим итогом с начала реализации мероприятия) – 102,204 млн ед.". Сравнение результата определено как meets_target, поэтому статус мероприятия установлен как "подтверждено". | AI10: =VLOOKUP(B10,'Результат и ПХР'!$A$1:$T$992,6,0) -> подтверждено | AJ10: да | AK10: =VLOOKUP(B10,'Старый ИИ'!A:AQ,27,FALSE) -> Подтверждено | AL10: =VLOOKUP(B10,'Старый ИИ'!A:AQ,29,FALSE) -> В отчете указано плановое (нарастающее) значение 100,144 млн ед. и фактическое 102,204 млн ед. за 31.12.2025, что подтверждает заявленное значение мероприятия и даже превышает его (см. раздел «по состоянию на 31.12.2025»). | AM10: =VLOOKUP(B10,'Старый ИИ'!A:AQ,30,FALSE) -> да | AN10: =VLOOKUP(B10,'Старый ИИ'!A:AQ,31,FALSE) -> да | AO10: =VLOOKUP(B10,'Старый ИИ'!A:AQ,32,FALSE) -> -
A11: 9191447906 | B11: 9191447973 | C11: Оснащены современным оборудованием кинозалы в населенных пунктах до 500 тыс. человек, в которых обеспечен прокат национальных фильмов | D11: В рамках результата предусмотрено: 1) сохранение действующих условий мероприятия для новых субъектов Российской Федерации до достижения ими средних показателей уровня кинофикации (с 2025 по 2030 годы будут оснащены 90 кинозалов в населенных пунктах с численностью населения до 500 тыс. человек); 2) предоставление возможности приобретения за счет средств федерального бюджета мультимедийного оборудования населенным пунктам с численностью населения до 50 тыс. человек (с 2025 по 2030 годы будут оснащены 900 кинозалов); 3) приобретение комплектующих и расходных частей ранее поддержанным кинозалам (1 кинозал = 2,5 млн рублей): 2025 - 46 кинозалов, 2026 - 104, 2027- 120, 2028 - 46, 2029 - 52, 2030 - 56). | E11: =VLOOKUP(B11,Подпись!$A$1:$E$100,5,0) -> #N/A | F11: =VLOOKUP(B11,Подпись!$A$1:$E$100,2,0) -> #N/A | G11: #N/A | H11: {=_xlfn.IFS(AND(G11=I11,K11="нет"),"нет",AND(G11=I11,K11="да"),"да",AND(G11<>I11,K11="нет"),"да",AND(G11<>I11,K11="да"),"нет")} -> #N/A | I11: =VLOOKUP(B11,'Старый ИИ'!A:AQ,3,FALSE) -> Не подтверждено | J11: =VLOOKUP(B11,'Старый ИИ'!A:AQ,5,FALSE) -> Найдены подписи: Кокошкина Ю.К., Ярина А.А., но они не совпадают с ответственными лицами | K11: =VLOOKUP(B11,'Старый ИИ'!A:AQ,6,FALSE) -> да | L11: =VLOOKUP(B11,'Старый ИИ'!A:AQ,7,FALSE) -> да | M11: =VLOOKUP(B11,'Старый ИИ'!A:AQ,8,FALSE) -> - | N11: В рамках результата предусмотрено: 1) сохранение действующих условий мероприятия для новых субъектов Российской Федерации до достижения ими средних показателей уровня кинофикации (с 2025 по 2030 годы будут оснащены 90 кинозалов в населенных пунктах с численностью населения до 500 тыс. человек); 2) предоставление возможности приобретения за счет средств федерального бюджета мультимедийного оборудования населенным пунктам с численностью населения до 50 тыс. человек (с 2025 по 2030 годы будут оснащены 900 кинозалов); 3) приобретение комплектующих и расходных частей ранее поддержанным кинозалам (1 кинозал = 2,5 млн рублей): 2025 - 46 кинозалов, 2026 - 104, 2027- 120, 2028 - 46, 2029 - 52, 2030 - 56). | O11: =VLOOKUP(A11,Характеристика!$A$1:$D$100,2,0) -> Подтверждающие сведения 1.pdf - Документ содержит информацию о реализации программ по поддержке кинопоказов и развитию инфраструктуры. Упоминается открытие кинозалов в малых населенных пунктах и модификация оборудования кинозалов. Это соответствует теме оснащения кинозалов в населенных пунктах, указанной в описании события. Подтверждающие сведения 2.pdf - Событие касается оснащения кинозалов в населенных пунктах. В предоставленном тексте упоминается модернизация 51 кинозала и приобретение комплектующих и расходных материалов для 50 ранее поддержанных кинозалов. Это напрямую связано с деятельностью по поддержке и оснащению киноинфраструктуры. | P11: =VLOOKUP(A11,Характеристика!$A$1:$D$100,4,0) -> Подтверждено | Q11: {=_xlfn.IFS(AND(P11=R11,T11="нет"),"нет",AND(P11=R11,T11="да"),"да",AND(P11<>R11,T11="нет"),"да",AND(P11<>R11,T11="да"),"нет")} -> да | R11: =VLOOKUP(B11,'Старый ИИ'!A:AQ,9,FALSE) -> Подтверждено | S11: =VLOOKUP(B11,'Старый ИИ'!A:AQ,11,FALSE) -> Отчет подтверждает, что в 2025 г. открыты 10 кинозалов в населённых пунктах до 500 тыс. чел. (Стр. 1) с оборудованием, обеспечивающим прокат национальных фильмов, а также 41 центр в населённых пунктах до 50 тыс. чел. (Стр. 2) оснащены современным мультимедийным оборудованием, что полностью соответствует заявленному мероприятию. | T11: =VLOOKUP(B11,'Старый ИИ'!A:AQ,12,FALSE) -> да | U11: =VLOOKUP(B11,'Старый ИИ'!A:AQ,13,FALSE) -> да | V11: =VLOOKUP(B11,'Старый ИИ'!A:AQ,14,FALSE) -> - | W11: Не указан | X11: =VLOOKUP(B11,'Результат и ПХР'!$A$1:$Q$992,14,0) -> Для мероприятия ПХР не задан в исходных данных. Поэтому doc-level проверка ПХР не запускалась и документы по ПХР не анализировались. Итоговый статус ПХР установлен как "не указано". | Y11: =VLOOKUP(B11,'Результат и ПХР'!$A$1:$Q$992,7,0) -> не указано | Z11: да | AA11: =VLOOKUP(B11,'Старый ИИ'!A:AQ,21,FALSE) -> Не применимо | AB11: =VLOOKUP(B11,'Старый ИИ'!A:AQ,23,FALSE) -> Анализ ПХР пропущен: показатели ПХР не указаны для данного мероприятия | AC11: =VLOOKUP(B11,'Старый ИИ'!A:AQ,24,FALSE) -> да | AD11: =VLOOKUP(B11,'Старый ИИ'!A:AQ,25,FALSE) -> нет | AE11: =VLOOKUP(B11,'Старый ИИ'!A:AQ,26,FALSE) -> ИИ не проанализировал ПХР, хотя у мероприятия есть количественная ненулевая характеристика, которая подтверждена по документам. | AF11: =VLOOKUP(B11,Общий!$E$2:$O$2000,10,0) -> 1514 | AG11: =VLOOKUP(B11,Общий!$E$2:$O$2000,11,0) -> Единица | AH11: =VLOOKUP(B11,'Результат и ПХР'!$A$1:$M$992,13,0) -> Основой вывода выбран summary документа "Подтверждающие сведения 2.pdf". В evidence найдены действие "Оснащены современным оборудованием кинозалы в населенных пунктах до 500 тыс", объект "человек, в которых обеспечен прокат национальных фильмов", сигнал завершения "Нарастающим итогом с начала реализации проекта модернизировано" и фактическое значение 1515.0 кинозалов. Ключевой фрагмент evidence: "Нарастающим итогом с начала реализации проекта модернизировано 1 515 кинозалов.". Сравнение результата определено как meets_target, поэтому статус мероприятия установлен как "подтверждено". | AI11: =VLOOKUP(B11,'Результат и ПХР'!$A$1:$T$992,6,0) -> подтверждено | AJ11: да | AK11: =VLOOKUP(B11,'Старый ИИ'!A:AQ,27,FALSE) -> Подтверждено | AL11: =VLOOKUP(B11,'Старый ИИ'!A:AQ,29,FALSE) -> В отчете указано, что к 30.12.2025 г. модернизировано 1 515 кинозалов (стр. 2), что превышает запланированное значение 1 514 ед. (план). Факт полностью подтверждает KPI. | AM11: =VLOOKUP(B11,'Старый ИИ'!A:AQ,30,FALSE) -> да | AN11: =VLOOKUP(B11,'Старый ИИ'!A:AQ,31,FALSE) -> да | AO11: =VLOOKUP(B11,'Старый ИИ'!A:AQ,32,FALSE) -> -
A12: 9187094213 | B12: 9187094278 | C12: Разработан комплекс мероприятий, направленный на организацию деятельности по формированию семейных ценностей в организациях культуры (нарастающий итог) | D12: В целях активизации работы учреждений культуры, ориентированной на сохранение и популяризацию семейных ценностей, Минкультуры России будет разработан соответствующий комплекс мероприятий, включающий в себя в том числе методические рекомендации для 89 регионов Российской Федерации. Эти методические рекомендации будут направлены на то, чтобы в учреждениях культуры проводились мероприятия, способствующие укреплению семейных ценностей и созданию условий для семейного досуга и творчества. Это позволит создать единое пространство для сохранения и популяризации семейных ценностей, а также обеспечить доступность и разнообразие мероприятий для семей всех возрастов и социальных групп. | E12: =VLOOKUP(B12,Подпись!$A$1:$E$100,5,0) -> #N/A | F12: =VLOOKUP(B12,Подпись!$A$1:$E$100,2,0) -> #N/A | G12: #N/A | H12: {=_xlfn.IFS(AND(G12=I12,K12="нет"),"нет",AND(G12=I12,K12="да"),"да",AND(G12<>I12,K12="нет"),"да",AND(G12<>I12,K12="да"),"нет")} -> #N/A | I12: =VLOOKUP(B12,'Старый ИИ'!A:AQ,3,FALSE) -> Не подтверждено | J12: =VLOOKUP(B12,'Старый ИИ'!A:AQ,5,FALSE) -> Найдены подписи: Эдды П.Т., но они не совпадают с ответственными лицами | K12: =VLOOKUP(B12,'Старый ИИ'!A:AQ,6,FALSE) -> нет | L12: =VLOOKUP(B12,'Старый ИИ'!A:AQ,7,FALSE) -> нет | M12: =VLOOKUP(B12,'Старый ИИ'!A:AQ,8,FALSE) -> ИИ не нашел в документе подпись ответственного исполнителя. | N12: В целях активизации работы учреждений культуры, ориентированной на сохранение и популяризацию семейных ценностей, Минкультуры России будет разработан соответствующий комплекс мероприятий, включающий в себя в том числе методические рекомендации для 89 регионов Российской Федерации. Эти методические рекомендации будут направлены на то, чтобы в учреждениях культуры проводились мероприятия, способствующие укреплению семейных ценностей и созданию условий для семейного досуга и творчества. Это позволит создать единое пространство для сохранения и популяризации семейных ценностей, а также обеспечить доступность и разнообразие мероприятий для семей всех возрастов и социальных групп. | O12: =VLOOKUP(A12,Характеристика!$A$1:$D$100,2,0) -> Подтверждающие сведения 1.pdf - Документ описывает сборник лучших региональных практик по формированию семейных ценностей в организациях культуры. Это напрямую соответствует цели мероприятия по активизации работы учреждений культуры, ориентированной на сохранение и популяризацию семейных ценностей. Упоминаются конкретные мероприятия, способствующие укреплению семейных уз и культурному досугу. Подтверждающие сведения 2.pdf - Документ описывает отчет об исполнении федерального проекта «Семейные ценности и инфраструктура культуры». В нем упоминается, что Минкультуры России разработало сборник лучших практик и методических рекомендаций для 89 регионов РФ. Это напрямую соответствует цели разработки комплекса мероприятий для формирования семейных ценностей в организациях культуры. | P12: =VLOOKUP(A12,Характеристика!$A$1:$D$100,4,0) -> Подтверждено | Q12: {=_xlfn.IFS(AND(P12=R12,T12="нет"),"нет",AND(P12=R12,T12="да"),"да",AND(P12<>R12,T12="нет"),"да",AND(P12<>R12,T12="да"),"нет")} -> да | R12: =VLOOKUP(B12,'Старый ИИ'!A:AQ,9,FALSE) -> Подтверждено | S12: =VLOOKUP(B12,'Старый ИИ'!A:AQ,11,FALSE) -> Отчет подтверждает достижение результата: «Разработан комплекс мероприятий, направленный на организацию деятельности по формированию семейных ценностей в организациях культуры» – плановое и фактическое значение = 1, результат достигнут в полном объёме (стр. 1). Кроме того, Минкультуры разработало сборник лучших практик, представляющий методические рекомендации для 89 регионов, включающий комплекс мероприятий, способствующих укреплению семейных ценностей (стр. 1). | T12: =VLOOKUP(B12,'Старый ИИ'!A:AQ,12,FALSE) -> да | U12: =VLOOKUP(B12,'Старый ИИ'!A:AQ,13,FALSE) -> да | V12: =VLOOKUP(B12,'Старый ИИ'!A:AQ,14,FALSE) -> - | W12: Не указан | X12: =VLOOKUP(B12,'Результат и ПХР'!$A$1:$Q$992,14,0) -> #N/A | Y12: =VLOOKUP(B12,'Результат и ПХР'!$A$1:$Q$992,7,0) -> #N/A | Z12: {=_xlfn.IFS(AND(Y12=AA12,AC12="нет"),"нет",AND(Y12=AA12,AC12="да"),"да",AND(Y12<>AA12,AC12="нет"),"да",AND(Y12<>AA12,AC12="да"),"нет")} -> #N/A | AA12: =VLOOKUP(B12,'Старый ИИ'!A:AQ,21,FALSE) -> Не применимо | AB12: =VLOOKUP(B12,'Старый ИИ'!A:AQ,23,FALSE) -> Анализ ПХР пропущен: показатели ПХР не указаны для данного мероприятия | AC12: =VLOOKUP(B12,'Старый ИИ'!A:AQ,24,FALSE) -> да | AD12: =VLOOKUP(B12,'Старый ИИ'!A:AQ,25,FALSE) -> да | AE12: =VLOOKUP(B12,'Старый ИИ'!A:AQ,26,FALSE) -> - | AF12: =VLOOKUP(B12,Общий!$E$2:$O$2000,10,0) -> 1 | AG12: =VLOOKUP(B12,Общий!$E$2:$O$2000,11,0) -> Единица | AH12: =VLOOKUP(B12,'Результат и ПХР'!$A$1:$M$992,13,0) -> #N/A | AI12: =VLOOKUP(B12,'Результат и ПХР'!$A$1:$T$992,6,0) -> #N/A | AJ12: #N/A | AK12: =VLOOKUP(B12,'Старый ИИ'!A:AQ,27,FALSE) -> Подтверждено | AL12: =VLOOKUP(B12,'Старый ИИ'!A:AQ,29,FALSE) -> Отчет подтверждает плановое значение KPI: в тексте указано «плановое значение … составляет 1 единицу (фактическое значение … — 1 единица)» (стр.1). Фактическое значение полностью совпадает с плановым — 1 единица, значит цель достигнута в полном объеме. | AM12: =VLOOKUP(B12,'Старый ИИ'!A:AQ,30,FALSE) -> да | AN12: =VLOOKUP(B12,'Старый ИИ'!A:AQ,31,FALSE) -> да | AO12: =VLOOKUP(B12,'Старый ИИ'!A:AQ,32,FALSE) -> -
A13: 9191447901 | B13: 9206750272 | C13: Реализованы творческие проекты, направленные на сохранение и популяризацию традиционных ценностей | D13: Комплекс указанных мер реализован посредством оказания поддержки (выделение субсидии) на конкурсной основе творческим проектам в сфере музыкального, театрального, изобразительного искусства и народного творчества, а также творческим проектам, с контентом, соответствующим стратегическим задачам нового времени. В рамках ФП "Творческие люди" НП "Культура" с 2019 по 2024 гг. было проведено 30 фестивалей детского творчества всех жанров и 60 всероссийских и международных творческих проектов в области музыкального, театрального и изобразительного искусства. С 2025 по 2030 гг. ежегодно планируется реализация 50 творческих проектов. Всего к концу 2030 года будет реализовано 390 творческих проектов. | E13: =VLOOKUP(B13,Подпись!$A$1:$E$100,5,0) -> Алексеева Жанна Владимировна - Статс-секретарь - заместитель Министра культуры Российской Федерации, Любимова Ольга Борисовна, Обрывалин Сергей Геннадьевич, Алексеева Жанна Владимировна, Осинцев Владимир Геннадьевич, Малышев Андрей Владимирович, Першин Сергей Васильевич | F13: =VLOOKUP(B13,Подпись!$A$1:$E$100,2,0) -> Ольга Борисовна, Малышев Андрей Владимирович | G13: Подтверждено | H13: {=_xlfn.IFS(AND(G13=I13,K13="нет"),"нет",AND(G13=I13,K13="да"),"да",AND(G13<>I13,K13="нет"),"да",AND(G13<>I13,K13="да"),"нет")} -> #N/A | I13: =VLOOKUP(B13,'Старый ИИ'!A:AQ,3,FALSE) -> Не подтверждено | J13: =VLOOKUP(B13,'Старый ИИ'!A:AQ,5,FALSE) -> 0 | K13: =VLOOKUP(B13,'Старый ИИ'!A:AQ,6,FALSE) -> #N/A | L13: =VLOOKUP(B13,'Старый ИИ'!A:AQ,7,FALSE) -> #N/A | M13: =VLOOKUP(B13,'Старый ИИ'!A:AQ,8,FALSE) -> #N/A | N13: Комплекс указанных мер реализован посредством оказания поддержки (выделение субсидии) на конкурсной основе творческим проектам в сфере музыкального, театрального, изобразительного искусства и народного творчества, а также творческим проектам, с контентом, соответствующим стратегическим задачам нового времени. В рамках ФП "Творческие люди" НП "Культура" с 2019 по 2024 гг. было проведено 30 фестивалей детского творчества всех жанров и 60 всероссийских и международных творческих проектов в области музыкального, театрального и изобразительного искусства. С 2025 по 2030 гг. ежегодно планируется реализация 50 творческих проектов. Всего к концу 2030 года будет реализовано 390 творческих проектов. | O13: =VLOOKUP(A13,Характеристика!$A$1:$D$100,2,0) -> Подтверждающие сведения 9.pdf - Документ описывает отчет о реализации творческих проектов в сферах музыки, театра и изобразительного искусства. Это соответствует цели события, которая заключается в реализации творческих проектов для сохранения и популяризации традиционных ценностей. Упоминание о проектах, направленных на укрепление института семьи и воспитание гражданственности, подтверждает соответствие тематике. + ТВОРЧЕСКИЙ ОТЧЕТ 054-10-2025-061 Концерт к 95-летию со дня рождения композитора Андрея Петрова.pdf - Описание события касается реализации творческих проектов в сфере музыкального искусства, что соответствует содержанию отчета. В тексте упоминается проведение гала-концерта, посвященного композитору, и фиксируются результаты использования субсидии. Это напрямую связано с поддержкой творческих проектов, упомянутых в описании события. ТВОРЧЕСКИЙ ОТЧЕТ 054-10-2025-062.pdf - Описание события касается реализации творческих проектов в сфере театрального искусства при поддержке субсидий. Предоставленный текст описывает реализацию театральной постановки «Пир во время чумы» за счет федеральной субсидии. Это напрямую соответствует тематике поддержки творческих проектов, упомянутой в описании события. ТВОРЧЕСКИЙ ОТЧЕТ 054-10-2025-063.pdf - Документ описывает Всероссийский хоровой фестиваль, который направлен на развитие музыкальной культуры. В тексте прямо указано, что проект соответствует целям государственной политики по сохранению традиционных духовно-нравственных ценностей. Это соответствует теме реализации творческих проектов для сохранения традиционных ценностей. ТВОРЧЕСКИЙ ОТЧЕТ 054-10-2025-064(4).pdf - Целевое событие касается реализации творческих проектов в сфере музыкального и изобразительного искусства. Предоставленный документ описывает отчет о проведении фестиваля классической музыки, что соответствует сфере музыкального искусства. Отчет содержит сведения о реализации творческого проекта в различных регионах России. + ТВОРЧЕСКИЙ ОТЧЕТ 054-10-2025-067 Московский хоровой фестиваль духовной музыки (Великопостный).pdf - Целевое событие касается реализации творческих проектов в сфере музыкального искусства. Предоставленный документ описывает отчет о проведении Международного Великопостного хорового фестиваля. Этот фестиваль является примером творческого проекта в области музыкального искусства, что соответствует тематике мероприятия. + ТВОРЧЕСКИЙ ОТЧЕТ 054-10-2025-070 Международный фестиваль балета DANCE OPEN.pdf - Событие касается реализации творческих проектов в сфере искусства, что соответствует теме сохранения и популяризации традиционных ценностей. Международный фестиваль балета является примером такого творческого проекта. В тексте упоминается, что проект реализован при поддержке Министерства культуры РФ и Президентского фонда культурных инициатив, что соответствует контексту поддержки творческих проектов. ТВОРЧЕСКИЙ ОТЧЁТ 054-10-2025-071.pdf - Описание события касается реализации творческих проектов в сфере искусства, включая театральное искусство. Предоставленный документ отчитывается о проведении Всероссийского фестиваля театрального искусства для детей «Арлекин». Это напрямую соответствует направлению реализации творческих проектов, упомянутому в описании события. ТВОРЧЕСКИЙ ОТЧЕТ 054-10-2025-073.pdf - Документ описывает реализацию творческого проекта, что соответствует теме мероприятия. Проект связан с показом спектакля, который является формой творческого искусства. Это подтверждает реализацию творческих проектов, упомянутых в описании события. ТВОРЧЕСКИЙ ОТЧЕТ 054-10-2025-074.pdf - Целевое событие касается реализации творческих проектов для сохранения и популяризации традиционных ценностей, включая музыкальное, театральное и изобразительное искусство. Предоставленный текст описывает отчет о церемонии вручения Приза «Бенуа де ла Данс» 2025 года. Хотя оба связаны с культурой, отчет фокусируется на конкретном танцевальном призе, а не на комплексной поддержке традиционных ценностей, как указано в описании события. + ТВОРЧЕСКИЙ ОТЧЕТ 054-10-2025-075 Международный фестиваль русских театров «Встречи в России.pdf - Описание события касается реализации творческих проектов в сфере театрального искусства. Предоставленный документ описывает проведение Международного фестиваля русских театров, что является примером реализации творческого проекта. Фестиваль включает театральные постановки, что соответствует сфере театрального искусства, упомянутой в описании события. ТВОРЧЕСКИЙ ОТЧЕТ 054-10-2025-076.pdf - Описание события касается поддержки творческих проектов в сфере музыкального, театрального и изобразительного искусства. Предоставленный текст описывает проведение Большого летнего музыкального фестиваля «Сириус», который включает выступления из различных музыкальных коллективов и театров. Это напрямую связано с реализацией творческих мероприятий, упомянутых в описании события. ТВОРЧЕСКИЙ ОТЧЕТ 054-10-2025-077.pdf - Документ описывает программу международного фестиваля искусств, который включает симфонические, камерные и джазовые концерты. Это соответствует сфере музыкального искусства, упомянутой в описании события. Кроме того, в тексте упоминается о показателях результативности субсидии Министерства культуры РФ, что связано с поддержкой творческих проектов. + ТВОРЧЕСКИЙ ОТЧЕТ 054-10-2025-078.pdf - Событие касается реализации творческих проектов в сфере искусства, что соответствует теме сохранения и популяризации традиционных ценностей. В тексте упоминается проведение Международного музыкального фестиваля, который является творческим проектом. Это напрямую связано с поддержкой творческих проектов в области музыкального искусства, упомянутой в описании события. + ТВОРЧЕСКИЙ ОТЧЕТ 054-10-2025-079 Международный фестиваль Мстислава Ростроповича.pdf - Целевое событие касается реализации творческих проектов в сфере музыкального искусства. Предоставленный документ описывает отчет о проведении Международного фестиваля Мстислава Ростроповича, который включает оперу и фортепианный концерт. Это напрямую соответствует сфере музыкального искусства, упомянутой в описании события. + ТВОРЧЕСКИЙ ОТЧЕТ 054-10-2025-088.pdf - Описание события касается реализации творческих проектов в сфере музыкального искусства. Предоставленный документ отчитывается о музыкальном конкурсе «Голоса Родины», который является примером такого творческого проекта. Участие в конкурсе и его результаты напрямую связаны с популяризацией и поддержкой творческих инициатив. ТВОРЧЕСКИЙ ОТЧЕТ 054-10-2025-089.pdf - Документ описывает отчет о фестивале, который включал музыкальные и игровые спектакли, творческие встречи и концерты. Это соответствует направлению творческих проектов в сфере музыкального и театрального искусства, упомянутому в описании события. Фестиваль является примером реализации творческих мероприятий. + ТВОРЧЕСКИЙ ОТЧЕТ 054-10-2025-091.pdf - Описание события касается реализации творческих проектов в сфере музыкального и театрального искусства. Предоставленный документ отчитывается о реализации проекта «Национальный фестиваль и премия «Музыкальное сердце театра» (2025 г.). Это напрямую соответствует направлению поддержки творческих проектов, упомянутому в описании события. + ТВОРЧЕСКИЙ ОТЧЕТ 054-10-2025-092.pdf - Документ описывает реализацию всероссийского музыкального проекта, направленного на популяризацию классической музыки. Это соответствует общей теме реализации творческих проектов, упомянутой в описании события. Проект реализуется при поддержке Министерства культуры, что соответствует контексту поддержки творческих инициатив. ТВОРЧЕСКИЙ ОТЧЕТ 054-10-2025-093.pdf - Событие касается реализации творческих проектов в сфере искусства, что соответствует тематике отчета. В тексте упоминается фестиваль классической музыки, который является примером творческого мероприятия. Это напрямую связано с реализацией творческих проектов, упомянутых в описании события. + ТВОРЧЕСКИЙ ОТЧЕТ 054-10-2025-095.pdf - Текст описывает проведение музыкального фестиваля и реализацию мероприятий, что соответствует теме реализации творческих проектов. Упоминается получение финансовой поддержки в рамках грантового конкурса, что соотносится с оказанием поддержки творческим проектам. Это подтверждает реализацию творческих инициатив. ТВОРЧЕСКИЙ ОТЧЕТ 054-10-2025-096.pdf - Описание события включает поддержку творческих проектов в сфере театрального искусства. Предоставленный документ является отчетом о проведении Международного театрального фестиваля, который был организован на основании федеральной субсидии. Это напрямую соответствует реализации творческих проектов, упомянутых в описании события. + ТВОРЧЕСКИЙ ОТЧЕТ 054-10-2025-097.pdf - Документ описывает проведение Международного фестиваля академической музыки, что является примером творческого мероприятия. Это соответствует общей теме реализации творческих проектов, упомянутой в описании события. Фестиваль включает музыкальные выступления, что относится к сфере музыкального искусства, упомянутой в описании. ТВОРЧЕСКИЙ ОТЧЕТ 054-10-2025-109.pdf - Описание события касается реализации творческих проектов в сфере искусства, включая театральное. Предоставленный документ отчитывается о XVII Международном фестивале кукольных и синтетических театров «КУКАРТ». Фестиваль является примером реализации творческого проекта в области театрального искусства, что соответствует тематике события. + ТВОРЧЕСКИЙ ОТЧЕТ 054-10-2025-110 Концерт к 85-летию со дня рождения Давида Тухманова.pdf - Событие касается реализации творческих проектов в сфере музыкального искусства, что соответствует описанию. В тексте упоминается отчет о предоставлении субсидии на реализацию мероприятий в области музыкального, театрального и изобразительного искусства. Это напрямую связано с поддержкой творческих проектов, упомянутых в описании события. + ТВОРЧЕСКИЙ ОТЧЕТ 054-10-2025-111.pdf - Событие касается реализации творческих проектов в сфере искусства. Предоставленный текст описывает гала-концерт с участием известных артистов и детских коллективов. Это мероприятие является примером реализации творческого проекта, что соответствует тематике события. ТВОРЧЕСКИЙ ОТЧЕТ 054-10-2025-112.pdf - Документ описывает отчет о Фестивале искусств «Традиция», который включает музыкальные выступления, театральные спектакли и поэтические чтения. Это соответствует реализации творческих проектов в сфере искусства, упомянутых в описании события. Фестиваль проводился при поддержке Президентского фонда культурных инициатив, что также связано с поддержкой творческих проектов. ТВОРЧЕСКИЙ ОТЧЕТ 054-10-2025-113.pdf - Событие касается реализации творческих проектов в сфере искусства, что соответствует тематике документа. Документ описывает отчет о реализации творческого проекта, связанного с театральной премией. Это напрямую связано с реализацией творческих проектов, упомянутых в описании события. ТВОРЧЕСКИЙ ОТЧЕТ 054-10-2025-114.pdf - Документ описывает проведение Международного фестиваля искусств, который включает в себя театральные постановки, концерты и образовательные проекты. Это соответствует реализации творческих проектов в сфере искусства, упомянутых в описании события. Фестиваль является примером культурного мероприятия, направленного на популяризацию искусства. ТВОРЧЕСКИЙ ОТЧЕТ 054-10-2025-115.pdf - Описание события касается реализации творческих проектов в сфере музыкального искусства. Предоставленный текст описывает отчет о Международном военно-музыкальном фестивале «Спасская башня», который является музыкальным мероприятием. Это напрямую связано с реализацией творческих проектов, упомянутых в описании события. ТВОРЧЕСКИЙ ОТЧЕТ 054-10-2025-117.pdf - Событие касается реализации творческих проектов, направленных на сохранение и популяризацию традиционных ценностей. Предоставленный документ описывает отчет о фестивале детских духовых оркестров, который включал исполнение народного и военно-патриотического репертуара. Это соответствует реализации творческих проектов в сфере народного творчества. ТВОРЧЕСКИЙ ОТЧЕТ 054-10-2025-118.pdf - Документ описывает проведение международного фестиваля оперы и балета, что является примером творческого проекта. Этот проект реализуется при поддержке Министерства культуры РФ, что соответствует контексту оказания поддержки творческим проектам. Фестиваль включает в себя выступления ансамблей и премьеры, что относится к сферам искусства, упомянутым в описании события. ТВОРЧЕСКИЙ ОТЧЕТ 054-10-2025-119.pdf - Описание события касается реализации творческих проектов для сохранения и популяризации традиционных ценностей. Предоставленный текст описывает проект, целью которого является "сохранение традиционных ценностей, популяризация истории и культуры российского казачества". Это напрямую соответствует тематике целевого события. ТВОРЧЕСКИЙ ОТЧЕТ 054-10-2025-121.pdf - Документ описывает реализацию творческого проекта «Пленэры молодых художников регионов России», что соответствует теме реализации творческих проектов. Проект связан с изобразительным искусством, которое является одной из сфер, упомянутых в описании события. Таким образом, отчет подтверждает реализацию творческой деятельности. + ТВОРЧЕСКИЙ ОТЧЕТ 054-10-2025-122.pdf - Описание события касается реализации творческих проектов в сфере музыкального и изобразительного искусства. Предоставленный документ является отчетом о музыкальном фестивале, что соответствует сфере музыкального искусства. Фестиваль был организован и имел определенную стоимость, что указывает на реализацию творческого проекта. ТВОРЧЕСКИЙ ОТЧЕТ 054-10-2025-123.pdf - Описание события касается реализации творческих проектов, направленных на сохранение и популяризацию традиционных ценностей. Предоставленный текст описывает отчет о проекте, который также направлен на продвижение традиционных ценностей и развитие театрального искусства. Таким образом, отчет напрямую связан с тематикой реализации творческих проектов. + ТВОРЧЕСКИЙ ОТЧЕТ 054-10-2025-124.pdf - Документ описывает реализацию проекта, направленного на поддержку детского театрального искусства, что соответствует сфере творческих проектов. В описании события упоминается поддержка творческих проектов в сфере театрального искусства. Проект включает мастер-классы и конференцию, что является формой реализации творческих инициатив. + ТВОРЧЕСКИЙ ОТЧЕТ 054-10-2025-125.pdf - Текст описывает реализацию Всероссийского фестиваля для детей и молодежи, что соответствует направлению поддержки творческих проектов. Упоминание конкурсных показов спектаклей и мастер-классов в области театрального искусства прямо связано с популяризацией творческих ценностей. Это подтверждает реализацию творческих проектов в сфере искусства. + ТВОРЧЕСКИЙ ОТЧЕТ 054-10-2025-126.pdf - The event focuses on supporting creative projects in music, theater, and fine arts to preserve traditional values. The evidence details the implementation of a project supporting musical theaters and mentions various festivals and performances. This directly relates to the scope of creative pr | P13: =VLOOKUP(A13,Характеристика!$A$1:$D$100,4,0) -> Подтверждено | Q13: {=_xlfn.IFS(AND(P13=R13,T13="нет"),"нет",AND(P13=R13,T13="да"),"да",AND(P13<>R13,T13="нет"),"да",AND(P13<>R13,T13="да"),"нет")} -> #N/A | R13: =VLOOKUP(B13,'Старый ИИ'!A:AQ,9,FALSE) -> Подтверждено | S13: =VLOOKUP(B13,'Старый ИИ'!A:AQ,11,FALSE) -> В приложенном документе прямо указан отчет с заголовком «Отчет об исполнении результата “Реализованы творческие проекты, направленные на сохранение и популяризацию традиционных ценностей” … по итогам 2025 года», и далее по тексту мероприятие/результат описывается именно как реализация творческих проектов, направленных на сохранение и популяризацию традиционных ценностей (то есть формулировка совпадает по сути и по названию). | T13: =VLOOKUP(B13,'Старый ИИ'!A:AQ,12,FALSE) -> #N/A | U13: =VLOOKUP(B13,'Старый ИИ'!A:AQ,13,FALSE) -> #N/A | V13: =VLOOKUP(B13,'Старый ИИ'!A:AQ,14,FALSE) -> #N/A | W13: =VLOOKUP(B13,'ПХР актуальный'!$A$1:$C$34,3,0) -> #NUM! | X13: =VLOOKUP(B13,'Результат и ПХР'!$A$1:$Q$992,14,0) -> Основой вывода выбран summary документа "Подтверждающие сведения 9.pdf". В evidence явно подтверждены метрика "Общее количество публикаций в СМИ, включая электронные коммуникационные системы и иные информационные сети (не запрещенные на территории РФ)", требуемая характеристика объекта и привязка количества к самому объекту метрики; зафиксировано значение 2426 Единица. Ключевой фрагмент evidence: "План по публикациям в СМИ (500 ед.) был значительно перевыполнен: зафиксировано 2 426 публикаций.". Поэтому строгие правила ПХР выполнены, и итоговый статус установлен как "подтверждено". | Y13: =VLOOKUP(B13,'Результат и ПХР'!$A$1:$Q$992,7,0) -> подтверждено | Z13: {=_xlfn.IFS(AND(Y13=AA13,AC13="нет"),"нет",AND(Y13=AA13,AC13="да"),"да",AND(Y13<>AA13,AC13="нет"),"да",AND(Y13<>AA13,AC13="да"),"нет")} -> #N/A | AA13: =VLOOKUP(B13,'Старый ИИ'!A:AQ,21,FALSE) -> Не применимо | AB13: =VLOOKUP(B13,'Старый ИИ'!A:AQ,23,FALSE) -> Анализ ПХР пропущен: показатели ПХР не указаны для данного мероприятия | AC13: =VLOOKUP(B13,'Старый ИИ'!A:AQ,24,FALSE) -> #N/A | AD13: =VLOOKUP(B13,'Старый ИИ'!A:AQ,25,FALSE) -> #N/A | AE13: =VLOOKUP(B13,'Старый ИИ'!A:AQ,26,FALSE) -> #N/A | AF13: =VLOOKUP(B13,Общий!$E$2:$O$2000,10,0) -> 140 | AG13: =VLOOKUP(B13,Общий!$E$2:$O$2000,11,0) -> Единица | AH13: =VLOOKUP(B13,'Результат и ПХР'!$A$1:$M$992,13,0) -> Основой вывода выбран summary документа "Подтверждающие сведения 9.pdf". В evidence найдены действие "Реализовано", объект "творческих проектов", сигнал завершения "реализовано" и фактическое значение 50 проектов. Ключевой фрагмент evidence: "В отчетном периоде реализовано 50 проектов". Сравнение результата определено как below_target, поэтому статус мероприятия установлен как "подтверждено". | AI13: =VLOOKUP(B13,'Результат и ПХР'!$A$1:$T$992,6,0) -> подтверждено | AJ13: #N/A | AK13: =VLOOKUP(B13,'Старый ИИ'!A:AQ,27,FALSE) -> Подтверждено | AL13: =VLOOKUP(B13,'Старый ИИ'!A:AQ,29,FALSE) -> В отчёте прямо указано, что по состоянию на 31.12.2025 по результату «Реализованы творческие проекты…» реализовано 140 проектов (при плановом значении нарастающим итогом в 2025 году — 140). Это соответствует KPI 140 единиц (и не ниже него). | AM13: =VLOOKUP(B13,'Старый ИИ'!A:AQ,30,FALSE) -> #N/A | AN13: =VLOOKUP(B13,'Старый ИИ'!A:AQ,31,FALSE) -> #N/A | AO13: =VLOOKUP(B13,'Старый ИИ'!A:AQ,32,FALSE) -> #N/A
A14: 9191447905 | B14: 9206711672 | C14: Проведены культурно-просветительские программы для школьников | D14: Культурно-просветительские программы для школьников - это программы, которые предусматривают посещения школьниками среднего и старшего возрастов историко-культурных и познавательных объектов показа (Города-Герои и Города Воинской славы, объекты всемирного наследия ЮНЕСКО, музеи), которые способствуют патриотическому и духовно-нравственному воспитанию детей и молодежи, а также увеличению посещаемости музейных учреждений. В программах традиционно участвуют победители олимпиад и конкурсов, учащиеся школ искусств и кадетских корпусов. Квоты для участия в программах предоставляются для всех субъектов Российской Федерации. Значение результата к 2030 году: к концу 2024 года проведено 314 культурно-просветительских программ, в 2025-2030 годах будет проведено 210 культурно-просветительских программ, участниками которых станут не менее 360 000 школьников. С 2019 по 2030 гг. будет проведено 524 культурно-просветительские программы. Эффект для бенефициаров и вклад в достижение показателя: К концу 2024 года участниками программы стали более 443 тысяч школьников, с 2025 по 2030 гг. участникам станут не менее 360 000 школьников (ежегодно около 60 000 школьников). С 2019-2030 гг. участниками станут не менее 803 тысяч школьников. | E14: =VLOOKUP(B14,Подпись!$A$1:$E$100,5,0) -> #N/A | F14: =VLOOKUP(B14,Подпись!$A$1:$E$100,2,0) -> #N/A | G14: #N/A | H14: {=_xlfn.IFS(AND(G14=I14,K14="нет"),"нет",AND(G14=I14,K14="да"),"да",AND(G14<>I14,K14="нет"),"да",AND(G14<>I14,K14="да"),"нет")} -> #N/A | I14: =VLOOKUP(B14,'Старый ИИ'!A:AQ,3,FALSE) -> Не подтверждено | J14: =VLOOKUP(B14,'Старый ИИ'!A:AQ,5,FALSE) -> Найдены подписи: Сухорукова ЕГ, но они не совпадают с ответственными лицами | K14: =VLOOKUP(B14,'Старый ИИ'!A:AQ,6,FALSE) -> нет | L14: =VLOOKUP(B14,'Старый ИИ'!A:AQ,7,FALSE) -> да | M14: =VLOOKUP(B14,'Старый ИИ'!A:AQ,8,FALSE) -> ИИ пишет о найденной подписи ответственного исполнителя, но в статусе не подтверждает ее. | N14: Культурно-просветительские программы для школьников - это программы, которые предусматривают посещения школьниками среднего и старшего возрастов историко-культурных и познавательных объектов показа (Города-Герои и Города Воинской славы, объекты всемирного наследия ЮНЕСКО, музеи), которые способствуют патриотическому и духовно-нравственному воспитанию детей и молодежи, а также увеличению посещаемости музейных учреждений. В программах традиционно участвуют победители олимпиад и конкурсов, учащиеся школ искусств и кадетских корпусов. Квоты для участия в программах предоставляются для всех субъектов Российской Федерации. Значение результата к 2030 году: к концу 2024 года проведено 314 культурно-просветительских программ, в 2025-2030 годах будет проведено 210 культурно-просветительских программ, участниками которых станут не менее 360 000 школьников. С 2019 по 2030 гг. будет проведено 524 культурно-просветительские программы. Эффект для бенефициаров и вклад в достижение показателя: К концу 2024 года участниками программы стали более 443 тысяч школьников, с 2025 по 2030 гг. участникам станут не менее 360 000 школьников (ежегодно около 60 000 школьников). С 2019-2030 гг. участниками станут не менее 803 тысяч школьников. | O14: =VLOOKUP(A14,Характеристика!$A$1:$D$100,2,0) -> Подтверждающие сведения 5.pdf - Документ прямо упоминает организацию культурно-просветительских программ для школьников (10–18 лет). Эти программы проводятся в рамках нацпроекта «Семья», что соответствует тематике события. В тексте указаны конкретные договоры и параметры этих программ. Подтверждающие сведения 6.pdf - Документ содержит акты сдачи-приемки услуг по реализации культурно-просветительских программ для школьников. Это напрямую соответствует теме события, которое описывает проведение таких программ. В тексте указаны объемы, включающие количество участников, что подтверждает реализацию программы. Подтверждающие сведения 7.pdf - Документ представляет собой отчет об исполнении культурно-просветительских программ для школьников. В нем указано количество проведенных программ и число участников за 2025 год. Это напрямую соответствует теме события, описанного как проведение таких программ. | P14: =VLOOKUP(A14,Характеристика!$A$1:$D$100,4,0) -> Подтверждено | Q14: {=_xlfn.IFS(AND(P14=R14,T14="нет"),"нет",AND(P14=R14,T14="да"),"да",AND(P14<>R14,T14="нет"),"да",AND(P14<>R14,T14="да"),"нет")} -> да | R14: =VLOOKUP(B14,'Старый ИИ'!A:AQ,9,FALSE) -> Подтверждено | S14: =VLOOKUP(B14,'Старый ИИ'!A:AQ,11,FALSE) -> Отчет подтверждает проведение культурно-просветительских программ для школьников: в пункте 1 указано «оказанных услуг ... по организации и проведению культурно-просветительских программ для школьников»; таблицы 3‑10 перечисляют конкретные маршруты и количество участников по регионам, а итоговое количество участников составляет 7 872. Это полностью соответствует заявленному мероприятию. | T14: =VLOOKUP(B14,'Старый ИИ'!A:AQ,12,FALSE) -> да | U14: =VLOOKUP(B14,'Старый ИИ'!A:AQ,13,FALSE) -> да | V14: =VLOOKUP(B14,'Старый ИИ'!A:AQ,14,FALSE) -> - | W14: =VLOOKUP(B14,'ПХР актуальный'!$A$1:$C$34,3,0) -> #NUM! | X14: =VLOOKUP(B14,'Результат и ПХР'!$A$1:$Q$992,14,0) -> #N/A | Y14: =VLOOKUP(B14,'Результат и ПХР'!$A$1:$Q$992,7,0) -> #N/A | Z14: {=_xlfn.IFS(AND(Y14=AA14,AC14="нет"),"нет",AND(Y14=AA14,AC14="да"),"да",AND(Y14<>AA14,AC14="нет"),"да",AND(Y14<>AA14,AC14="да"),"нет")} -> #N/A | AA14: =VLOOKUP(B14,'Старый ИИ'!A:AQ,21,FALSE) -> Подтверждено | AB14: =VLOOKUP(B14,'Старый ИИ'!A:AQ,23,FALSE) -> Отчёт подтверждает, что фактическое количество участников в 2025 году равно плановому значению 60 000 человек. Следовательно, цель по количеству участников достигнута. | AC14: =VLOOKUP(B14,'Старый ИИ'!A:AQ,24,FALSE) -> да | AD14: =VLOOKUP(B14,'Старый ИИ'!A:AQ,25,FALSE) -> нет | AE14: =VLOOKUP(B14,'Старый ИИ'!A:AQ,26,FALSE) -> Корректно по статусу, но некорректно по анализу. ИИ соотносит некорректное количество ПХР. ПХР по подтверждающим документам выполнена. | AF14: =VLOOKUP(B14,Общий!$E$2:$O$2000,10,0) -> 349 | AG14: =VLOOKUP(B14,Общий!$E$2:$O$2000,11,0) -> Единица | AH14: =VLOOKUP(B14,'Результат и ПХР'!$A$1:$M$992,13,0) -> #N/A | AI14: =VLOOKUP(B14,'Результат и ПХР'!$A$1:$T$992,6,0) -> #N/A | AJ14: #N/A | AK14: =VLOOKUP(B14,'Старый ИИ'!A:AQ,27,FALSE) -> Подтверждено | AL14: =VLOOKUP(B14,'Старый ИИ'!A:AQ,29,FALSE) -> В отчете (стр. 1) указано плановое значение 349 ед., а фактическое количество проведённых программ = 379 ед. (стр. 1). Факт превышает план, значит KPI полностью выполнен и подтверждён. | AM14: =VLOOKUP(B14,'Старый ИИ'!A:AQ,30,FALSE) -> да | AN14: =VLOOKUP(B14,'Старый ИИ'!A:AQ,31,FALSE) -> да | AO14: =VLOOKUP(B14,'Старый ИИ'!A:AQ,32,FALSE) -> -
A15: 9193757673 | B15: 9206711696 | C15: Проведены выставочные проекты федеральных и региональных музеев в субъектах Российской Федерации | D15: Организация передвижных выставочных проектов, для демонстрации культурных ценностей в различных регионах Российской Федерации в целях обеспечения доступа населения к культурным благам. Значение результата к 2030 году: C 2019 по 2024 год проведено 53 проекта, с охватом 360 тыс. человек во всех субъектах Российской Федерации. С 2025 по 2030 год будет проведено 96 проектов с охватом 720 тысяч человек. С 2019 по 2030 гг. будет проведено 149 проектов с охватом 1 080 тысяч человек. Эффект для бенефициаров и вклад в достижение показателя: Повышение доступа населения Российской Федерации к культурным благам, демонстрация знаковых экспонатов из музейных коллекций музеев мирового уровня в регионах Российской Федерации. | E15: =VLOOKUP(B15,Подпись!$A$1:$E$100,5,0) -> Алексеева Жанна Владимировна - Статс-секретарь - заместитель Министра культуры Российской Федерации, Любимова Ольга Борисовна, Обрывалин Сергей Геннадьевич, Алексеева Жанна Владимировна, Осинцев Владимир Геннадьевич, Малышев Андрей Владимирович, Першин Сергей Васильевич | F15: =VLOOKUP(B15,Подпись!$A$1:$E$100,2,0) -> Алексеева Жанна Владимировна | G15: Подтверждено | H15: {=_xlfn.IFS(AND(G15=I15,K15="нет"),"нет",AND(G15=I15,K15="да"),"да",AND(G15<>I15,K15="нет"),"да",AND(G15<>I15,K15="да"),"нет")} -> нет | I15: =VLOOKUP(B15,'Старый ИИ'!A:AQ,3,FALSE) -> Не подтверждено | J15: =VLOOKUP(B15,'Старый ИИ'!A:AQ,5,FALSE) -> OCR обнаружил подписи, но анализ текста их не подтвердил. Возможно проблемы с качеством скана или распознаванием. | K15: =VLOOKUP(B15,'Старый ИИ'!A:AQ,6,FALSE) -> да | L15: =VLOOKUP(B15,'Старый ИИ'!A:AQ,7,FALSE) -> нет | M15: =VLOOKUP(B15,'Старый ИИ'!A:AQ,8,FALSE) -> ИИ корректно не принимает мероприятие - так как в документах стоит подпись не ответственного исполнителя, но в обосновании пишет о технической ошибке. Нет корректного обоснования какие подписи найдены. | N15: Организация передвижных выставочных проектов, для демонстрации культурных ценностей в различных регионах Российской Федерации в целях обеспечения доступа населения к культурным благам. Значение результата к 2030 году: C 2019 по 2024 год проведено 53 проекта, с охватом 360 тыс. человек во всех субъектах Российской Федерации. С 2025 по 2030 год будет проведено 96 проектов с охватом 720 тысяч человек. С 2019 по 2030 гг. будет проведено 149 проектов с охватом 1 080 тысяч человек. Эффект для бенефициаров и вклад в достижение показателя: Повышение доступа населения Российской Федерации к культурным благам, демонстрация знаковых экспонатов из музейных коллекций музеев мирового уровня в регионах Российской Федерации. | O15: =VLOOKUP(A15,Характеристика!$A$1:$D$100,2,0) -> ’¢®àç¥áª¨© ®âç¥â ”®­¤ ’ ¢®«£ ‘­ë ‘¨¡¨à¨.pdf - Документ описывает творческий отчет по выставочному проекту «Сны Сибири», который реализуется в региональных художественных музеях. Это соответствует теме организации передвижных выставочных проектов в субъектах Российской Федерации. Проект демонстрирует культурное и археологическое наследие, что соответствует цели обеспечения доступа населения к культурным благам. ’¢®àç¥áª¨© ®âç¥â „¥©­¥ª .pdf - Документ описывает реализацию выставки, которая проходила в регионах (Рязань и Тула). Это соответствует теме организации выставочных проектов в субъектах Российской Федерации. Упоминание о том, что проект получил освещение в региональных и федеральных СМИ, также подтверждает контекст. Таким образом, документ относится к теме проведения выставочных проектов. ’¢®àç¥áª¨© ®âç¥â ˆ¬¯¥à â®àáª¨© ¬ àèàãâ.pdf - Документ описывает реализацию выставочного проекта, который включает экспонаты из множества музеев. Это соответствует теме проведения выставочных проектов федеральных и региональных музеев. Проект организован при поддержке Министерства культуры РФ, что связано с культурными инициативами в РФ. ’¢®àç¥áª¨© ®âç¥â ƒˆŒ ˜ª âã«ª .pdf - Документ описывает реализацию выставки, что соответствует теме проведения выставочных проектов. Упоминается демонстрация произведений искусства в региональных музеях, таких как Астраханский музей-заповедник и Пензенская областная картинная галерея. Это прямо связано с целью обеспечения доступа населения к культурным благам в регионах РФ. ’¢®àç¥áª¨© ®âç¥â ƒ–Œ‘ˆ Œ ïª¨ àãááª®£® ¬¨à .pdf - Документ описывает реализацию выставочного проекта, что соответствует теме организации выставочных проектов. Проект включал транспортировку и экспонирование музейных предметов в региональных музеях. Это напрямую связано с целью демонстрации культурных ценностей в различных регионах Российской Федерации. ’¢®àç¥áª¨© ®âç¥â ƒ–Œ‘ˆ Žª­ ’€‘‘.pdf - Документ описывает реализацию выставочного проекта «Окна ТАСС», что соответствует теме проведения выставочных проектов. Проект проходил в различных городах, что соответствует цели демонстрации культурных ценностей в регионах Российской Федерации. Упоминание о размещении подлинных экспонатов подтверждает связь с музейной деятельностью. ’¢®àç¥áª¨© ®âç¥â Œã§¥© ª¨­® ‘®¡¨à â¥«¨.pdf - Документ описывает реализацию передвижной выставки «Собиратели земель русских», что соответствует теме организации передвижных выставочных проектов. Выставка проводилась в различных регионах Российской Федерации, включая Рязань, Тульскую область и Воронеж. Это напрямую поддерживает цель демонстрации культурных ценностей в регионах. ’¢®àç¥áª¨© ®âç¥â áª®¢áª¨© ¬ã§¥©.pdf - Документ описывает творческий отчет по выставочному проекту, реализованному музеем. Этот проект соответствует теме организации выставочных проектов федеральных и региональных музеев. Упоминается конкретный музей и проведение выставки в разных городах, что подтверждает реализацию подобных мероприятий. ’¢®àç¥áª¨© ®âç¥â ãááª¨© ¬ã§¥© ‘¥à®¢.pdf - Документ описывает выставку «Валентин Серов», которая демонстрировалась в музеях Сибирского федерального округа. Это соответствует теме организации выставочных проектов в субъектах Российской Федерации. Упоминание о демонстрации экспонатов из различных музеев подтверждает контекст мероприятия. ’¢®àç¥áª¨© ®âç¥â åàãèª «¨á¥æª ï ®«îá ¬ £¨¨.pdf - Документ описывает реализацию выставочного проекта «Плисецкая. Полюс магии», который проходил в различных городах, таких как Казань, Рязань и Тула. Это соответствует теме организации выставочных проектов в субъектах Российской Федерации. Проект демонстрирует культурные ценности, что соответствует цели мероприятия. ’¢®àç¥áª¨© ®âç¥â Ž‘ˆ‡Ž.pdf - Документ описывает реализацию выставочного проекта «Народные художественные промыслы», который включал перемещение экспозиций по маршрутам в различных регионах. Это соответствует теме организации передвижных выставочных проектов в субъектах Российской Федерации. Упоминаются конкретные музеи и регионы, что подтверждает контекст мероприятия. ’¢®àç¥áª¨© ®âç¥â „ ˆ à¨¤ã¬ ­® ¨ á¤¥« ­® ¢ ®áá¨¨.pdf - Документ описывает реализацию передвижной выставки «Придумано и сделано в России», что соответствует теме организации передвижных выставочных проектов. Выставка включала музейные экспонаты, что связано с демонстрацией культурных ценностей. Упоминание о проведении выставки в регионах подтверждает контекст мероприятия. Ž’—…’ à®¤ë ®áá¨¨. ®«ìè ï á¥¬ìï - ®¡é ï ¨áâ®à¨ï.pdf - Документ описывает реализацию выставочного проекта «Народы России. Большая семья — общая история». Этот проект демонстрирует культурные ценности из музейных коллекций, что соответствует цели организации передвижных выставочных проектов. Упоминается участие Национального музея РМ им. Т. Евсеева, что подтверждает связь с музейной деятельностью в регионах. Отчет Кижи.pdf - Документ описывает реализацию проекта, который включал тематические выставки в музеях, что соответствует теме проведения выставочных проектов. Упоминаются музейные предметы и участие в рамках нацпроекта, что связано с культурными ценностями. Проект реализован в музее-заповеднике «Кижи», который является субъектом Российской Федерации. Подтверждающие сведения 2.pdf - Документ содержит отчет о проведении выставочных проектов музеев в рамках федерального проекта. Это напрямую соответствует теме мероприятия о проведении выставочных проектов федеральных и региональных музеев. Упоминаются конкретные цифры по проведенным проектам и охвату посетителей. Территория культуры Семья душа России творческий отчет.pdf - Документ описывает реализацию выставки, в экспозиции которой были представлены произведения из собраний федеральных и региональных музеев. Это соответствует теме проведения выставочных проектов федеральных и региональных музеев. Упоминание о демонстрации экспонатов из музейных коллекций подтверждает связь с целью мероприятия. 弔ｮ珸･皙ｨｩ ｮ粡･ 蔓珮ｪｮ･ 皈ｫｮ 尚涬 ｨ 譬瑟.pdf - Документ описывает реализацию передвижной выставки «Поэт и царь», что соответствует теме организации передвижных выставочных проектов. Выставка была организована совместно крупными музеями, что соответствует контексту федеральных и региональных музеев. Проект охватил несколько городов, что подтверждает реализацию в различных регионах. 蝿項祇弔ｮ珸･皙ｨｩ_ｮ粡･秬ｯｮ_｢ 笄｢ｮ遲ｮｬ綫ｯ牋･ｪ粤_枢 駐逗_準検宙.pdf - Документ описывает реализацию выставочного проекта, что соответствует теме проведения выставочных проектов. Проект посвящен архитектуре и включает экспозиции, что связано с демонстрацией культурных ценностей. Упоминаются конкретные города (Нижний Новгород, Улан-Удэ, Смоленск), что соответствует охвату в субъектах Российской Федерации. | P15: =VLOOKUP(A15,Характеристика!$A$1:$D$100,4,0) -> Подтверждено | Q15: {=_xlfn.IFS(AND(P15=R15,T15="нет"),"нет",AND(P15=R15,T15="да"),"да",AND(P15<>R15,T15="нет"),"да",AND(P15<>R15,T15="да"),"нет")} -> да | R15: =VLOOKUP(B15,'Старый ИИ'!A:AQ,9,FALSE) -> Подтверждено | S15: =VLOOKUP(B15,'Старый ИИ'!A:AQ,11,FALSE) -> Отчет полностью подтверждает выполнение мероприятия: в нём указано, что к 31.12.2025 г. проведено 70 выставочных проектов федеральных и региональных музеев (превышая план 69), приведён перечень из 17 проектов 2025 г., а также зафиксировано количество посетителей – 849 189 человек (план 480 000). Эти данные соответствуют заявленному мероприятию «Проведены выставочные проекты федеральных и региональных музеев в субъектах Российской Федерации». | T15: =VLOOKUP(B15,'Старый ИИ'!A:AQ,12,FALSE) -> да | U15: =VLOOKUP(B15,'Старый ИИ'!A:AQ,13,FALSE) -> да | V15: =VLOOKUP(B15,'Старый ИИ'!A:AQ,14,FALSE) -> - | W15: =VLOOKUP(B15,'ПХР актуальный'!$A$1:$C$34,3,0) -> #NUM! | X15: =VLOOKUP(B15,'Результат и ПХР'!$A$1:$Q$992,14,0) -> Основой вывода выбран ocr документа "’¢®àç¥áª¨© ®âç¥â ”®­¤ ’ ¢®«£ ‘­ë ‘¨¡¨à¨.pdf". В evidence явно подтверждены метрика "Количество посетителей выставочных проектов федеральных и региональных музеев в субъектах Российской Федерации", требуемая характеристика объекта и привязка количества к самому объекту метрики; зафиксировано значение 3781 Человек. Ключевой фрагмент evidence: "Сообщаем, что выставку «Сны Сибири», работающую в Галерее сибирского искусства Иркутского областного художественного музея им. В. П. Сукачева, с 14 ноября по 22 декабря 2025 г. посетило 3 781 человек (в т.ч. 257 - по Пушкинской карте).". Поэтому строгие правила ПХР выполнены, и итоговый статус установлен как "подтверждено". | Y15: =VLOOKUP(B15,'Результат и ПХР'!$A$1:$Q$992,7,0) -> не подтверждено | Z15: {=_xlfn.IFS(AND(Y15=AA15,AC15="нет"),"нет",AND(Y15=AA15,AC15="да"),"да",AND(Y15<>AA15,AC15="нет"),"да",AND(Y15<>AA15,AC15="да"),"нет")} -> нет | AA15: =VLOOKUP(B15,'Старый ИИ'!A:AQ,21,FALSE) -> Подтверждено | AB15: =VLOOKUP(B15,'Старый ИИ'!A:AQ,23,FALSE) -> Отчёт подтверждает проведение выставочных проектов: в разделе «По состоянию на 31.12.2025… проведено 70 выставочных проектов», что превышает плановое значение 69 ед. (стр. 1). Перечень проектов (стр. 1‑2) и данные о посетителях (849 189 чел.) также присутствуют, что полностью соответствует заявленному мероприятию. | AC15: =VLOOKUP(B15,'Старый ИИ'!A:AQ,24,FALSE) -> да | AD15: =VLOOKUP(B15,'Старый ИИ'!A:AQ,25,FALSE) -> нет | AE15: =VLOOKUP(B15,'Старый ИИ'!A:AQ,26,FALSE) -> Корректно по статусу, но некорректно по анализу. ИИ соотносит некорректное количество ПХР. | AF15: =VLOOKUP(B15,Общий!$E$2:$O$2000,10,0) -> 69 | AG15: =VLOOKUP(B15,Общий!$E$2:$O$2000,11,0) -> Единица | AH15: =VLOOKUP(B15,'Результат и ПХР'!$A$1:$M$992,13,0) -> Основой вывода выбран ocr документа "’¢®àç¥áª¨© ®âç¥â ”®­¤ ’ ¢®«£ ‘­ë ‘¨¡¨à¨.pdf". В evidence найдены действие "Проведены выставочные проекты федеральных и региональных музеев в субъектах Российской Федерации", объект "Организация передвижных выставочных проектов, для демонстрации культурных ценностей в различных регионах Российской Федерации в целях обеспечения доступа населения к культурным благам.", сигнал завершения "посетило" и фактическое значение 8150 человек. Ключевой фрагмент evidence: "Сообщаем, что выставку «Сны Сибири», работающую в Галерее сибирского искусства Иркутского областного художественного музея им. В. П. Сукачева, с 14 ноября по 22 декабря 2025 г. посетило 3 781 человек (в т.ч. 257 - по Пушкинской карте). Справка Сообщаем, что выставку «Сны Сибири», работающую в Государственном автономном учреждении культуры Новосибирской области «Новосибирский государственный художественный музей», с 27 ноября по 22 декабря 2025 года посетило 4 369 человек (в том числе 327 — по Пушкинской карте).". Сравнение результата определено как meets_target, поэтому статус мероприятия установлен как "подтверждено". | AI15: =VLOOKUP(B15,'Результат и ПХР'!$A$1:$T$992,6,0) -> не подтверждено | AJ15: нет | AK15: =VLOOKUP(B15,'Старый ИИ'!A:AQ,27,FALSE) -> Подтверждено | AL15: =VLOOKUP(B15,'Старый ИИ'!A:AQ,29,FALSE) -> Плановое значение KPI – 69 единиц (см. «значение мероприятия»). В отчете указано, что проведено 70 выставочных проектов (стр. 1). Факт превышает план, тем самым KPI выполнен и даже превзойден, но значение не совпадает точно с запланированным. | AM15: =VLOOKUP(B15,'Старый ИИ'!A:AQ,30,FALSE) -> да | AN15: =VLOOKUP(B15,'Старый ИИ'!A:AQ,31,FALSE) -> да | AO15: =VLOOKUP(B15,'Старый ИИ'!A:AQ,32,FALSE) -> -
A16: 9187094209 | B16: 9206750237 | C16: Оснащены региональные и муниципальные театры, находящиеся в городах с численностью населения более 300 тыс. человек | D16: Оснащение театров, расположенных в крупных городах, современным оборудованием, необходимым для осуществления творческой деятельности. Значение результата к 2030 году: к концу 2024 года мероприятия по оснащению проведены в 131 театре. Новое оборудование в 2025 году приобретут 30 театров, а с 2026 года оснащаться новым оборудованием будут не менее 50 театров ежегодно (2026 г. - 50, 2027 г. - 51, 2028 г. - 52, 2029 г. - 52, 2030 г. - 52). Таким образом, с 2023 года к 2030 году потребность в частичном оснащении по основным группам оборудования (свет, звук) будет полностью удовлетворена на 100%. Эффект для бенефициаров и вклад в достижение показателя: - оснащение по основным группам оборудования (световым, звуковым) позволит значительно расширить художественные возможности театров и повысить качество постановок, что способствует привлечению в театры новых зрителей и, как следствие, увеличивает количество посещений организаций культуры; - в рамках ГП Развитие культуры регионам предоставляется субсидия на поддержку творческой деятельности театров (средства могут быть направлены на создание новых постановок и показов спектаклей, а также на укрепление материально-технической базы театров); - качественно новые постановки, созданные в модернизированных театрах, могут быть выдвинуты в качестве соискателей премии Минкультуры России имени Федора Волкова за вклад в развитие театрального искусства Российской Федерации. | E16: =VLOOKUP(B16,Подпись!$A$1:$E$100,5,0) -> Алексеева Жанна Владимировна - Статс-секретарь - заместитель Министра культуры Российской Федерации, Любимова Ольга Борисовна, Обрывалин Сергей Геннадьевич, Алексеева Жанна Владимировна, Осинцев Владимир Геннадьевич, Малышев Андрей Владимирович, Першин Сергей Васильевич | F16: =VLOOKUP(B16,Подпись!$A$1:$E$100,2,0) -> Малышев Андрей Владимирович | G16: Подтверждено | H16: {=_xlfn.IFS(AND(G16=I16,K16="нет"),"нет",AND(G16=I16,K16="да"),"да",AND(G16<>I16,K16="нет"),"да",AND(G16<>I16,K16="да"),"нет")} -> да | I16: =VLOOKUP(B16,'Старый ИИ'!A:AQ,3,FALSE) -> Не подтверждено | J16: =VLOOKUP(B16,'Старый ИИ'!A:AQ,5,FALSE) -> Найдены подписи: генеральный директор, ответственный за правильность оформления факта хозяйственной жизни; ответственный за правильность оформления факта хозяйственной жизни, но они не совпадают с ответственными лицами | K16: =VLOOKUP(B16,'Старый ИИ'!A:AQ,6,FALSE) -> нет | L16: =VLOOKUP(B16,'Старый ИИ'!A:AQ,7,FALSE) -> нет | M16: =VLOOKUP(B16,'Старый ИИ'!A:AQ,8,FALSE) -> ИИ не нашел в документе подпись ответственного исполнителя. | N16: Оснащение театров, расположенных в крупных городах, современным оборудованием, необходимым для осуществления творческой деятельности. Значение результата к 2030 году: к концу 2024 года мероприятия по оснащению проведены в 131 театре. Новое оборудование в 2025 году приобретут 30 театров, а с 2026 года оснащаться новым оборудованием будут не менее 50 театров ежегодно (2026 г. - 50, 2027 г. - 51, 2028 г. - 52, 2029 г. - 52, 2030 г. - 52). Таким образом, с 2023 года к 2030 году потребность в частичном оснащении по основным группам оборудования (свет, звук) будет полностью удовлетворена на 100%. Эффект для бенефициаров и вклад в достижение показателя: - оснащение по основным группам оборудования (световым, звуковым) позволит значительно расширить художественные возможности театров и повысить качество постановок, что способствует привлечению в театры новых зрителей и, как следствие, увеличивает количество посещений организаций культуры; - в рамках ГП Развитие культуры регионам предоставляется субсидия на поддержку творческой деятельности театров (средства могут быть направлены на создание новых постановок и показов спектаклей, а также на укрепление материально-технической базы театров); - качественно новые постановки, созданные в модернизированных театрах, могут быть выдвинуты в качестве соискателей премии Минкультуры России имени Федора Волкова за вклад в развитие театрального искусства Российской Федерации. | O16: =VLOOKUP(A16,Характеристика!$A$1:$D$100,2,0) -> #N/A | P16: =VLOOKUP(A16,Характеристика!$A$1:$D$100,4,0) -> #N/A | Q16: {=_xlfn.IFS(AND(P16=R16,T16="нет"),"нет",AND(P16=R16,T16="да"),"да",AND(P16<>R16,T16="нет"),"да",AND(P16<>R16,T16="да"),"нет")} -> #N/A | R16: =VLOOKUP(B16,'Старый ИИ'!A:AQ,9,FALSE) -> Подтверждено | S16: =VLOOKUP(B16,'Старый ИИ'!A:AQ,11,FALSE) -> В отчете за 29.08.2025 подтверждается покупка оборудования (пульт помощника режиссера) на сумму 350 400 ₽ для ИРКУТСКОГО МУЗЫКАЛЬНОГО ТЕАТРА ИМ. Н.М. ЗАГУРСКОГО (город с населением >300 тыс.). Это свидетельствует о выполнении мероприятия по оснащению театра в крупном городе, однако документ охватывает лишь один объект, поэтому оценка 4 из 5. | T16: =VLOOKUP(B16,'Старый ИИ'!A:AQ,12,FALSE) -> да | U16: =VLOOKUP(B16,'Старый ИИ'!A:AQ,13,FALSE) -> да | V16: =VLOOKUP(B16,'Старый ИИ'!A:AQ,14,FALSE) -> - | W16: Не указан | X16: =VLOOKUP(B16,'Результат и ПХР'!$A$1:$Q$992,14,0) -> Для мероприятия ПХР не задан в исходных данных. Поэтому doc-level проверка ПХР не запускалась и документы по ПХР не анализировались. Итоговый статус ПХР установлен как "не указано". | Y16: =VLOOKUP(B16,'Результат и ПХР'!$A$1:$Q$992,7,0) -> не указано | Z16: да | AA16: =VLOOKUP(B16,'Старый ИИ'!A:AQ,21,FALSE) -> Не применимо | AB16: =VLOOKUP(B16,'Старый ИИ'!A:AQ,23,FALSE) -> Анализ ПХР пропущен: показатели ПХР не указаны для данного мероприятия | AC16: =VLOOKUP(B16,'Старый ИИ'!A:AQ,24,FALSE) -> да | AD16: =VLOOKUP(B16,'Старый ИИ'!A:AQ,25,FALSE) -> да | AE16: =VLOOKUP(B16,'Старый ИИ'!A:AQ,26,FALSE) -> - | AF16: =VLOOKUP(B16,Общий!$E$2:$O$2000,10,0) -> 161 | AG16: =VLOOKUP(B16,Общий!$E$2:$O$2000,11,0) -> Единица | AH16: =VLOOKUP(B16,'Результат и ПХР'!$A$1:$M$992,13,0) -> Проверка опиралась на summary документа "10 pdf.pdf". В выбранном evidence не подтверждены следующие обязательные сигналы: обязательные сигналы. Имеющийся фрагмент "Предмет: поставка 20 штук прожекторов сценического освещения (модель Anzhee P14x15 SLIM LED PAR) из КНР." не дает прямого подтверждения выполнения. По правилу fail-closed статус мероприятия установлен как "не подтверждено". | AI16: =VLOOKUP(B16,'Результат и ПХР'!$A$1:$T$992,6,0) -> не подтверждено | AJ16: нет | AK16: =VLOOKUP(B16,'Старый ИИ'!A:AQ,27,FALSE) -> Подтверждено | AL16: =VLOOKUP(B16,'Старый ИИ'!A:AQ,29,FALSE) -> **1. Что удалось собрать:** - **Подтверждено ли плановое значение:** да - **Найдено ли фактическое значение в отчете:** да (все ключевые данные присутствуют) - **Соответствует ли фактическое значение плановому:** полностью - **Краткие выводы по каждому параметру:** - Дата платежного поручения — 29.08.2025 (стр. 1). - Номер платежного поручения — 569107 (стр. 1). - Сумма — 350 400,00 ₽, прописана цифрой и прописью (стр. 1). - Данные плательщика (ИНН, КПП, наименование, BIK, счёт) – указаны в таблице. - Данные получателя (ИНН, КПП, наименование, BIK, счёт) – указаны в таблице. - Назначение платежа — детальное, с указанием оборудования, договоров и актов (стр. 1). - НДС — 16 685,71 ₽ (стр. 1). - Подписи, отметки банка, печать — поле для подписи и печати присутствуют (стр. 1); реальных подписей нет, но требование выполнено. **2. Что не удалось собрать:** - Реальные подписи (отсутствуют, но поля для подписей и печати присутствуют, что считается выполнением требования). **3. Общий статус:** - **Подтверждено ли выполнение планового значения:** да - **Краткое резюме:** По представленному фрагменту отчёта все пункты чек‑листа собраны и соответствуют плановым требованиям; отсутствие только реальных подписей не влияет на подтверждение выполнения. | AM16: =VLOOKUP(B16,'Старый ИИ'!A:AQ,30,FALSE) -> да | AN16: =VLOOKUP(B16,'Старый ИИ'!A:AQ,31,FALSE) -> да | AO16: =VLOOKUP(B16,'Старый ИИ'!A:AQ,32,FALSE) -> -
A17: 9191447900 | B17: 9206711684 | C17: Реализованы творческие проекты некоммерческих организаций, направленные на укрепление российской гражданской идентичности на основе духовно-нравственных и культурных ценностей народов Российской Федерации, включая мероприятия, направленные на популяризацию русского языка и литературы, народных художественных промыслов и ремесел | D17: Предоставление грантов НКО, деятельность которых направлена на укрепление гражданской идентичности на основе духовно-нравственных и культурных ценностей народов Российской Федерации. В период 2025-2030 гг. планируется предоставление грантов НКО для реализации творческих проектов в сфере народного творчества, музыкального, театрального, хореографического, изобразительного, декоративно-прикладного искусства, музейного и библиотечного дела. Значение результата к 2030 году: с 2019 по 2024 гг. реализовано 735 творческих проектов НКО, с 2025 по 2030 гг. будет реализовано не менее 600 творческих проектов НКО. С 2019 по 2030 гг. будет реализовано не менее 1335 творческих проектов НКО. Ежегодно поддерживается не менее 100 проектов из 50 регионах. Эффект для бенефициаров и вклад в достижение показателя: Влияет на достижение показателя по количеству поддержанных творческих проектов и инициатив. | E17: =VLOOKUP(B17,Подпись!$A$1:$E$100,5,0) -> #N/A | F17: =VLOOKUP(B17,Подпись!$A$1:$E$100,2,0) -> #N/A | G17: #N/A | H17: {=_xlfn.IFS(AND(G17=I17,K17="нет"),"нет",AND(G17=I17,K17="да"),"да",AND(G17<>I17,K17="нет"),"да",AND(G17<>I17,K17="да"),"нет")} -> #N/A | I17: =VLOOKUP(B17,'Старый ИИ'!A:AQ,3,FALSE) -> Не подтверждено | J17: =VLOOKUP(B17,'Старый ИИ'!A:AQ,5,FALSE) -> Ошибка анализа: ошибка анализа | K17: =VLOOKUP(B17,'Старый ИИ'!A:AQ,6,FALSE) -> нет | L17: =VLOOKUP(B17,'Старый ИИ'!A:AQ,7,FALSE) -> нет | M17: =VLOOKUP(B17,'Старый ИИ'!A:AQ,8,FALSE) -> ИИ некорректно не принимает мероприятие - так как в документах стоит подпись ответственного исполнителя. | N17: Предоставление грантов НКО, деятельность которых направлена на укрепление гражданской идентичности на основе духовно-нравственных и культурных ценностей народов Российской Федерации. В период 2025-2030 гг. планируется предоставление грантов НКО для реализации творческих проектов в сфере народного творчества, музыкального, театрального, хореографического, изобразительного, декоративно-прикладного искусства, музейного и библиотечного дела. Значение результата к 2030 году: с 2019 по 2024 гг. реализовано 735 творческих проектов НКО, с 2025 по 2030 гг. будет реализовано не менее 600 творческих проектов НКО. С 2019 по 2030 гг. будет реализовано не менее 1335 творческих проектов НКО. Ежегодно поддерживается не менее 100 проектов из 50 регионах. Эффект для бенефициаров и вклад в достижение показателя: Влияет на достижение показателя по количеству поддержанных творческих проектов и инициатив. | O17: =VLOOKUP(A17,Характеристика!$A$1:$D$100,2,0) -> 25-1-000002 Договор (подписан обеими сторонами).pdf - Документ описывает договор о предоставлении гранта, что соответствует теме предоставления грантов НКО. Проект, финансируемый грантом, включает проведение фестиваля и концерта, что относится к реализации творческих проектов. Эти мероприятия связаны с культурной деятельностью, что соответствует направленности события. 25-1-000005 Договор (подписан обеими сторонами).pdf - Документ описывает договор о предоставлении гранта, что соответствует теме предоставления грантов НКО. Грант предоставляется для реализации проекта, который включает мероприятия, связанные с культурой и литературой. Это напрямую связано с реализацией творческих проектов, направленных на культурные ценности. 25-1-000006 Договор (подписан обеими сторонами).pdf - Документ описывает предоставление гранта, что соответствует теме события о предоставлении грантов НКО. Грант выделяется на реализацию проекта, который включает мероприятия, связанные с культурой и искусством. Проект «Строгановский стиль» может быть связан с народными художественными промыслами, упомянутыми в описании события. 25-1-000013 Договор (подписан обеими сторонами).pdf - Документ представляет собой договор о предоставлении гранта, что соответствует теме предоставления грантов НКО. Грант выделяется на реализацию проекта, включающего мастер-классы и выставку работ, что относится к сфере народного творчества и культурных ценностей. Это напрямую связано с целью укрепления гражданской идентичности через творческие проекты. 25-1-000014 Договор (подписан обеими сторонами).pdf - Документ описывает договор о предоставлении гранта, что соответствует теме предоставления грантов НКО. Грант выделяется на реализацию проекта «II Фестиваль народного творчества "Подмосковные узоры"», что связано с народным творчеством, упомянутым в описании события. Таким образом, документ напрямую поддерживает реализацию творческих проектов НКО. 25-1-000019 Договор (подписан обеими сторонами).pdf - Данный документ является договором о предоставлении гранта, что соответствует теме предоставления грантов НКО. Грант предназначен для реализации проекта, связанного с «национальной культурой, народного творчества и ремесел», что напрямую соответствует направленности мероприятия. Таким образом, документ подтверждает реализацию творческого проекта в сфере народного творчества. 25-1-000022 Договор (подписан обеими сторонами).pdf - Данный документ является договором о предоставлении гранта, что соответствует теме предоставления грантов НКО. Грант выделяется на реализацию проекта, связанного с культурной деятельностью, что соответствует сфере народного творчества и культурных ценностей. Проект «Преступление и наказание» в рамках федерального проекта «Семейные ценности и инфраструктура культуры» косвенно связан с укреплением ценностей. 25-1-000025 Договор (подписан обеими сторонами).pdf - Документ описывает договор о предоставлении гранта, что соответствует теме предоставления грантов НКО. Грант выделен на реализацию проекта, который связан с культурной деятельностью, что соответствует сфере творческих проектов. Проект направлен на культурные мероприятия, что пересекается с фокусом на культурных ценностях. 25-1-000035 Договор (подписан обеими сторонами).pdf - Документ представляет собой договор о предоставлении гранта, что соответствует теме предоставления грантов НКО. Грант предоставляется для реализации проекта, что связано с реализацией творческих проектов. Проект связан с культурной сферой, что соответствует направленности мероприятия. 25-1-000040 Договор (подписан обеими сторонами).pdf - Документ описывает договор о предоставлении гранта, что соответствует теме предоставления грантов НКО. Грант выделяется на реализацию творческого проекта, а именно "Театральная постановка по мотивам сказки С.Т. Аксакова". Это напрямую связано с реализацией творческих проектов в сфере культуры, упомянутых в описании события. 25-1-000047 Договор (подписан обеими сторонами).pdf - Документ представляет собой договор о предоставлении гранта, что соответствует теме предоставления грантов НКО. Грант предоставляется для реализации проекта, который включает театрализованные реконструкции, что относится к сфере творческих проектов. Это напрямую связано с целью укрепления гражданской идентичности через культурные ценности. 25-1-000050 Договор (подписан обеими сторонами).pdf - Документ описывает договор о предоставлении гранта, что соответствует теме предоставления грантов НКО. Проект, финансируемый грантом, является творческим мероприятием («Семейный танцевальный фестиваль»), что соответствует направлению реализации творческих проектов. Грант выделяется в рамках нацпроекта, что подтверждает контекст поддержки культурных инициатив. 25-1-000061 Договор (подписан обеими сторонами).pdf - Документ представляет собой договор о предоставлении гранта, что соответствует теме предоставления грантов НКО. Грант предоставляется для реализации проекта, который включает выставочные и творческие мероприятия. Это напрямую связано с реализацией творческих проектов, упомянутых в описании события. 25-1-000083 Договор (подписан обеими сторонами).pdf - Документ описывает договор о предоставлении гранта, что соответствует теме предоставления грантов НКО. Грант направлен на реализацию проекта, связанного с народно-художественными промыслами, что соответствует направлению укрепления гражданской идентичности через культурные ценности. Проект включает мероприятия, такие как выставки и мастер-классы, что является частью творческих проектов. 25-1-000093 Договор (подписан обеими сторонами).pdf - Событие касается предоставления грантов НКО для реализации творческих проектов. Данный документ является договором о предоставлении гранта в размере 2 500 000 рублей. Проект, финансируемый грантом, связан с театральной деятельностью, что соответствует сфере народного творчества, упомянутой в описании события. Таким образом, документ напрямую поддерживает реализацию творческого проекта через грантовое финансирование. 25-1-000094 Договор (подписан обеими сторонами).pdf - Документ представляет собой договор о предоставлении гранта, что соответствует теме предоставления грантов НКО. Грант выделяется на реализацию проекта, который связан с культурными ценностями, что соответствует направлению укрепления гражданской идентичности. Проект «Певец во стане русских воинов» также может быть связан с популяризацией русской культуры. 25-1-000109 Договор (подписан обеими сторонами).pdf - Документ описывает предоставление гранта, что соответствует теме предоставления грантов НКО. Грант предоставляется на реализацию проекта, который включает мероприятия, связанные с культурой и традициями, что соответствует направлению укрепления гражданской идентичности. Проект включает фольклорный праздник и форум-практикум, что связано с культурными ценностями. 25-1-000115 Договор (подписан обеими сторонами).pdf - Данный документ является договором о предоставлении гранта, что соответствует теме предоставления грантов НКО. Проект, финансируемый по этому договору, направлен на популяризацию русского языка и культуры, что напрямую связано с укреплением гражданской идентичности. В договоре упоминается реализация проекта, что соответствует цели мероприятия. 25-1-000121 Договор (подписан обеими сторонами).pdf - Документ представляет собой договор о предоставлении гранта, что соответствует теме предоставления грантов НКО. Грант выделяется для реализации проекта, связанного с культурой, что соответствует сфере творческих проектов. В договоре упоминается реализация проекта, что является частью деятельности, описанной в событии. 25-1-000125 Договор (подписан обеими сторонами).pdf - Документ описывает предоставление гранта, что соответствует теме предоставления грантов НКО. Грант выделен на реализацию проекта, который включает культурные мероприятия, что связано с творческими проектами. Проект связан с книгой и культурой, что соответствует направлению укрепления гражданской идентичности через культурные ценности. 25-1-000126 Договор (подписан обеими сторонами).PDF - Документ описывает договор о предоставлении гранта, что соответствует теме предоставления грантов НКО. Грант выделяется на реализацию проекта, который включает мероприятия, такие как фестивали и выставки, что связано с творческими проектами. Проект направлен на патриотизм, что перекликается с укреплением гражданской идентичности. 25-1-000151 Договор (подписан обеими сторонами).pdf - Документ описывает договор о предоставлении гранта, что соответствует теме предоставления грантов НКО. Грант выделяется на реализацию творческого проекта, который включает мастер-классы, хореографию и изобразительное искусство. Это напрямую связано с реализацией творческих проектов в сфере народного творчества, упомянутых в описании события. 25-1-000152 Договор (подписан обеими сторонами).pdf - Данный документ является договором о предоставлении гранта, что соответствует теме предоставления грантов НКО. Проект, финансируемый грантом, включает литературные фестивали и уроки, что связано с популяризацией литературы, упомянутой в описании события. Таким образом, документ напрямую поддерживает реализацию творческих проектов НКО. 25-1-000157 Договор (подписан обеими сторонами).pdf - Документ представляет собой договор о предоставлении гранта, что соответствует теме предоставления грантов НКО. Грант выделяется на реализацию проекта «Фестиваль народного творчества "Карусель сказок"», что напрямую связано с реализацией творческих проектов в сфере народного творчества. Это подтверждает связь с целью укрепления гражданской идентичности через культурные ценности. 25-1-000159 Договор (подписан обеими сторонами) .PDF - Документ представляет собой договор о предоставлении гранта, что соответствует теме предоставления грантов НКО. Грант предназначен для реализации проекта, связанного с культурой, что соответствует сфере творческих проектов. Упоминание о гранте и реализации проекта напрямую связано с целью укрепления гражданской идентичности через культурные ценности. 25-1-000167 Договор (подписан обеими сторонами).pdf - Документ описывает договор о предоставлении гранта, что соответствует теме предоставления грантов НКО. Грант предоставляется для реализации проекта, который включает творческие мероприятия, что связано с реализацией творческих проектов НКО. Проект также связан с культурной сферой, что соответствует направленности мероприятия. 25-1-000168 Договор (подписан обеими сторонами).pdf - Данный документ является договором о предоставлении гранта, что соответствует теме предоставления грантов НКО. Проект, финансируемый грантом, связан с гончарным искусством и проведением мероприятий, что относится к сфере народного творчества. Это напрямую поддерживает реализацию творческих проектов НКО, упомянутых в описании события. 25-1-000176 Договор (подписан обеими сторонами).pdf - Документ представляет собой договор о предоставлении гранта, что соответствует теме предоставления грантов НКО. Проект, финансируемый грантом, включает творческие занятия и премьеру спектакля, что связано с реализацией творческих проектов. Это напрямую поддерживает контекст укрепления гражданской идентичности через культурные ценности. 25-1-000181 Договор (подписан обеими сторонами).pdf - Событие касается предоставления грантов НКО для реализации творческих проектов. Данный документ является договором о предоставлении гранта в размере 2 553 000 рублей. Грант предназначен для реализации проекта, что соответствует контексту реализации творческих проектов НКО. Таким образом, документ напрямую связан с деятельностью, описанной в событии. 25-1-000182 Договор (подписан обеими сторонами).pdf - Документ представляет собой договор о предоставлении гранта, что соответствует теме предоставления грантов НКО. Грант выделяется на реализацию творческого проекта, а именно спектакля, что соответствует сфере народного творчества, упомянутой в описании события. Таким образом, документ напрямую связан с реализацией творческих проектов НКО. 25-1-000184 Договор (подписан обеими сторонами).pdf - Документ описывает договор о предоставлении гранта, что соответствует теме предоставления грантов НКО. Проект, финансируемый грантом, включает проведение мастер-классов и организацию творческой выставки, что связано с реализацией творческих проектов. Это напрямую поддерживает контекст укрепления культурных ценностей через творческую деятельность. 25-1-000190 Договор (подписан обеими сторонами).pdf - Документ является договором о предоставлении гранта, что соответствует теме предоставления грантов НКО. Грант выделяется на реализацию проекта, что связано с реализацией творческих проектов. Проект связан с культурной сферой, что соответствует направленности мероприятия. 25-1-000194 Договор (подписан обеими сторонами).pdf - Данный документ является договором о предоставлении гранта, что соответствует теме предоставления грантов НКО. Грант предназначен для реализации проекта, который связан с культурной деятельностью, что соответствует направлению укрепления гражданской идентичности через культурные ценности. В договоре упоминается реализация проекта, что соответствует контексту творческих проектов НКО. 25-1-000199 Договор (подписан обеими сторонами).pdf - Документ представляет собой договор о предоставлении гранта, что соответствует теме предоставления грантов НКО. Проект, описанный в договоре, включает книжную выставку и литературные семинары, что связано с популяризацией литературы, упомянутой в описании события. Таким образом, документ напрямую касается реализации творческого проекта в рамках грантовой поддержки. 25-1-000206 Договор (подписан обеими сторонами).pdf - Данный документ является договором о предоставлении гранта НКО, что соответствует теме события. Грант выделяется на реализацию проекта, связанного с культурными ценностями, а именно "Традиционный костюм для всей семьи". Это напрямую связано с реализацией творческих проектов НКО в сфере культуры. 25-1-000207 Договор (подписан обеими сторонами).pdf - Данный документ является договором о предоставлении гранта, что соответствует теме предоставления грантов НКО. Проект, описанный в договоре, связан с реализацией творческого проекта, что соответствует направлению мероприятия. Проект включает форум-театр, что относится к сфере культурных и творческих проектов. 25-1-000222 Договор (подписан обеими сторонами).pdf - Документ представляет собой договор о предоставлении гранта, что соответствует теме предоставления грантов НКО. Грант предоставляется для реализации проекта «Фестиваль народного творчества "Нарядная провинция"», что связано с народным творчеством, упомянутым в описании события. Таким образом, документ напрямую поддерживает реализацию творческих проектов НКО. 25-1-000230 Договор (подписан обеими сторонами).pdf - Документ описывает договор о предоставлении гранта, что соответствует теме предоставления грантов НКО. Грант выделяется на реализацию проекта «Межрегиональный фестиваль русского народного творчества "Ро | P17: =VLOOKUP(A17,Характеристика!$A$1:$D$100,4,0) -> Подтверждено | Q17: {=_xlfn.IFS(AND(P17=R17,T17="нет"),"нет",AND(P17=R17,T17="да"),"да",AND(P17<>R17,T17="нет"),"да",AND(P17<>R17,T17="да"),"нет")} -> да | R17: =VLOOKUP(B17,'Старый ИИ'!A:AQ,9,FALSE) -> Подтверждено | S17: =VLOOKUP(B17,'Старый ИИ'!A:AQ,11,FALSE) -> Отчет подтверждает выполнение мероприятия: на странице 1 указано, что к 31.12.2025 реализовано 852 творческих проекта НКО (план 835) и 117 проектов в 2025 году; на страницах 2‑5 приведён перечень 115 проектов, охватывающих народное творчество, литературу, ремёсла и популяризацию русского языка; количество публикаций (6 876) превышает требуемое минимум (300). Всё соответствует заявленным целям мероприятия. | T17: =VLOOKUP(B17,'Старый ИИ'!A:AQ,12,FALSE) -> да | U17: =VLOOKUP(B17,'Старый ИИ'!A:AQ,13,FALSE) -> да | V17: =VLOOKUP(B17,'Старый ИИ'!A:AQ,14,FALSE) -> - | W17: =VLOOKUP(B17,'ПХР актуальный'!$A$1:$C$34,3,0) -> #NUM! | X17: =VLOOKUP(B17,'Результат и ПХР'!$A$1:$Q$992,14,0) -> Проверка опиралась на summary документа "25-1-000002 Договор (подписан обеими сторонами).pdf". В выбранном evidence для метрики "Общее количество публикаций в СМИ, электронных коммуникационных системах и иных информационных сетях (не запрещенных на территории РФ)" установлено, что метрика не совпала; характеристика объекта не подтверждена явно; количество не привязано к объекту метрики; фактическое значение отсутствует; единица измерения отсутствует. Прямой подтверждающий фрагмент в evidence не найден. По правилу fail-closed статус ПХР установлен как "не подтверждено". | Y17: =VLOOKUP(B17,'Результат и ПХР'!$A$1:$Q$992,7,0) -> не подтверждено | Z17: {=_xlfn.IFS(AND(Y17=AA17,AC17="нет"),"нет",AND(Y17=AA17,AC17="да"),"да",AND(Y17<>AA17,AC17="нет"),"да",AND(Y17<>AA17,AC17="да"),"нет")} -> нет | AA17: =VLOOKUP(B17,'Старый ИИ'!A:AQ,21,FALSE) -> Подтверждено | AB17: =VLOOKUP(B17,'Старый ИИ'!A:AQ,23,FALSE) -> Отчет (стр. 1) прямо подтверждает реализацию творческих проектов НКО, направленных на укрепление российской гражданской идентичности, популяризацию русского языка, литературы и народных промыслов. Приведены количественные показатели: реализовано 852 проекта (план 835), 6 876 публикаций (план 300) и 100 % кассового исполнения бюджета (стр. 1‑5). Список конкретных проектов (стр. 2‑5) полностью соответствует заявленным мероприятиям. | AC17: =VLOOKUP(B17,'Старый ИИ'!A:AQ,24,FALSE) -> да | AD17: =VLOOKUP(B17,'Старый ИИ'!A:AQ,25,FALSE) -> да | AE17: =VLOOKUP(B17,'Старый ИИ'!A:AQ,26,FALSE) -> - | AF17: =VLOOKUP(B17,Общий!$E$2:$O$2000,10,0) -> 835 | AG17: =VLOOKUP(B17,Общий!$E$2:$O$2000,11,0) -> Единица | AH17: =VLOOKUP(B17,'Результат и ПХР'!$A$1:$M$992,13,0) -> Проверка опиралась на summary документа "25-1-000002 Договор (подписан обеими сторонами).pdf". В выбранном evidence не подтверждены следующие обязательные сигналы: сигнал завершения, фактическое значение, единица измерения. Прямой подтверждающий фрагмент в evidence не найден. По правилу fail-closed статус мероприятия установлен как "не подтверждено". | AI17: =VLOOKUP(B17,'Результат и ПХР'!$A$1:$T$992,6,0) -> не подтверждено | AJ17: нет | AK17: =VLOOKUP(B17,'Старый ИИ'!A:AQ,27,FALSE) -> Подтверждено | AL17: =VLOOKUP(B17,'Старый ИИ'!A:AQ,29,FALSE) -> В соответствии с паспортом проекта плановое значение составляет 835 ед., а в отчете указано, что к 31.12.2025 реализовано 852 творческих проекта НКО (из них 117 в 2025 г.) – фактическое значение превышает план, следовательно KPI выполнен. | AM17: =VLOOKUP(B17,'Старый ИИ'!A:AQ,30,FALSE) -> да | AN17: =VLOOKUP(B17,'Старый ИИ'!A:AQ,31,FALSE) -> да | AO17: =VLOOKUP(B17,'Старый ИИ'!A:AQ,32,FALSE) -> -
A18: 9191447903 | B18: 9206750206 | C18: Проведены военно-исторические лагеря на территории субъектов Российской Федерации | D18: Проведение военно-исторических лагерей для детей и подростков в возрасте от 12 до 17 лет, направленных на изучение военной истории России, сохранение духовного и культурного наследия, воспитание патриотизма. Планируется ежегодно с 2025 года проведение не менее 4 лагерей, участниками которых становятся 3 тысяч человек. Лагеря проводятся на основе уникальной программы, утвержденной Минкультуры России. Программой предусмотрены мероприятия в различных формах взаимодействия с участниками (лекции, творческие конкурсы, посвященные юбилейным датам событий истории Отечества и выдающихся личностей). Значение результата к 2030 году: С 2019 по 2024 гг. будет проведено 28 лагерей ориентировочно в 21 субъекте, участниками которых станут более 28 000 детей. С 2025 по 2030 гг. будет проведено 24 лагеря (ежегодно по 4 лагеря), участниками ВИЛ станут не менее 18 000 детей из регионов России. С 2019 по 2030 гг. будет проведено 52 лагеря, участниками которых станут более 46 000 детей. Эффект для бенефициаров и вклад в достижение показателя: Проведение военно-исторических лагерей имеет цель получения новых исторических знаний и приобщения подрастающего поколения к истории своей Родины. Мероприятие направлено на воспитании в молодом поколении основ развития духовно-патриотического воспитания, идентификации себя как части многонационального этнокультурного российского народа, имеющего богатейшую историю. | E18: =VLOOKUP(B18,Подпись!$A$1:$E$100,5,0) -> Алексеева Жанна Владимировна - Статс-секретарь - заместитель Министра культуры Российской Федерации, Любимова Ольга Борисовна, Обрывалин Сергей Геннадьевич, Алексеева Жанна Владимировна, Осинцев Владимир Геннадьевич, Малышев Андрей Владимирович, Першин Сергей Васильевич | F18: =VLOOKUP(B18,Подпись!$A$1:$E$100,2,0) -> Першин Сергей Васильевич | G18: Подтверждено | H18: {=_xlfn.IFS(AND(G18=I18,K18="нет"),"нет",AND(G18=I18,K18="да"),"да",AND(G18<>I18,K18="нет"),"да",AND(G18<>I18,K18="да"),"нет")} -> #N/A | I18: =VLOOKUP(B18,'Старый ИИ'!A:AQ,3,FALSE) -> Не подтверждено | J18: =VLOOKUP(B18,'Старый ИИ'!A:AQ,5,FALSE) -> Найдены подписи: Баркова К.С., Полетыкина Ю.Н., Мартынюк В.Н., Киселева А.Ю., Вергизова С.В., Решетникова М.С., Дьякова О.Г., Парий Н.В., Коткин А.В., но они не совпадают с ответственными лицами | K18: =VLOOKUP(B18,'Старый ИИ'!A:AQ,6,FALSE) -> #N/A | L18: =VLOOKUP(B18,'Старый ИИ'!A:AQ,7,FALSE) -> #N/A | M18: =VLOOKUP(B18,'Старый ИИ'!A:AQ,8,FALSE) -> #N/A | N18: Проведение военно-исторических лагерей для детей и подростков в возрасте от 12 до 17 лет, направленных на изучение военной истории России, сохранение духовного и культурного наследия, воспитание патриотизма. Планируется ежегодно с 2025 года проведение не менее 4 лагерей, участниками которых становятся 3 тысяч человек. Лагеря проводятся на основе уникальной программы, утвержденной Минкультуры России. Программой предусмотрены мероприятия в различных формах взаимодействия с участниками (лекции, творческие конкурсы, посвященные юбилейным датам событий истории Отечества и выдающихся личностей). Значение результата к 2030 году: С 2019 по 2024 гг. будет проведено 28 лагерей ориентировочно в 21 субъекте, участниками которых станут более 28 000 детей. С 2025 по 2030 гг. будет проведено 24 лагеря (ежегодно по 4 лагеря), участниками ВИЛ станут не менее 18 000 детей из регионов России. С 2019 по 2030 гг. будет проведено 52 лагеря, участниками которых станут более 46 000 детей. Эффект для бенефициаров и вклад в достижение показателя: Проведение военно-исторических лагерей имеет цель получения новых исторических знаний и приобщения подрастающего поколения к истории своей Родины. Мероприятие направлено на воспитании в молодом поколении основ развития духовно-патриотического воспитания, идентификации себя как части многонационального этнокультурного российского народа, имеющего богатейшую историю. | O18: =VLOOKUP(A18,Характеристика!$A$1:$D$100,2,0) -> #N/A | P18: =VLOOKUP(A18,Характеристика!$A$1:$D$100,4,0) -> #N/A | Q18: {=_xlfn.IFS(AND(P18=R18,T18="нет"),"нет",AND(P18=R18,T18="да"),"да",AND(P18<>R18,T18="нет"),"да",AND(P18<>R18,T18="да"),"нет")} -> #N/A | R18: =VLOOKUP(B18,'Старый ИИ'!A:AQ,9,FALSE) -> Подтверждено | S18: =VLOOKUP(B18,'Старый ИИ'!A:AQ,11,FALSE) -> В приложенных материалах мероприятие описано прямо и по смыслу совпадает с вашим описанием, включая ключевые параметры именно на 2025 год. В документе «Подтверждающие сведения 5.pdf» (стр. 1) это буквально отчет по результату «Проведены военно-исторические лагеря на территории субъектов Российской Федерации… по итогам 2025 года», где указано: целевая аудитория 12–17 лет, цели (изучение военной истории России, сохранение духовного и культурного наследия, воспитание патриотизма), проведение на основе уникальной программы, утвержденной Минкультуры России, и формы работы (лекции, творческие конкурсы, посвященные юбилейным датам и выдающимся личностям). Там же зафиксировано, что в 2025 году проведены 4 лагеря в 4 регионах. Дополнительно, «Подтверждающие сведения 4.pdf» (стр. 1–2) — это Положение об организации и проведении военно-исторических лагерей «Страна Героев» в 2025 году, утвержденное Минкультуры (дата утверждения на титульной странице). В нем прямо закреплено, что в 2025 году проводится 4 лагеря в 4 субъектах РФ, а участниками станут 3 000 человек; также подтвержден возраст 12–17 лет и общий смысл программы (в т.ч. историко-просветительские и культурно-массовые форматы, учебный курс «Военная история России» и т.п.). Итого: источники действительно описывают именно это мероприятие и содержательно соответствуют заявленной характеристике, а параметры на 2025 год (4 лагеря, 3 000 участников, 12–17 лет, программа Минкультуры, лекции/творческие конкурсы) в них присутствуют. | T18: =VLOOKUP(B18,'Старый ИИ'!A:AQ,12,FALSE) -> #N/A | U18: =VLOOKUP(B18,'Старый ИИ'!A:AQ,13,FALSE) -> #N/A | V18: =VLOOKUP(B18,'Старый ИИ'!A:AQ,14,FALSE) -> #N/A | W18: Не указан | X18: =VLOOKUP(B18,'Результат и ПХР'!$A$1:$Q$992,14,0) -> #N/A | Y18: =VLOOKUP(B18,'Результат и ПХР'!$A$1:$Q$992,7,0) -> #N/A | Z18: {=_xlfn.IFS(AND(Y18=AA18,AC18="нет"),"нет",AND(Y18=AA18,AC18="да"),"да",AND(Y18<>AA18,AC18="нет"),"да",AND(Y18<>AA18,AC18="да"),"нет")} -> #N/A | AA18: =VLOOKUP(B18,'Старый ИИ'!A:AQ,21,FALSE) -> Не применимо | AB18: =VLOOKUP(B18,'Старый ИИ'!A:AQ,23,FALSE) -> Анализ ПХР пропущен: показатели ПХР не указаны для данного мероприятия | AC18: =VLOOKUP(B18,'Старый ИИ'!A:AQ,24,FALSE) -> #N/A | AD18: =VLOOKUP(B18,'Старый ИИ'!A:AQ,25,FALSE) -> #N/A | AE18: =VLOOKUP(B18,'Старый ИИ'!A:AQ,26,FALSE) -> #N/A | AF18: =VLOOKUP(B18,Общий!$E$2:$O$2000,10,0) -> 32 | AG18: =VLOOKUP(B18,Общий!$E$2:$O$2000,11,0) -> Единица | AH18: =VLOOKUP(B18,'Результат и ПХР'!$A$1:$M$992,13,0) -> #N/A | AI18: =VLOOKUP(B18,'Результат и ПХР'!$A$1:$T$992,6,0) -> #N/A | AJ18: #N/A | AK18: =VLOOKUP(B18,'Старый ИИ'!A:AQ,27,FALSE) -> Подтверждено | AL18: =VLOOKUP(B18,'Старый ИИ'!A:AQ,29,FALSE) -> В приложенных материалах есть «Отчет о проведении военно-исторических лагерей … по итогам 2025 года» (Подтверждающие сведения 5). В нем прямо указано: по состоянию на 31.12.2025 «проведено … 32 военно-исторических лагеря» (накопительным итогом), а также отдельно отмечено, что «в 2025 году проведено 4 лагеря в 4 субъектах РФ». Поскольку KPI задан как 32 единицы, и отчет фиксирует достижение значения 32 на дату 31.12.2025, показатель считается достигнутым (и подтвержден документально). | AM18: =VLOOKUP(B18,'Старый ИИ'!A:AQ,30,FALSE) -> #N/A | AN18: =VLOOKUP(B18,'Старый ИИ'!A:AQ,31,FALSE) -> #N/A | AO18: =VLOOKUP(B18,'Старый ИИ'!A:AQ,32,FALSE) -> #N/A
A19: 9166821650 | B19: 9168218775 | C19: Проведено строительство и модернизация региональных и муниципальных детских школ искусств | D19: Проведение капитального ремонта и реконструкции зданий, в которых располагаются региональные и муниципальные детские школы искусств, являющиеся важным звеном отечественного художественного образования. Детские школы искусств располагаются в 8597 зданиях, требуют капитального ремонта и являются аварийными 1678 зданий. Значение результата к 2030 году: будет отремонтировано (реконструировано) 1001 здание детских школ искусств, что составляет 59% от зданий, требующих капитального ремонта (2020-2024 - 859 зданий, 2025-2030 - 142 здания). Кроме того, будет построено 50 зданий ДШИ. Эффект для бенефициаров и вклад в достижение показателя: реализация мероприятия позволит создать комфортные условия для обучения одаренных детей по дополнительным предпрофессиональным программам в области искусств, способствует увеличению площади для ведения образовательной деятельности, в том числе путем передачи капитально отремонтированных и реконструированных зданий в оперативное управление детским школам искусств, создает условия для посещения гражданами творческих мероприятий, проводимых детскими школами искусств. | E19: =VLOOKUP(B19,Подпись!$A$1:$E$100,5,0) -> Алексеева Жанна Владимировна - Статс-секретарь - заместитель Министра культуры Российской Федерации, Любимова Ольга Борисовна, Обрывалин Сергей Геннадьевич, Алексеева Жанна Владимировна, Осинцев Владимир Геннадьевич, Малышев Андрей Владимирович, Першин Сергей Васильевич | F19: =VLOOKUP(B19,Подпись!$A$1:$E$100,2,0) -> Осинцев Владимир Геннадьевич | G19: Подтверждено | H19: {=_xlfn.IFS(AND(G19=I19,K19="нет"),"нет",AND(G19=I19,K19="да"),"да",AND(G19<>I19,K19="нет"),"да",AND(G19<>I19,K19="да"),"нет")} -> нет | I19: =VLOOKUP(B19,'Старый ИИ'!A:AQ,3,FALSE) -> Не подтверждено | J19: =VLOOKUP(B19,'Старый ИИ'!A:AQ,5,FALSE) -> Найдены подписи: Осинцев В.Г.. Подпись не совпадает со списком ответственных лиц | K19: =VLOOKUP(B19,'Старый ИИ'!A:AQ,6,FALSE) -> да | L19: =VLOOKUP(B19,'Старый ИИ'!A:AQ,7,FALSE) -> да | M19: =VLOOKUP(B19,'Старый ИИ'!A:AQ,8,FALSE) -> - | N19: Проведение капитального ремонта и реконструкции зданий, в которых располагаются региональные и муниципальные детские школы искусств, являющиеся важным звеном отечественного художественного образования. Детские школы искусств располагаются в 8597 зданиях, требуют капитального ремонта и являются аварийными 1678 зданий. Значение результата к 2030 году: будет отремонтировано (реконструировано) 1001 здание детских школ искусств, что составляет 59% от зданий, требующих капитального ремонта (2020-2024 - 859 зданий, 2025-2030 - 142 здания). Кроме того, будет построено 50 зданий ДШИ. Эффект для бенефициаров и вклад в достижение показателя: реализация мероприятия позволит создать комфортные условия для обучения одаренных детей по дополнительным предпрофессиональным программам в области искусств, способствует увеличению площади для ведения образовательной деятельности, в том числе путем передачи капитально отремонтированных и реконструированных зданий в оперативное управление детским школам искусств, создает условия для посещения гражданами творческих мероприятий, проводимых детскими школами искусств. | O19: =VLOOKUP(A19,Характеристика!$A$1:$D$100,2,0) -> —¥ç¥­áª ï ¥á¯ã¡«¨ª (á. ‘¥à­®¢®¤áª®¥) (30 796 695,47 àã¡.).pdf - Документ содержит акты о приемке выполненных работ по контракту на проведение капитального ремонта «Детской школы искусств». Это напрямую соответствует теме мероприятия о проведении капитального ремонта и реконструкции детских школ искусств. Упоминание ДШИ и капитального ремонта подтверждает релевантность документа. €ªâ10_Š¨à®¢ 41_6_005_995_47 (2).pdf - Событие касается проведения капитального ремонта и реконструкции зданий детских школ искусств. Предоставленный документ является актом о приемке выполненных работ по капитальному ремонту здания. Это напрямую связано с реализацией мероприятий по ремонту зданий, упомянутых в описании события. €ªâ_11_Š¨à®¢ _6_005_995_48.pdf - Целевое событие касается строительства и модернизации детских школ искусств. Предоставленный документ содержит подробные сметные расчеты на выполнение строительно-монтажных работ. Эти расчеты охватывают теплоизоляцию, вентиляцию и сантехнические системы, что напрямую связано с капитальным ремонтом и реконструкцией зданий. €ªâ_12_Š¨à®¢ 41_3_283_409_38.pdf - Событие касается проведения капитального ремонта и реконструкции зданий детских школ искусств. Предоставленный документ является актом о приемке выполненных работ по объекту капитального ремонта здания. Это напрямую связано с процессом реализации мероприятия по ремонту зданий ДШИ. €ªâ_13_Š¨à®¢ 41_343_708_67.pdf - Событие касается проведения капитального ремонта и реконструкции зданий детских школ искусств. Предоставленный документ является актом о приемке выполненных работ по капитальному ремонту здания. Это напрямую соответствует теме проведения ремонтных работ в контексте детских школ искусств. €ªâ 1 (4 728 879,85 àã¡.).pdf - Описание события включает проведение капитального ремонта и реконструкции зданий детских школ искусств. Предоставленный документ содержит акты о приемке выполненных работ по контракту на капитальный ремонт здания МБУ ДО ДШИ г. Камышин. Таким образом, документ напрямую подтверждает реализацию мероприятий, связанных с ремонтом ДШИ. €ªâ_14_Š¨à®¢ 41_5_127_339_38.pdf - Событие касается строительства и модернизации детских школ искусств. Однако предоставленный текст описывает технические и химические данные, связанные с фармацевтическим или аналитическим производством. Также упоминается монтаж систем кондиционирования, что не связано с ремонтом школ искусств. €ªâ_15_Š¨à®¢ 41_2_510_826_30.pdf - Событие касается строительства и модернизации детских школ искусств. Предоставленный документ является детальной сметой на выполнение электромонтажных работ. Хотя электромонтажные работы могут быть частью модернизации, сам текст сметы не описывает строительство или реконструкцию зданий ДШИ. Он фокусируется на технических и финансовых деталях электрооборудования. €ªâ_16_Š¨à®¢ 41_3_455_877_91.pdf - Целевое событие касается капитального ремонта и реконструкции зданий детских школ искусств. Предоставленный документ является актом о приемке выполненных работ по капитальному ремонту здания. Хотя в тексте упоминаются сети связи, сам факт проведения работ по ремонту здания соответствует контексту мероприятия. Это прямое подтверждение реализации строительных работ. €ªâ_17_Š¨à®¢ 41_7_360_580_04.pdf - Событие касается строительства и модернизации детских школ искусств. Предоставленный текст содержит только подробные технические и финансовые данные по строительным материалам и трудозатратам. Эти данные являются общими для строительных работ, но не привязаны к конкретному контексту детских школ искусств. €ªâ_18_Š¨à®¢ 412_804_368_64.pdf - Событие касается строительства и модернизации детских школ искусств. Предоставленный текст описывает технические таблицы с перечнем материалов и работ, таких как тактильные пиктограммы, поручни и резиновая крошка. Эти детали не связаны напрямую с процессом строительства или реконструкции самих детских школ искусств. €ªâ_19_Š¨à®¢ 41_3_214_818_20.pdf - Событие касается проведения капитального ремонта и реконструкции зданий детских школ искусств. Предоставленный документ является отчетной документацией по приемке выполненных строительно-монтажных работ в рамках капитального ремонта здания. Это напрямую соответствует теме проведения строительных работ для объектов, упомянутых в описании события. Таким образом, документ относится к теме модернизации детских школ искусств. €ªâ1_Š¨à®¢ 41_3_572_650_47 (1).pdf - Событие касается проведения капитального ремонта и реконструкции зданий детских школ искусств. Предоставленный документ является актом приемки выполненных работ по капитальному ремонту здания. Упоминание капитального ремонта напрямую соответствует теме модернизации и ремонта зданий ДШИ. €ªâ_20_Š¨à®¢ 41_982_9448_14.pdf - Смета описывает выполнение работ по капитальному ремонту здания. Это напрямую связано с целью мероприятия, которая включает проведение капитального ремонта зданий детских школ искусств. Упоминание капитального ремонта подтверждает релевантность документа. €ªâ_21_Š¨à®¢ 41_117_786_16.pdf - Событие касается проведения капитального ремонта и реконструкции зданий детских школ искусств. Предоставленный документ является актом приемки выполненных работ по капитальному ремонту здания. Упоминание капитального ремонта напрямую связано с деятельностью, описанной в событии. €ªâ_22_Š¨à®¢ 41_240_660_52.pdf - Событие касается строительства и модернизации детских школ искусств. Однако предоставленный текст описывает перечни работ, сметные расчеты, отделочные и сантехнические работы, а также обслуживание сельскохозяйственной техники. В тексте нет упоминаний о детских школах искусств или их реконструкции. €ªâ 2 (45 381 200,54 àã¡.).pdf - Событие касается строительства и модернизации детских школ искусств. Предоставленный документ содержит акты о приемке выполненных работ по капитальному ремонту здания МБУ ДО ДШИ г. Камышин. Это напрямую соответствует теме капитального ремонта зданий детских школ искусств, упомянутой в описании события. €ªâ2_Š¨à®¢ 41_144_957_05.pdf - Событие касается проведения капитального ремонта и реконструкции зданий детских школ искусств. Предоставленный документ является актом о приемке выполненных работ по капитальному ремонту здания. Это напрямую соответствует теме проведения строительных работ для объектов, упомянутых в описании события. €ªâ_3_Š¨à®¢ 41_909_401_75.pdf - Событие касается проведения капитального ремонта и реконструкции зданий детских школ искусств. Предоставленный документ является актом приемки выполненных работ по капитальному ремонту здания. Упоминание о капитальном ремонте напрямую соответствует теме мероприятия. €ªâ_4_Š¨à®¢ 41_1_378_986_20.pdf - Событие касается проведения капитального ремонта и реконструкции зданий детских школ искусств. Предоставленный документ является актом приемки выполненных работ по капитальному ремонту здания. Это напрямую связано с реализацией мероприятий по ремонту зданий, упомянутых в описании события. €ªâ5_Š¨à®¢ 41_2_523_682_00 (3).pdf - Описание события включает проведение капитального ремонта и реконструкции зданий детских школ искусств. Предоставленный документ является актом приемки выполненных работ по капитальному ремонту здания. Это напрямую соответствует теме капитального ремонта, упомянутой в описании мероприятия. €ªâ6_Š¨à®¢ 41_1_310_950_96 (3).pdf - Свидетельство описывает акт приемки выполненных работ по капитальному ремонту здания в г. Симферополе. Это напрямую связано с темой проведения капитального ремонта зданий, в которых располагаются детские школы искусств. Упоминание о ремонте здания соответствует цели мероприятия по модернизации региональных и муниципальных детских школ искусств. €ªâ7_Š¨à®¢ 41_1_707_557_52.pdf - Событие касается проведения капитального ремонта и реконструкции зданий детских школ искусств. Предоставленный документ является актом приемки выполненных работ по капитальному ремонту здания. Хотя в тексте не упоминается напрямую, что это ДШИ, сам факт проведения капитального ремонта соответствует теме мероприятия. Это прямое подтверждение реализации строительных работ. €ªâ8_Š¨à®¢ 41_463_805_38 (3).pdf - Смета описывает строительно-монтажные работы по капитальному ремонту здания. Это напрямую соответствует теме мероприятия о проведении капитального ремонта и реконструкции зданий детских школ искусств. Упоминание адреса и заказчика подтверждает контекст реализации строительных работ. €ªâ9_Š¨à®¢ 41_6_005_995_47.pdf - Событие касается проведения капитального ремонта и реконструкции зданий детских школ искусств. Предоставленный документ является актом приемки выполненных работ по капитальному ремонту здания. Это напрямую соответствует теме проведения строительных работ, упомянутой в описании события. €ªâ ¯à¨¥¬ª¨ ¢ë¯®«­¥­­ëå à ¡®â.pdf - Событие касается проведения капитального ремонта и реконструкции зданий детских школ искусств. Предоставленный документ является актом приемки выполненных работ по капитальному ремонту здания. Это напрямую соответствует теме проведения капитального ремонта зданий, упомянутой в описании события. €ªâ ­ áâà®©ª®­âà®«ì 1_551225,0.pdf - Документ содержит акт об оказании услуг строительного контроля по объекту «Капитальный ремонт здания школы искусств». Это напрямую соответствует теме проведения капитального ремонта зданий детских школ искусств, упомянутой в описании события. Упоминание ДШИ также подтверждает релевантность документа. €ªâ ­ áâà®©ª®­âà®«ì 2_551225,0.pdf - Документ содержит акт об оказании услуг строительного контроля по объекту «Капитальный ремонт здания школы искусств». Это напрямую соответствует теме проведения капитального ремонта зданий детских школ искусств, упомянутой в описании события. Упоминание ДШИ также подтверждает релевантность документа. €ªâ_Š¨à®¢ 41_117_530_80_1.pdf - Событие касается проведения капитального ремонта и реконструкции зданий детских школ искусств. Предоставленный документ является актом об оказании услуг строительного контроля по объекту капитального ремонта здания. Это напрямую связано с реализацией мероприятий по ремонту зданий, упомянутых в описании события. €ªâ_Š¨à®¢ 41_117_530_80.pdf - Событие касается проведения капитального ремонта и реконструкции зданий детских школ искусств. Предоставленный документ является актом об оказании услуг строительного контроля по объекту капитального ремонта здания. Это напрямую связано с реализацией мероприятий по ремонту зданий, упомянутых в описании события. €ªâ_Š¨à®¢ 41_352_592_40.pdf - Событие касается проведения капитального ремонта и реконструкции зданий детских школ искусств. Предоставленный документ является актом об оказании услуг строительного контроля по объекту капитального ремонта здания. Это напрямую связано с реализацией мероприятий по ремонту зданий, упомянутых в описании события. €‚ ό37 ®β 16.09.2025£.pdf - Документ содержит акт о выполнении работ по строительному контролю капитального ремонта здания детской школы искусств. Это напрямую связано с целью мероприятия, которая включает проведение капитального ремонта зданий детских школ искусств. Упоминание МАУ ДО «Петропавловская ДШИ» подтверждает контекст детских школ искусств. 1. “¤¬γΰβα ο ¥α―γ΅«¨ (£. ƒ« §®Ά).pdf - Целевое событие касается проведения капитального ремонта и реконструкции детских школ искусств. Предоставленный документ содержит акты о приемке выполненных работ по контракту на капитальный ремонт здания детской музыкальной школы. Это напрямую соответствует теме капитального ремонта зданий детских школ искусств. 1. ‘¢¥à¤«®¢áª ï ®¡« áâì (29 778 736,46 àã¡.).pdf - Описание события касается проведения капитального ремонта и реконструкции зданий детских школ искусств. Предоставленный документ содержит акты о приемке выполненных работ по капитальному ремонту здания, которое принадлежит «Алапаевской детской школе искусств». Это напрямую соответствует теме капитального ремонта в сфере детских школ искусств. 10. ˆàªãâáª ï ®¡« áâì (¯. “à¨ª).pdf - Описание события касается проведения капитального ремонта и реконструкции зданий детских школ искусств. Предоставленный документ содержит акты о приемке выполненных работ по контракту на капитальный ремонт здания. Это напрямую связано с реализацией мероприятий по ремонту зданий, упомянутых в описании события. 10. ‘-2 ό 9 ®β 15.09.2025 (956 872,00 ΰγ΅.).pdf - Свидетельство описывает акт о приемке выполненных работ и сметные расчеты, включающие детализацию строительных работ. Эти работы включают демонтаж, усиление фундамента, установку окон и дверей, что соответствует теме капитального ремонта и реконструкции зданий. Таким образом, документ напрямую связан с процессом строительства и модернизации. 10. 蔵ｬ 珮ｪ ｮ｡ｫ 矮 (｣. 聴ｫ 粐ｨ).pdf - Событие касается проведения капитального ремонта и реконструкции детских школ искусств. Предоставленный документ содержит акты о приемке выполненных работ по капитальному ремонту помещений МБУ ДО ДШИ № 1. Это напрямую соответствует теме проведения ремонтных работ в детских школах искусств. 11. ‡ ¡ ©ª «ìáª¨© ªà © (£. ®à§ï).pdf - Событие касается проведения капитального ремонта и реконструкции детских школ искусств. Предоставленный документ содержит акты о приемке выполненных работ по капитальному ремонту здания Детской музыкальной школы. Это напрямую соответствует теме проведения ремонта зданий детских школ искусств. 1.1. ‘-2 (666 503,6 אד¡.).pdf - Свидетельство описывает смету на выполнение демонтажных работ в рамках капитального ремонта здания МБУДО «Детская школа искусств Земетчинского района». Это напрямую соответствует теме проведения капитального ремонта зданий детских школ искусств, указанной в описании события. Документ детализирует строительные работы, связанные с объектом, упомянутым в событии. 11. ‘-2 ό 10 ®β 15.09.2025 (2 251 068,00 ΰγ΅.).pdf - Свидетельство описывает акт приемки выполненных строительно-отделочных работ, таких как монтаж потолков и внутренняя отделка стен. Это напрямую связано с темой капитального ремонта и реконструкции зданий, упомянутой в описании мероприятия. Строительные работы являются частью процесса модернизации детских школ искусств. 12. €«â ©áª¨© ªà © (á. Š®á¨å ).pdf - Документ описывает акты о приемке выполненных работ по капитальному ремонту объекта. В тексте прямо упоминается, что работы проводятся для МБУДО «Косихинская районная детская школа искусств». Это напрямую соответствует теме проведения капитального ремонта детских школ искусств, указанной в описании события. 1.2. ‘-2 (5 679 890,08 אד¡.).PDF - Свидетельство явно касается капитального ремонта здания детской школы искусств, что соответствует теме мероприятия. В тексте упоминается МБУДО «Детская школа искусств Земетчинского района» и детализация строительных работ. Это напрямую поддерживает цель по проведению капитального ремонта и реконструкции зданий ДШИ. 12. ‘-2 ό 11 ®β 15.09.2025 (1 076 021,00 ΰγ΅.).pdf - Документ содержит акт о приемке выполненных работ по капитальному ремонту фасада МБУ ДО «Детская школа искусств». Это напрямую соответствует теме проведения капитального ремонта зданий детских школ искусств, | P19: =VLOOKUP(A19,Характеристика!$A$1:$D$100,4,0) -> Подтверждено | Q19: {=_xlfn.IFS(AND(P19=R19,T19="нет"),"нет",AND(P19=R19,T19="да"),"да",AND(P19<>R19,T19="нет"),"да",AND(P19<>R19,T19="да"),"нет")} -> да | R19: =VLOOKUP(B19,'Старый ИИ'!A:AQ,9,FALSE) -> Подтверждено | S19: =VLOOKUP(B19,'Старый ИИ'!A:AQ,11,FALSE) -> Отчет об исполнении результата «Проведено строительство и модернизация региональных и муниципальных детских школ искусств» содержит описание выполнения мероприятия и указывает, что в 2025 году проведены работы по модернизации 57 объектов в 46 субъектах РФ (реконструкция — 8 объектов; капитальный ремонт — 49 объектов). Это соответствует заявленному мероприятию по строительству/модернизации ДШИ. | T19: =VLOOKUP(B19,'Старый ИИ'!A:AQ,12,FALSE) -> да | U19: =VLOOKUP(B19,'Старый ИИ'!A:AQ,13,FALSE) -> да | V19: =VLOOKUP(B19,'Старый ИИ'!A:AQ,14,FALSE) -> Корректно, но в описании мероприятия сказано о постройке 50 школ до 30 года, а в 2025 новых школ с нуля построено не было. Понятно, что это не нарушает описательную часть характеристики, но возможно дает под сомнение постройку школ. | W19: =VLOOKUP(B19,'ПХР актуальный'!$A$1:$C$34,3,0) -> #NUM! | X19: =VLOOKUP(B19,'Результат и ПХР'!$A$1:$Q$992,14,0) -> Проверка опиралась на summary документа "—¥ç¥­áª ï ¥á¯ã¡«¨ª (á. ‘¥à­®¢®¤áª®¥) (30 796 695,47 àã¡.).pdf". В выбранном evidence для метрики "Общая площадь построенных и модернизированных зданий" установлено, что характеристика объекта не подтверждена явно; количество не привязано к объекту метрики; фактическое значение отсутствует; единица измерения отсутствует. Прямой подтверждающий фрагмент в evidence не найден. По правилу fail-closed статус ПХР установлен как "не подтверждено". | Y19: =VLOOKUP(B19,'Результат и ПХР'!$A$1:$Q$992,7,0) -> не подтверждено | Z19: {=_xlfn.IFS(AND(Y19=AA19,AC19="нет"),"нет",AND(Y19=AA19,AC19="да"),"да",AND(Y19<>AA19,AC19="нет"),"да",AND(Y19<>AA19,AC19="да"),"нет")} -> нет | AA19: =VLOOKUP(B19,'Старый ИИ'!A:AQ,21,FALSE) -> Не подтверждено | AB19: =VLOOKUP(B19,'Старый ИИ'!A:AQ,23,FALSE) -> В отчете указано: план по доп. характеристике на 2025 год — 25 944,1 кв. м, фактическое значение — 34 173,4 кв. м. Значение 13 121,1 кв. м в отчете отсутствует, поэтому данный показатель не подтвержден. | AC19: =VLOOKUP(B19,'Старый ИИ'!A:AQ,24,FALSE) -> нет | AD19: =VLOOKUP(B19,'Старый ИИ'!A:AQ,25,FALSE) -> нет | AE19: =VLOOKUP(B19,'Старый ИИ'!A:AQ,26,FALSE) -> Некорректно указана информация по количественной части характеристики, поэтому ИИ искал не то значение и не подтвердил его, хотя в подтверждающем документе оно прописано | AF19: =VLOOKUP(B19,Общий!$E$2:$O$2000,10,0) -> 880 | AG19: =VLOOKUP(B19,Общий!$E$2:$O$2000,11,0) -> Единица | AH19: =VLOOKUP(B19,'Результат и ПХР'!$A$1:$M$992,13,0) -> Проверка опиралась на summary документа "—¥ç¥­áª ï ¥á¯ã¡«¨ª (á. ‘¥à­®¢®¤áª®¥) (30 796 695,47 àã¡.).pdf". В выбранном evidence не подтверждены следующие обязательные сигналы: фактическое значение, единица измерения. Имеющийся фрагмент "Документы содержат два акта о приемке выполненных работ по контракту № 1 от 04.03.2025 на проведение капитального ремонта «Детской школы искусств» в г. Серноводске." не дает прямого подтверждения выполнения. По правилу fail-closed статус мероприятия установлен как "не подтверждено". | AI19: =VLOOKUP(B19,'Результат и ПХР'!$A$1:$T$992,6,0) -> не подтверждено | AJ19: нет | AK19: =VLOOKUP(B19,'Старый ИИ'!A:AQ,27,FALSE) -> Подтверждено | AL19: =VLOOKUP(B19,'Старый ИИ'!A:AQ,29,FALSE) -> В отчете приведены значения результата на 2025 год: плановое значение — 895 ед. (базовое значение 2024 г. — 861 ед.), фактическое значение — 900 ед. (нарастающим итогом). Значение 880 ед. в документе не указано, поэтому KPI 880.0 “Единица” не подтверждается текстом отчета. | AM19: =VLOOKUP(B19,'Старый ИИ'!A:AQ,30,FALSE) -> да | AN19: =VLOOKUP(B19,'Старый ИИ'!A:AQ,31,FALSE) -> да | AO19: =VLOOKUP(B19,'Старый ИИ'!A:AQ,32,FALSE) -> -
A20: 9187094211 | B20: 9206711690 | C20: Проведена модернизация театров, находящихся в региональной и муниципальной собственности. | D20: Проведение капитального ремонта региональных и муниципальных театров. Всего 665 региональных и муниципальных театров, из них 365 в неудовлетворительном состоянии. К 2030 году будет отремонтировано 27% от зданий, требующих капитального ремонта, по отношению к 2022 году. Эффект для бенефициаров и вклад в достижение показателя: реализация мероприятия позволит создать комфортные условия гостей и жителей населенных пунктов, создает условия для посещения театров. | E20: =VLOOKUP(B20,Подпись!$A$1:$E$100,5,0) -> Алексеева Жанна Владимировна - Статс-секретарь - заместитель Министра культуры Российской Федерации, Любимова Ольга Борисовна, Обрывалин Сергей Геннадьевич, Алексеева Жанна Владимировна, Осинцев Владимир Геннадьевич, Малышев Андрей Владимирович, Першин Сергей Васильевич | F20: =VLOOKUP(B20,Подпись!$A$1:$E$100,2,0) -> Осинцев Владимир Геннадьевич | G20: Подтверждено | H20: {=_xlfn.IFS(AND(G20=I20,K20="нет"),"нет",AND(G20=I20,K20="да"),"да",AND(G20<>I20,K20="нет"),"да",AND(G20<>I20,K20="да"),"нет")} -> нет | I20: =VLOOKUP(B20,'Старый ИИ'!A:AQ,3,FALSE) -> Не подтверждено | J20: =VLOOKUP(B20,'Старый ИИ'!A:AQ,5,FALSE) -> Найдены подписи: Панасенко Б.Ю., Орлова Н.И., но они не совпадают с ответственными лицами | K20: =VLOOKUP(B20,'Старый ИИ'!A:AQ,6,FALSE) -> да | L20: =VLOOKUP(B20,'Старый ИИ'!A:AQ,7,FALSE) -> да | M20: =VLOOKUP(B20,'Старый ИИ'!A:AQ,8,FALSE) -> - | N20: Проведение капитального ремонта региональных и муниципальных театров. Всего 665 региональных и муниципальных театров, из них 365 в неудовлетворительном состоянии. К 2030 году будет отремонтировано 27% от зданий, требующих капитального ремонта, по отношению к 2022 году. Эффект для бенефициаров и вклад в достижение показателя: реализация мероприятия позволит создать комфортные условия гостей и жителей населенных пунктов, создает условия для посещения театров. | O20: =VLOOKUP(A20,Характеристика!$A$1:$D$100,2,0) -> #N/A | P20: =VLOOKUP(A20,Характеристика!$A$1:$D$100,4,0) -> #N/A | Q20: {=_xlfn.IFS(AND(P20=R20,T20="нет"),"нет",AND(P20=R20,T20="да"),"да",AND(P20<>R20,T20="нет"),"да",AND(P20<>R20,T20="да"),"нет")} -> #N/A | R20: =VLOOKUP(B20,'Старый ИИ'!A:AQ,9,FALSE) -> Подтверждено | S20: =VLOOKUP(B20,'Старый ИИ'!A:AQ,11,FALSE) -> В отчете за 07‑20.10.2025 зафиксировано капитальное ремонт и модернизацию конкретного регионального театра (г. Тюмень, ул. Республики, 129) – установка видеонаблюдения, пожарной сигнализации, систем контроля доступа и др. (стр. 1, таблица «О стоимости выполненных работ и затрат»). Это подтверждает проведение модернизации театров в региональной собственности, но охватывает лишь один объект, без сведения о всей заявленной программe, поэтому подтверждение частичное. | T20: =VLOOKUP(B20,'Старый ИИ'!A:AQ,12,FALSE) -> да | U20: =VLOOKUP(B20,'Старый ИИ'!A:AQ,13,FALSE) -> да | V20: =VLOOKUP(B20,'Старый ИИ'!A:AQ,14,FALSE) -> - | W20: Не указан | X20: =VLOOKUP(B20,'Результат и ПХР'!$A$1:$Q$992,14,0) -> Для мероприятия ПХР не задан в исходных данных. Поэтому doc-level проверка ПХР не запускалась и документы по ПХР не анализировались. Итоговый статус ПХР установлен как "не указано". | Y20: =VLOOKUP(B20,'Результат и ПХР'!$A$1:$Q$992,7,0) -> не указано | Z20: да | AA20: =VLOOKUP(B20,'Старый ИИ'!A:AQ,21,FALSE) -> Не применимо | AB20: =VLOOKUP(B20,'Старый ИИ'!A:AQ,23,FALSE) -> Анализ ПХР пропущен: показатели ПХР не указаны для данного мероприятия | AC20: =VLOOKUP(B20,'Старый ИИ'!A:AQ,24,FALSE) -> да | AD20: =VLOOKUP(B20,'Старый ИИ'!A:AQ,25,FALSE) -> да | AE20: =VLOOKUP(B20,'Старый ИИ'!A:AQ,26,FALSE) -> - | AF20: =VLOOKUP(B20,Общий!$E$2:$O$2000,10,0) -> 10 | AG20: =VLOOKUP(B20,Общий!$E$2:$O$2000,11,0) -> Единица | AH20: =VLOOKUP(B20,'Результат и ПХР'!$A$1:$M$992,13,0) -> Основой вывода выбран ocr документа "€ªâ ® ¯à¨¥¬ª¥ ¢ë¯®«­¥­­ëå à ¡®â.pdf". В evidence найдены действие "Проведена модернизация театров", объект "находящихся в региональной и муниципальной собственности.", сигнал завершения "Работы приняты в полном объеме" и фактическое значение 0.46717524243 Условная единица (876). Ключевой фрагмент evidence: "Работы приняты в полном объеме". Сравнение результата определено как not_applicable, поэтому статус мероприятия установлен как "подтверждено". | AI20: =VLOOKUP(B20,'Результат и ПХР'!$A$1:$T$992,6,0) -> подтверждено | AJ20: да | AK20: =VLOOKUP(B20,'Старый ИИ'!A:AQ,27,FALSE) -> Подтверждено | AL20: =VLOOKUP(B20,'Старый ИИ'!A:AQ,29,FALSE) -> **1. Что удалось собрать:** - **Подтверждено плановое значение:** да (отчёт соответствует ключевым требованиям чек‑листа). - **Найдено фактическое значение:** да – в таблице стоимости работ указаны суммы за период, а в разделе «Итого» присутствуют «Сумма НДС» и «Всего с учётом НДС». - **Соответствует ли фактическое значение плановому:** не проверено явно в комментарии (нет сравнения с плановой цифрой). - **Краткие выводы по параметрам:** • Шапка формы присутствует. • Указаны все стороны (инвестор, заказчик, подрядчик). • Описаны объект и проект. • Приведены номер и дата договора. • Заполнена таблица «Номер документа, Дата составления, Отчётный период». • Таблица стоимости работ содержит все обязательные столбцы и итоговую сумму. • В разделе «Итого» указаны суммы НДС и общая сумма. • Присутствуют подписи и печати обеих сторон. **2. Что не удалось собрать:** - Отсутствует явное указание плановой величины и её сравнение с фактической (в комментарии не указано). - Пустые поля (коды ОКУД/ОКПО) не заполнены – отмечено как несущественное. **3. Общий статус:** - **Подтверждено выполнение планового значения:** частично (отчёт полностью соответствует чек‑листу, но сравнение фактических сумм с плановыми не продемонстрировано). - **Краткое резюме:** отчёт удовлетворяет всем обязательным требованиям формы и содержит необходимые финансовые данные, однако подтверждение соответствия фактических результатов плановым показателям требует отдельной проверки. | AM20: =VLOOKUP(B20,'Старый ИИ'!A:AQ,30,FALSE) -> да | AN20: =VLOOKUP(B20,'Старый ИИ'!A:AQ,31,FALSE) -> да | AO20: =VLOOKUP(B20,'Старый ИИ'!A:AQ,32,FALSE) -> -
A21: 9177987295 | B21: 9206750266 | C21: Проведена модернизация учреждений культурно-досугового типа в населенных пунктах с численностью до 500 тыс. чел. | D21: Проведение капитального ремонта региональных и муниципальных учреждений культурно-досугового типа в населенных пунктах до 500 тыс. чел. Всего 41 180 учреждений культурно-досугового типа, из них 7 770 в неудовлетворительном состоянии. К 2030 году будет отремонтировано 6% от зданий, требующих капитального ремонта, по отношению к 2022 году. Эффект для бенефициаров и вклад в достижение показателя: реализация мероприятия позволит создать комфортные условия гостей и жителей населенных пунктов, создает условия для посещения учреждений культуры. | E21: =VLOOKUP(B21,Подпись!$A$1:$E$100,5,0) -> #N/A | F21: =VLOOKUP(B21,Подпись!$A$1:$E$100,2,0) -> #N/A | G21: #N/A | H21: {=_xlfn.IFS(AND(G21=I21,K21="нет"),"нет",AND(G21=I21,K21="да"),"да",AND(G21<>I21,K21="нет"),"да",AND(G21<>I21,K21="да"),"нет")} -> #N/A | I21: =VLOOKUP(B21,'Старый ИИ'!A:AQ,3,FALSE) -> Подтверждено | J21: =VLOOKUP(B21,'Старый ИИ'!A:AQ,5,FALSE) -> Найдены следующие ответственные: Осинцев В.Г.. | K21: =VLOOKUP(B21,'Старый ИИ'!A:AQ,6,FALSE) -> #N/A | L21: =VLOOKUP(B21,'Старый ИИ'!A:AQ,7,FALSE) -> #N/A | M21: =VLOOKUP(B21,'Старый ИИ'!A:AQ,8,FALSE) -> #N/A | N21: Проведение капитального ремонта региональных и муниципальных учреждений культурно-досугового типа в населенных пунктах до 500 тыс. чел. Всего 41 180 учреждений культурно-досугового типа, из них 7 770 в неудовлетворительном состоянии. К 2030 году будет отремонтировано 6% от зданий, требующих капитального ремонта, по отношению к 2022 году. Эффект для бенефициаров и вклад в достижение показателя: реализация мероприятия позволит создать комфортные условия гостей и жителей населенных пунктов, создает условия для посещения учреждений культуры. | O21: =VLOOKUP(A21,Характеристика!$A$1:$D$100,2,0) -> #N/A | P21: =VLOOKUP(A21,Характеристика!$A$1:$D$100,4,0) -> #N/A | Q21: {=_xlfn.IFS(AND(P21=R21,T21="нет"),"нет",AND(P21=R21,T21="да"),"да",AND(P21<>R21,T21="нет"),"да",AND(P21<>R21,T21="да"),"нет")} -> #N/A | R21: =VLOOKUP(B21,'Старый ИИ'!A:AQ,9,FALSE) -> Не подтверждено | S21: =VLOOKUP(B21,'Старый ИИ'!A:AQ,11,FALSE) -> В приложенном источнике действительно описывается результат/мероприятие с тем же названием и общей логикой работ: речь про модернизацию учреждений культурно-досугового типа в населённых пунктах до 500 тыс. человек через капитальный ремонт, а также указан ожидаемый эффект в терминах создания условий для посещения учреждений культуры (в т.ч. для гостей и жителей) и приведены итоги за 2025 год (план 23, факт 24 объекта). Однако в источнике нет ключевых количественных параметров из вашего описания: “всего 41 180 учреждений, из них 7 770 в неудовлетворительном состоянии” и целевого ориентира “к 2030 году будет отремонтировано 6% от зданий… по отношению к 2022 году”. Поэтому подтвердить мероприятие именно “с таким описанием” по данному источнику нельзя. | T21: =VLOOKUP(B21,'Старый ИИ'!A:AQ,12,FALSE) -> #N/A | U21: =VLOOKUP(B21,'Старый ИИ'!A:AQ,13,FALSE) -> #N/A | V21: =VLOOKUP(B21,'Старый ИИ'!A:AQ,14,FALSE) -> #N/A | W21: Не указан | X21: =VLOOKUP(B21,'Результат и ПХР'!$A$1:$Q$992,14,0) -> Для мероприятия ПХР не задан в исходных данных. Поэтому doc-level проверка ПХР не запускалась и документы по ПХР не анализировались. Итоговый статус ПХР установлен как "не указано". | Y21: =VLOOKUP(B21,'Результат и ПХР'!$A$1:$Q$992,7,0) -> не указано | Z21: {=_xlfn.IFS(AND(Y21=AA21,AC21="нет"),"нет",AND(Y21=AA21,AC21="да"),"да",AND(Y21<>AA21,AC21="нет"),"да",AND(Y21<>AA21,AC21="да"),"нет")} -> #N/A | AA21: =VLOOKUP(B21,'Старый ИИ'!A:AQ,21,FALSE) -> Не применимо | AB21: =VLOOKUP(B21,'Старый ИИ'!A:AQ,23,FALSE) -> Анализ ПХР пропущен: показатели ПХР не указаны для данного мероприятия | AC21: =VLOOKUP(B21,'Старый ИИ'!A:AQ,24,FALSE) -> #N/A | AD21: =VLOOKUP(B21,'Старый ИИ'!A:AQ,25,FALSE) -> #N/A | AE21: =VLOOKUP(B21,'Старый ИИ'!A:AQ,26,FALSE) -> #N/A | AF21: =VLOOKUP(B21,Общий!$E$2:$O$2000,10,0) -> 22 | AG21: =VLOOKUP(B21,Общий!$E$2:$O$2000,11,0) -> Единица | AH21: =VLOOKUP(B21,'Результат и ПХР'!$A$1:$M$992,13,0) -> Основой вывода выбран ocr документа "€ªâ ¯à¨¥¬ª¨.jpeg". В evidence найдены действие "Выполнение работ по капитальному ремонту объекта капитального строительства в сфере культуры", объект "объекта капитального строительства в сфере культуры", сигнал завершения "Работы выполнены в полном объеме" и фактическое значение 1.00113407 Условная единица. Ключевой фрагмент evidence: "Выполнение работ по капитальному ремонту объекта капитального строительства в сфере культуры". Сравнение результата определено как below_target, поэтому статус мероприятия установлен как "подтверждено". | AI21: =VLOOKUP(B21,'Результат и ПХР'!$A$1:$T$992,6,0) -> не подтверждено | AJ21: #N/A | AK21: =VLOOKUP(B21,'Старый ИИ'!A:AQ,27,FALSE) -> Подтверждено | AL21: =VLOOKUP(B21,'Старый ИИ'!A:AQ,29,FALSE) -> В представленном отчёте «…по итогам 2025 года» прямо указано, что по состоянию на 31.12.2025 по результату «Проведена модернизация учреждений культурно-досугового типа… до 500 тыс. чел.» проведена модернизация 24 учреждений (при этом в тексте отдельно упомянуто плановое значение на 2025 год — 23 единицы). Следовательно, KPI 22 единицы в 2025 году достигнут и превышен (24 ≥ 22). | AM21: =VLOOKUP(B21,'Старый ИИ'!A:AQ,30,FALSE) -> #N/A | AN21: =VLOOKUP(B21,'Старый ИИ'!A:AQ,31,FALSE) -> #N/A | AO21: =VLOOKUP(B21,'Старый ИИ'!A:AQ,32,FALSE) -> #N/A
A22: 9191447902 | B22: 9206750231 | C22: Созданы памятные места, связанные с военной историей России | D22: Российским военно-историческим обществом на ежегодной основе реализуется мероприятие по установке памятных мест - мемориальные комплексы, монументы, скульптурные композиции, памятники-бюсты, кенотафы, обелиски, стелы, рельефы, мемориальные доски, арт-объекты и другие произведения монументально-декоративного искусства. Функция памятного места - сохранять от забвения определенную историческую информацию, представляющую ценность для сохранения национального самосознания. Значение результата к 2030 году: будет установлено 310 памятных мест (с 2019 по 2024 гг. будет установлено 174 памятных места (ежегодно не менее 27 ед.), в период 2025 - 2030 будет установлено 136 памятных мест (ежегодно не менее 20 ед.), что позволит удовлетворить потребность регионов РФ в установке памятных мест на территории субъектов на 80%. Эффект для бенефициаров и вклад в достижение показателя: Реализация мероприятий по расширению сети памятных мест является важным условием для воспитания патриотичной и социально ответственной личности, формирующейся на основе традиционных российских духовно-нравственных и культурно-исторических ценностей. Создание новых памятных мест и работа по поддержанию существующих способствует личностному развитию и патриотическому воспитанию молодых людей, а также обеспечивает продвижение и защиту традиционных российских духовно-нравственных ценностей. | E22: =VLOOKUP(B22,Подпись!$A$1:$E$100,5,0) -> #N/A | F22: =VLOOKUP(B22,Подпись!$A$1:$E$100,2,0) -> #N/A | G22: #N/A | H22: {=_xlfn.IFS(AND(G22=I22,K22="нет"),"нет",AND(G22=I22,K22="да"),"да",AND(G22<>I22,K22="нет"),"да",AND(G22<>I22,K22="да"),"нет")} -> #N/A | I22: =VLOOKUP(B22,'Старый ИИ'!A:AQ,3,FALSE) -> Не подтверждено | J22: =VLOOKUP(B22,'Старый ИИ'!A:AQ,5,FALSE) -> Найдены подписи: Дьякова ОГ, Громова ИИ, Коткин АВ, но они не совпадают с ответственными лицами | K22: =VLOOKUP(B22,'Старый ИИ'!A:AQ,6,FALSE) -> да | L22: =VLOOKUP(B22,'Старый ИИ'!A:AQ,7,FALSE) -> да | M22: =VLOOKUP(B22,'Старый ИИ'!A:AQ,8,FALSE) -> - | N22: Российским военно-историческим обществом на ежегодной основе реализуется мероприятие по установке памятных мест - мемориальные комплексы, монументы, скульптурные композиции, памятники-бюсты, кенотафы, обелиски, стелы, рельефы, мемориальные доски, арт-объекты и другие произведения монументально-декоративного искусства. Функция памятного места - сохранять от забвения определенную историческую информацию, представляющую ценность для сохранения национального самосознания. Значение результата к 2030 году: будет установлено 310 памятных мест (с 2019 по 2024 гг. будет установлено 174 памятных места (ежегодно не менее 27 ед.), в период 2025 - 2030 будет установлено 136 памятных мест (ежегодно не менее 20 ед.), что позволит удовлетворить потребность регионов РФ в установке памятных мест на территории субъектов на 80%. Эффект для бенефициаров и вклад в достижение показателя: Реализация мероприятий по расширению сети памятных мест является важным условием для воспитания патриотичной и социально ответственной личности, формирующейся на основе традиционных российских духовно-нравственных и культурно-исторических ценностей. Создание новых памятных мест и работа по поддержанию существующих способствует личностному развитию и патриотическому воспитанию молодых людей, а также обеспечивает продвижение и защиту традиционных российских духовно-нравственных ценностей. | O22: =VLOOKUP(A22,Характеристика!$A$1:$D$100,2,0) -> #N/A | P22: =VLOOKUP(A22,Характеристика!$A$1:$D$100,4,0) -> #N/A | Q22: {=_xlfn.IFS(AND(P22=R22,T22="нет"),"нет",AND(P22=R22,T22="да"),"да",AND(P22<>R22,T22="нет"),"да",AND(P22<>R22,T22="да"),"нет")} -> #N/A | R22: =VLOOKUP(B22,'Старый ИИ'!A:AQ,9,FALSE) -> Подтверждено | S22: =VLOOKUP(B22,'Старый ИИ'!A:AQ,11,FALSE) -> Отчет подтверждает выполнение мероприятия: в акте № 5 (стр. 1) указано, что исполнителем создано памятное место, посвящённое Защитникам Отечества и их матерям (три бронзовые фигуры на гранитном постаменте в Биробиджане). Это напрямую соответствует заявленному событию – созданию памятных мест, связанных с военной историей России. | T22: =VLOOKUP(B22,'Старый ИИ'!A:AQ,12,FALSE) -> да | U22: =VLOOKUP(B22,'Старый ИИ'!A:AQ,13,FALSE) -> да | V22: =VLOOKUP(B22,'Старый ИИ'!A:AQ,14,FALSE) -> - | W22: Не указан | X22: =VLOOKUP(B22,'Результат и ПХР'!$A$1:$Q$992,14,0) -> Для мероприятия ПХР не задан в исходных данных. Поэтому doc-level проверка ПХР не запускалась и документы по ПХР не анализировались. Итоговый статус ПХР установлен как "не указано". | Y22: =VLOOKUP(B22,'Результат и ПХР'!$A$1:$Q$992,7,0) -> не указано | Z22: да | AA22: =VLOOKUP(B22,'Старый ИИ'!A:AQ,21,FALSE) -> Не применимо | AB22: =VLOOKUP(B22,'Старый ИИ'!A:AQ,23,FALSE) -> Анализ ПХР пропущен: показатели ПХР не указаны для данного мероприятия | AC22: =VLOOKUP(B22,'Старый ИИ'!A:AQ,24,FALSE) -> да | AD22: =VLOOKUP(B22,'Старый ИИ'!A:AQ,25,FALSE) -> да | AE22: =VLOOKUP(B22,'Старый ИИ'!A:AQ,26,FALSE) -> - | AF22: =VLOOKUP(B22,Общий!$E$2:$O$2000,10,0) -> 199 | AG22: =VLOOKUP(B22,Общий!$E$2:$O$2000,11,0) -> Единица | AH22: =VLOOKUP(B22,'Результат и ПХР'!$A$1:$M$992,13,0) -> Основой вывода выбран ocr документа "АКТ 1 от 12.12.2025 ИП Мишов В.А..pdf". В evidence найдены действие "Созданы памятные места", объект "связанные с военной историей России", сигнал завершения "Заказчик принял выполненные Исполнителем" и фактическое значение 1 Единица. Ключевой фрагмент evidence: "Исполнитель сдал, а Заказчик принял выполненные Исполнителем, включающие в себя: ... доставку и монтаж (установку) скульптурной композиции на заранее подготовленное Заказчиком основание по адресу: Курская область, г. Курск, улица Ленина, 85". Сравнение результата определено как meets_target, поэтому статус мероприятия установлен как "подтверждено". | AI22: =VLOOKUP(B22,'Результат и ПХР'!$A$1:$T$992,6,0) -> подтверждено | AJ22: да | AK22: =VLOOKUP(B22,'Старый ИИ'!A:AQ,27,FALSE) -> Подтверждено | AL22: =VLOOKUP(B22,'Старый ИИ'!A:AQ,29,FALSE) -> **1. Что удалось собрать:** - **Подтверждено ли плановое значение:** да (все пункты чек‑листа присутствуют). - **Найдено ли фактическое значение в отчете:** да – на страницах 1‑3 указаны все требуемые сведения. - **Соответствует ли фактическое значение плановому:** полностью соответствует. **Краткие выводы по каждому параметру:** - **Идентификация акта (номер, дата):** найдено на странице 1, соответствует плану. - **Стороны договора:** указаны на странице 1, соответствует плану. - **Перечень выполненных работ:** присутствует на странице 1, соответствует плану. - **Технические характеристики работ:** указаны на странице 1, соответствует плану. - **Стоимость:** указана на странице 1, соответствует плану. - **Порядок налогообложения:** указан на странице 1, соответствует плану. - **Передача прав:** зафиксирована на странице 1, соответствует плану. - **Подписи сторон:** присутствуют на странице 1 и 2, соответствуют плану. - **Количество экземпляров акта:** указано на странице 2, соответствует плану. - **Приложение‑фотоотчёт:** присутствует на странице 3, соответствует плану. **2. Что не удалось собрать:** - Нет отсутствующих параметров; все требуемые элементы найдены и подтверждены. **3. Общий статус:** - **Подтверждено ли выполнение планового значения:** да. - **Краткое резюме:** В предоставленном фрагменте полностью реализованы все пункты чек‑листа, поэтому плановое значение выполнено в полной мере. | AM22: =VLOOKUP(B22,'Старый ИИ'!A:AQ,30,FALSE) -> да | AN22: =VLOOKUP(B22,'Старый ИИ'!A:AQ,31,FALSE) -> да | AO22: =VLOOKUP(B22,'Старый ИИ'!A:AQ,32,FALSE) -> -
A23: 9196225605 | B23: 9206750249 | C23: Созданы детские культурно-просветительские центры на базе учреждений культуры | D23: Создание на базе региональных и (или) муниципальных учреждений культуры (музеи, библиотеки, дома культуры) детских культурно-просветительских центров, которые включают в себя ремонтные работы, формирование современных пространств для организации культурно-просветительской деятельности детей. В среднем стоимость 1 центра - 4 млн рублей. Значение результата к 2030: с 2025 по 2030 гг. будет создано не менее 1 500 детских культурно-просветительских центров. Эффект для бенефициаров и вклад в достижение показателя: дети получат дополнительные общеразвивающие программы в сфере культуры и искусства, а их родители - возможность посещения различных мероприятий (занятий в студиях, досуговых объединениях, читальных залах и т.д.). | E23: =VLOOKUP(B23,Подпись!$A$1:$E$100,5,0) -> Алексеева Жанна Владимировна - Статс-секретарь - заместитель Министра культуры Российской Федерации, Любимова Ольга Борисовна, Обрывалин Сергей Геннадьевич, Алексеева Жанна Владимировна, Осинцев Владимир Геннадьевич, Малышев Андрей Владимирович, Першин Сергей Васильевич | F23: =VLOOKUP(B23,Подпись!$A$1:$E$100,2,0) -> Алексеева Жанна Владимировна, Ольга Борисовна | G23: Подтверждено | H23: {=_xlfn.IFS(AND(G23=I23,K23="нет"),"нет",AND(G23=I23,K23="да"),"да",AND(G23<>I23,K23="нет"),"да",AND(G23<>I23,K23="да"),"нет")} -> нет | I23: =VLOOKUP(B23,'Старый ИИ'!A:AQ,3,FALSE) -> Не подтверждено | J23: =VLOOKUP(B23,'Старый ИИ'!A:AQ,5,FALSE) -> Найдены подписи: Журавлев ИГ, Мартынова СЮ, Соболев ЮЮ, Карагодина НВ, Пуминов ДВ, Пронин ВА, Шматъко ВИ, Баженова ЛВ, Проворов ПМ, Преображен ПМ, но они не совпадают с ответственными лицами | K23: =VLOOKUP(B23,'Старый ИИ'!A:AQ,6,FALSE) -> да | L23: =VLOOKUP(B23,'Старый ИИ'!A:AQ,7,FALSE) -> да | M23: =VLOOKUP(B23,'Старый ИИ'!A:AQ,8,FALSE) -> - | N23: Создание на базе региональных и (или) муниципальных учреждений культуры (музеи, библиотеки, дома культуры) детских культурно-просветительских центров, которые включают в себя ремонтные работы, формирование современных пространств для организации культурно-просветительской деятельности детей. В среднем стоимость 1 центра - 4 млн рублей. Значение результата к 2030: с 2025 по 2030 гг. будет создано не менее 1 500 детских культурно-просветительских центров. Эффект для бенефициаров и вклад в достижение показателя: дети получат дополнительные общеразвивающие программы в сфере культуры и искусства, а их родители - возможность посещения различных мероприятий (занятий в студиях, досуговых объединениях, читальных залах и т.д.). | O23: =VLOOKUP(A23,Характеристика!$A$1:$D$100,2,0) -> #N/A | P23: =VLOOKUP(A23,Характеристика!$A$1:$D$100,4,0) -> #N/A | Q23: {=_xlfn.IFS(AND(P23=R23,T23="нет"),"нет",AND(P23=R23,T23="да"),"да",AND(P23<>R23,T23="нет"),"да",AND(P23<>R23,T23="да"),"нет")} -> #N/A | R23: =VLOOKUP(B23,'Старый ИИ'!A:AQ,9,FALSE) -> Подтверждено | S23: =VLOOKUP(B23,'Старый ИИ'!A:AQ,11,FALSE) -> В договоре №70/4/ЭА-2025 (стр. 1, п. 1.1) указано, что подрядчик обязуется выполнить работы по оформлению и оснащению помещений Музея кино с целью создания детского культурно-просветительского центра в рамках проекта «Семейные ценности и инфраструктура культуры». Это подтверждает реализацию мероприятия по созданию такого центра, хотя документ охватывает лишь один объект и фазу выполнения работ. | T23: =VLOOKUP(B23,'Старый ИИ'!A:AQ,12,FALSE) -> да | U23: =VLOOKUP(B23,'Старый ИИ'!A:AQ,13,FALSE) -> да | V23: =VLOOKUP(B23,'Старый ИИ'!A:AQ,14,FALSE) -> - | W23: Не указан | X23: =VLOOKUP(B23,'Результат и ПХР'!$A$1:$Q$992,14,0) -> Для мероприятия ПХР не задан в исходных данных. Поэтому doc-level проверка ПХР не запускалась и документы по ПХР не анализировались. Итоговый статус ПХР установлен как "не указано". | Y23: =VLOOKUP(B23,'Результат и ПХР'!$A$1:$Q$992,7,0) -> не указано | Z23: да | AA23: =VLOOKUP(B23,'Старый ИИ'!A:AQ,21,FALSE) -> Не применимо | AB23: =VLOOKUP(B23,'Старый ИИ'!A:AQ,23,FALSE) -> Анализ ПХР пропущен: показатели ПХР не указаны для данного мероприятия | AC23: =VLOOKUP(B23,'Старый ИИ'!A:AQ,24,FALSE) -> да | AD23: =VLOOKUP(B23,'Старый ИИ'!A:AQ,25,FALSE) -> да | AE23: =VLOOKUP(B23,'Старый ИИ'!A:AQ,26,FALSE) -> - | AF23: =VLOOKUP(B23,Общий!$E$2:$O$2000,10,0) -> 25 | AG23: =VLOOKUP(B23,Общий!$E$2:$O$2000,11,0) -> Единица | AH23: =VLOOKUP(B23,'Результат и ПХР'!$A$1:$M$992,13,0) -> Проверка опиралась на summary документа "10 Биэм Групп Интегратор ПП на сумму 345 000.pdf". В выбранном evidence не подтверждены следующие обязательные сигналы: действие, субъект, сигнал завершения, фактическое значение, единица измерения. Прямой подтверждающий фрагмент в evidence не найден. По правилу fail-closed статус мероприятия установлен как "не подтверждено". | AI23: =VLOOKUP(B23,'Результат и ПХР'!$A$1:$T$992,6,0) -> не подтверждено | AJ23: нет | AK23: =VLOOKUP(B23,'Старый ИИ'!A:AQ,27,FALSE) -> Подтверждено | AL23: =VLOOKUP(B23,'Старый ИИ'!A:AQ,29,FALSE) -> **1. Что удалось собрать:** - **Подтверждено ли плановое значение:** да. - **Найдено ли фактическое значение в отчете:** да (сумма 10 000 000 руб., указана как цифрами, так и прописью). - **Соответствует ли фактическое значение плановому:** да (значение полностью соответствует требуемому плановому показателю). - **Краткие выводы по каждому параметру:** • Номер платёжного поручения указан («ПЛАТЕЖНОЕ ПОРУЧЕНИЕ № 536848»). • Сумма указана прописью и цифрами («Десять миллионов рублей 00 копеек», «10 000 000‑00»). • Реквизиты плательщика (ГУ Банка России по ЦФО) и получателя (ООО «ГРАТА АДВ») присутствуют. • Банковские реквизиты обеих сторон (ИНН, КПП, BIK, счета) включены. • Описание цели платежа и ссылка на договор (контракт № 88‑Б‑25 от 20.06.25, документ о приёмке № 95 от 01.10.25). • Налоговые детали (НДС 1 666 666,67). • Подпись и отметка банка, фамилия ответственного лица (Борсиева Светлана Викторовна). • Дата операции – 09.10.2025. • Подтверждение наличия электронно‑подписанного документа и сведения о сертификате ЭП. **2. Что не удалось собрать:** - Параметров, не найденных или не подтверждённых, не обнаружено. **3. Общий статус:** - **Подтверждено ли выполнение планового значения:** да. - **Краткое резюме:** Представленный документ полностью удовлетворяет чек‑листу, подтверждая выполнение планового значения мероприятия. | AM23: =VLOOKUP(B23,'Старый ИИ'!A:AQ,30,FALSE) -> да | AN23: =VLOOKUP(B23,'Старый ИИ'!A:AQ,31,FALSE) -> нет | AO23: =VLOOKUP(B23,'Старый ИИ'!A:AQ,32,FALSE) -> Корректно по статусу. Но ИИ нашел некорректное значение и принял его как фактическое.
A24: 9317333761 | B24: 9317334852 | C24: Проведена научно-исследовательская работа в рамках определения технологии ликвидации НВОС БЦБК | D24: К концу 2025 года будет проведена научно-исследовательская работа на тему "Выбор оптимальных природоподобных технологий (технологических решений) для очистки, обезвреживания и рекультивации объекта накопленного вреда окружающей среде - полигон "Солзанский" ОАО "Байкальский целлюлозно-бумажный комбинат" | E24: =VLOOKUP(B24,Подпись!$A$1:$E$100,5,0) -> #N/A | F24: =VLOOKUP(B24,Подпись!$A$1:$E$100,2,0) -> #N/A | G24: #N/A | H24: {=_xlfn.IFS(AND(G24=I24,K24="нет"),"нет",AND(G24=I24,K24="да"),"да",AND(G24<>I24,K24="нет"),"да",AND(G24<>I24,K24="да"),"нет")} -> #N/A | I24: =VLOOKUP(B24,'Старый ИИ'!A:AQ,3,FALSE) -> Не подтверждено | J24: =VLOOKUP(B24,'Старый ИИ'!A:AQ,5,FALSE) -> Найдены подписи: С.С. Карлов, И.В. Перминова, Перминова ИВ, Ларионов КС, Алешкевич-Суслов ЯВ, Болотник ТА, Владимиров СА, Волков ДС, Гаджибагомедов ПА, Гусманов ТТ, Ефременко ЕН, Жиркова АМ, Зайцев КВ, Зейнетдинова ГР, М.В. Котова, В.А. Кудакина, Н.А. Куликова, Е.Г. Куст, А.А. Николаева, А.В. Николаева, К.В. Петров, П.А. Раджабзода, А.В. Растрогуев, О.В. Сенько, А.Д. Смоленков, Н.А. Степанов, М.О. Трубников, О.И. Филиппова, А.Н. Хрептугова, И.В. Черняк, К.Д. Шестаков, А.В. Верхоэина, Н.В. Дорофеев, Ю.А. Маркова, А.В. Поморцев, М.С. Карепова, А.С. Миронова, Е.С. Преловская, И.В. Бычков, П.К. Фёдоров, А.Е. Хмельнов, А.С. Гаченко, Ю.В. Авраменко, Е.С. Фереферов, А.П. Виноградова, Кондратьев В.В., Будяк А.Е., Тарасова Ю.И., Брюханова Н.Н., Петровский А.А., А.В. Перепёлов, А.И. Березовская, Петухов А.А., А.Б. Перепелов, Куликова Н.А., Михеев И.В., В.И. Воронин, А.В. Верхозина, Р.К. Фёдоров, Перепелов А.Б., но они не совпадают с ответственными лицами | K24: =VLOOKUP(B24,'Старый ИИ'!A:AQ,6,FALSE) -> да | L24: =VLOOKUP(B24,'Старый ИИ'!A:AQ,7,FALSE) -> да | M24: =VLOOKUP(B24,'Старый ИИ'!A:AQ,8,FALSE) -> - | N24: К концу 2025 года будет проведена научно-исследовательская работа на тему "Выбор оптимальных природоподобных технологий (технологических решений) для очистки, обезвреживания и рекультивации объекта накопленного вреда окружающей среде - полигон "Солзанский" ОАО "Байкальский целлюлозно-бумажный комбинат" | O24: =VLOOKUP(A24,Характеристика!$A$1:$D$100,2,0) -> #N/A | P24: =VLOOKUP(A24,Характеристика!$A$1:$D$100,4,0) -> #N/A | Q24: {=_xlfn.IFS(AND(P24=R24,T24="нет"),"нет",AND(P24=R24,T24="да"),"да",AND(P24<>R24,T24="нет"),"да",AND(P24<>R24,T24="да"),"нет")} -> #N/A | R24: =VLOOKUP(B24,'Старый ИИ'!A:AQ,9,FALSE) -> Не выполнено | S24: =VLOOKUP(B24,'Старый ИИ'!A:AQ,11,FALSE) -> 0 | T24: =VLOOKUP(B24,'Старый ИИ'!A:AQ,12,FALSE) -> да | U24: =VLOOKUP(B24,'Старый ИИ'!A:AQ,13,FALSE) -> да | V24: =VLOOKUP(B24,'Старый ИИ'!A:AQ,14,FALSE) -> - | W24: =VLOOKUP(B24,'ПХР актуальный'!$A$1:$C$34,3,0) -> #NUM! | X24: =VLOOKUP(B24,'Результат и ПХР'!$A$1:$Q$992,14,0) -> #N/A | Y24: =VLOOKUP(B24,'Результат и ПХР'!$A$1:$Q$992,7,0) -> #N/A | Z24: {=_xlfn.IFS(AND(Y24=AA24,AC24="нет"),"нет",AND(Y24=AA24,AC24="да"),"да",AND(Y24<>AA24,AC24="нет"),"да",AND(Y24<>AA24,AC24="да"),"нет")} -> #N/A | AA24: =VLOOKUP(B24,'Старый ИИ'!A:AQ,21,FALSE) -> Не выполнено | AB24: =VLOOKUP(B24,'Старый ИИ'!A:AQ,23,FALSE) -> 0 | AC24: =VLOOKUP(B24,'Старый ИИ'!A:AQ,24,FALSE) -> да | AD24: =VLOOKUP(B24,'Старый ИИ'!A:AQ,25,FALSE) -> да | AE24: =VLOOKUP(B24,'Старый ИИ'!A:AQ,26,FALSE) -> - | AF24: =VLOOKUP(B24,Общий!$E$2:$O$2000,10,0) -> 1 | AG24: =VLOOKUP(B24,Общий!$E$2:$O$2000,11,0) -> Единица | AH24: =VLOOKUP(B24,'Результат и ПХР'!$A$1:$M$992,13,0) -> #N/A | AI24: =VLOOKUP(B24,'Результат и ПХР'!$A$1:$T$992,6,0) -> #N/A | AJ24: #N/A | AK24: =VLOOKUP(B24,'Старый ИИ'!A:AQ,27,FALSE) -> Не выполнено | AL24: =VLOOKUP(B24,'Старый ИИ'!A:AQ,29,FALSE) -> 0 | AM24: =VLOOKUP(B24,'Старый ИИ'!A:AQ,30,FALSE) -> да | AN24: =VLOOKUP(B24,'Старый ИИ'!A:AQ,31,FALSE) -> да | AO24: =VLOOKUP(B24,'Старый ИИ'!A:AQ,32,FALSE) -> -
